Workbook
Name IQ_CH: 110000
Name IQ_CQ: 5000
Name IQ_CY: 10000
Name IQ_DAILY: 500000
Name IQ_FH: 100000
Name IQ_FQ: 500
Name IQ_FY: 1000
Name IQ_LTM: 2000
Name IQ_MONTH: 15000
Name IQ_NTM: 6000
Name IQ_WEEK: 50000
Name IQ_YTD: 3000

Sheet Input Sheet
B3: Please Provide the below Inputs
B5: Name of the Company | C5: Marico Ltd
B7: WACC Inputs
B8: Country | C8: India
B9: Local Currency 10Y Government Yield | C9: 0.0651
B10: =C8&"'s"&" Moodys Sovereign Rating" -> India's Moodys Sovereign Rating | C10: =VLOOKUP(C8,'Damodaran Data'!B4:D161,3,FALSE) -> Baa3
B11: Credit Default spread as per Dr Damodaran | C11: =VLOOKUP(C8,'Damodaran Data'!B4:E161,4,) -> 0.021609858
B12: Implied US Equity Risk Premium | C12: 0.0373
B13: Asset Beta | C13: 0.45
B14: Asset Beta Variation (+/-) | C14: 0.05
B15: Debt to Equity Ratio | C15: ='Assumptions Working '!I659 -> 0.095345912
B16: Debt to Capital (Gearing) | C16: ='Assumptions Working '!I660 -> 0.081593111 | Z16: Large | AB16: Yes
B17: Marginal Tax Rate | C17: 0.2512 | Z17: Small | AB17: No
B18: Company Credit Rating Available? | C18: Yes
B19: Company is Large Firm or Small Firm | C19: Large
B20: Provide Credit Rating | C20: Aaa/AAA
B21: Interest Coverage Ratio | C21: ='3 Statement Model'!N47 -> 50.047842
B22: ICR Based Corporate Default Spread | C22: =IF(C19="Largr",VLOOKUP(C21,'Damodaran Data'!G6:J21,4,TRUE),VLOOKUP('Input Sheet'!C21,'Damodaran Data'!L6:O21,4,TRUE)) -> 0.0045
B23: Small Size Premium | C23: 0.026

Sheet WACC
B2: ='Input Sheet'!C5 -> Marico Ltd
B3: Weighted Average Cost of Capital
B5: Particulars | D5: Low | E5: Mid | F5: High | H5: Risk Free Rate
B7: Risk Free Rate | D7: ='Input Sheet'!C9-'Input Sheet'!C11 -> 0.043490142 | E7: =D7 -> 0.043490142 | F7: =E7 -> 0.043490142 | H7: ="We have considered "&TEXT(E7,"0.00%")&" as the risk free rate in estimation of cost of equity of "&TEXT(E12,"0.00%")&". The risk free rate of India is calculated by considering local currency 10 years government bond yield adjusted for default spread of India." -> We have considered 4.35% as the risk free rate in estimation of cost of equity of 7.19%. The risk free rate of India is calculated by considering local currency 10 years government bond yield adjusted for default spread of India.
B8: Equity Risk Premium | D8: ='Input Sheet'!C12+'Input Sheet'!C11 -> 0.058909858 | E8: =D8 -> 0.058909858 | F8: =E8 -> 0.058909858
B9: Asset Beta | D9: =E9-'Input Sheet'!C14 -> 0.4 | E9: ='Input Sheet'!C13 -> 0.45 | F9: =E9+'Input Sheet'!C14 -> 0.5
B10: D/E Ratio | D10: ='Input Sheet'!C15 -> 0.095345912 | E10: =D10 -> 0.095345912 | F10: =E10 -> 0.095345912
B11: Equity Beta | D11: =D9*(1+(D10*(1-'Input Sheet'!$C$17))) -> 0.42855801 | E11: =E9*(1+(E10*(1-'Input Sheet'!$C$17))) -> 0.48212776 | F11: =F9*(1+(F10*(1-'Input Sheet'!$C$17))) -> 0.53569751
B12: CAMP Cost of Equity | D12: =D7+(D8*D11) -> 0.068736433 | E12: =E7+(E8*E11) -> 0.07189222 | F12: =F7+(F8*F11) -> 0.075048006 | H12: Asset Beta
H13: ="We have estimated an asset beta range of "&TEXT(D9,"0.00")&" to "&TEXT(F9,"0.00")&", with a mid point of "&TEXT(E9,"0.00")&" based on observed median of 5 year monthly asset beta of benchmark listed companies adjusted for blume effect." -> We have estimated an asset beta range of 0.40 to 0.50, with a mid point of 0.45 based on observed median of 5 year monthly asset beta of benchmark listed companies adjusted for blume effect.
B14: Small Size Premium | D14: ='Input Sheet'!C23 -> 0.026 | E14: =D14 -> 0.026 | F14: =E14 -> 0.026
B15: Asset Specific Premium | D15: 0 | E15: =D15 -> 0 | F15: =E15 -> 0
B16: Modified Cost of Equity | D16: =D12+D14+D15 -> 0.094736433 | E16: =E12+E14+E15 -> 0.09789222 | F16: =F12+F14+F15 -> 0.10104801
H17: Equity Risk Premium (ERP)
B18: Pre Tax Cost of Debt | D18: ='Input Sheet'!C9+(IF('Input Sheet'!C18="No",'Input Sheet'!C22,VLOOKUP('Input Sheet'!C20,'Damodaran Data'!I7:J21,2,FALSE))) -> 0.0696 | E18: =D18 -> 0.0696 | F18: =E18 -> 0.0696 | H18: ="An ERP of "&TEXT(E8,"0.00%") &" has been adopted based on US implied equity risk premium, relative equity volatiliy of ICE BofA Public Sector Issues Emerging Mkts Index, S&P Emerging BMI Index and country risk premium of India." -> An ERP of 5.89% has been adopted based on US implied equity risk premium, relative equity volatiliy of ICE BofA Public Sector Issues Emerging Mkts Index, S&P Emerging BMI Index and country risk premium of India.
B19: Marginal Tax Rate | D19: ='Input Sheet'!C17 -> 0.2512 | E19: =D19 -> 0.2512 | F19: =E19 -> 0.2512
B20: Post Tax Cost of Debt | D20: =D18*(1-D19) -> 0.05211648 | E20: =E18*(1-E19) -> 0.05211648 | F20: =F18*(1-F19) -> 0.05211648
B22: Capital Gearing (D/D+E) | D22: ='Input Sheet'!C16 -> 0.081593111 | E22: =D22 -> 0.081593111 | F22: =E22 -> 0.081593111 | H22: Cost of Debt
B23: Weighted Average Cost of Capital | D23: =(D20*D22)+(D16*(1-D22)) -> 0.091258939 | E23: =(E20*E22)+(E16*(1-E22)) -> 0.094157235 | F23: =(F20*F22)+(F16*(1-F22)) -> 0.097055531 | H23: For the purpose of assessing the cost of debt, we have used country's risk free rate, country's default spread and corporate default spread based on company's debt rating and interest coverage ratio
B24: Weighted Average Cost of Capital (Rounded) | D24: =ROUNDUP(D23,2) -> 0.1 | E24: =ROUNDUP(E23,2) -> 0.1 | F24: =ROUNDUP(F23,2) -> 0.1
B26: 1. Tax rate is considered as Marginal Tax Rate of India
B27: 2. Asset Beta is considered as median of 5 years beta of comps adjusted for blume afeect
B28: 3. Equity Beta = Asset Beta * (1+(1-Tax Rate%)*(Debt/Equity) | H28: Small Size Premium & Asset Specific Premium
H29: Emperically small size assets have exceeded the returns as compared to large sized asset. We have used the study on size premium conducted by Incwert which is based on difference between actual return and CAPM expected returns arranged in decile basis market capitalization of Indian companies.
B40: =B2 -> Marico Ltd
B41: Beta Analysis - 2 Years Weekly
B44: Comparable Company | D44: Ticker | E44: No.of Weekly Observations | F44: Market Cap (Cr) | G44: Asset Beta | H44: 2 Years avg D/E | I44: Equity Beta | J44: 2 Years avg D/D+E | L44: Considered ?
B46: Dabur India | D46: NSE: DABUR | E46: 104 | F46: 91,904 | G46: =I46/(1+(H46*(1-'Input Sheet'!$C$17))) -> 0.61445013 | H46: ='Cal Sheet'!C53 -> 0.092479565 | I46: 0.657 | J46: ='Cal Sheet'!E53 -> 0.084175573 | L46: Yes
B47: Hindustan Unilever | D47: NSE: HINDUNILVR | E47: 104 | F47: 569870 | G47: =I47/(1+(H47*(1-'Input Sheet'!$C$17))) -> 0.38796019 | H47: ='Cal Sheet'!C54 -> 0.00013702956 | I47: 0.388 | J47: ='Cal Sheet'!E54 -> 0.00013699715 | L47: Yes
B48: Sundrop Brands Ltd | D48: NSE: SUNDROP | E48: 104 | F48: 2857 | G48: =I48/(1+(H48*(1-'Input Sheet'!$C$17))) -> 0.44874336 | H48: ='Cal Sheet'!C55 -> 0.0335 | I48: 0.46 | J48: ='Cal Sheet'!E55 -> 0.031396439 | L48: No
B49: Gokul Agro Resources Ltd | D49: NSE: GOKULAGRO | E49: 104 | F49: 6071 | G49: =I49/(1+(H49*(1-'Input Sheet'!$C$17))) -> 0.87049777 | H49: ='Cal Sheet'!C56 -> 0.62823592 | I49: 1.28 | J49: ='Cal Sheet'!E56 -> 0.38256343 | L49: No
B50: Godrej Consumer Products Ltd | D50: NSE: GODREJCP | E50: 104 | F50: 118072 | G50: =I50/(1+(H50*(1-'Input Sheet'!$C$17))) -> 0.43543924 | H50: ='Cal Sheet'!C57 -> 0.2869461 | I50: 0.529 | J50: ='Cal Sheet'!E57 -> 0.22234014 | L50: Yes
B51: Britannia Industries Ltd | D51: NSE: BRITANNIA | E51: 104 | F51: 141739 | G51: =I51/(1+(H51*(1-'Input Sheet'!$C$17))) -> 0.36254819 | H51: ='Cal Sheet'!C58 -> 0.39948939 | I51: 0.471 | J51: ='Cal Sheet'!E58 -> 0.28031396 | L51: No
B52: Emami Ltd | D52: NSE: EMAMILTD | E52: 104 | F52: 22475 | G52: =I52/(1+(H52*(1-'Input Sheet'!$C$17))) -> 0.66754095 | H52: ='Cal Sheet'!C59 -> 0.024925341 | I52: 0.68 | J52: ='Cal Sheet'!E59 -> 0.024315754 | L52: Yes
B53: Bajaj Consumer Care Ltd | D53: NSE: BAJAJCON | E53: 104 | F53: 3665 | G53: =I53/(1+(H53*(1-'Input Sheet'!$C$17))) -> 0.827 | H53: ='Cal Sheet'!C60 -> 0 | I53: 0.827 | J53: ='Cal Sheet'!E60 -> 0 | L53: Yes
B55: Median - Broad Set | G55: =MEDIAN(G46:G53) -> 0.53159675 | H55: =MEDIAN(H46:H53) -> 0.062989783 | I55: =MEDIAN(I46:I53) -> 0.593 | J55: =MEDIAN(J46:J53) -> 0.057786006
B56: Average - Broad Set | G56: =AVERAGE(G46:G53) -> 0.57677248 | H56: =AVERAGE(H46:H53) -> 0.18321417 | I56: =AVERAGE(I46:I53) -> 0.6615 | J56: =AVERAGE(J46:J53) -> 0.12815529
B58: Median - Considered Set | G58: =MEDIAN(G46,G47,G50,G52:G53) -> 0.61445013 | H58: =MEDIAN(H46,H47,H50,H52:H53) -> 0.024925341 | I58: =MEDIAN(I46,I47,I50,I52:I53) -> 0.657 | J58: =MEDIAN(J46,J47,J50,J52:J53) -> 0.024315754
B59: Average - Considered Set | G59: =AVERAGE(G46:G47,G52:G53,G50) -> 0.5864781 | H59: =AVERAGE(H46:H47,H52:H53,H50) -> 0.080897608 | I59: =AVERAGE(I46:I47,I52:I53,I50) -> 0.6162 | J59: =AVERAGE(J46:J47,J52:J53,J50) -> 0.066193692
B63: Beta Analysis - 5 Years Monthly
B65: Comparable Company | D65: Ticker | E65: No.of Weekly Observations | F65: Market Cap (Cr) | G65: Asset Beta | H65: 5 Years avg D/E | I65: Equity Beta | J65: 5 Years avg D/D+E | L65: Considered ?
B67: Dabur India | D67: NSE: DABUR | E67: 60 | F67: 91,904 | G67: =I67/(1+(H67*(1-'Input Sheet'!$C$17))) -> 0.23436276 | H67: ='Cal Sheet'!D53 -> 0.089105757 | I67: 0.25 | J67: ='Cal Sheet'!F53 -> 0.081210641 | L67: Yes
B68: Hindustan Unilever | D68: NSE: HINDUNILVR | E68: 60 | F68: 569870 | G68: =I68/(1+(H68*(1-'Input Sheet'!$C$17))) -> 0.31989354 | H68: ='Cal Sheet'!D54 -> 0.00044444287 | I68: 0.32 | J68: ='Cal Sheet'!F54 -> 0.00044367232 | L68: Yes
B69: Sundrop Brands Ltd | D69: NSE: SUNDROP | E69: 60 | F69: 2857 | G69: =I69/(1+(H69*(1-'Input Sheet'!$C$17))) -> 0.39478589 | H69: ='Cal Sheet'!D55 -> 0.051465844 | I69: 0.41 | J69: ='Cal Sheet'!F55 -> 0.047274046 | L69: No
B70: Gokul Agro Resources Ltd | D70: NSE: GOKULAGRO | E70: 60 | F70: 6071 | G70: =I70/(1+(H70*(1-'Input Sheet'!$C$17))) -> 0.1362404 | H70: ='Cal Sheet'!D56 -> 0.62499105 | I70: 0.2 | J70: ='Cal Sheet'!F56 -> 0.38253157 | L70: No
B71: Godrej Consumer Products Ltd | D71: NSE: GODREJCP | E71: 60 | F71: 118072 | G71: =I71/(1+(H71*(1-'Input Sheet'!$C$17))) -> 0.20068718 | H71: ='Cal Sheet'!D57 -> 0.19506176 | I71: 0.23 | J71: ='Cal Sheet'!F57 -> 0.15886461 | L71: Yes
B72: Britannia Industries Ltd | D72: NSE: BRITANNIA | E72: 60 | F72: 141739 | G72: =I72/(1+(H72*(1-'Input Sheet'!$C$17))) -> 0.3583106 | H72: ='Cal Sheet'!D58 -> 0.63990869 | I72: 0.53 | J72: ='Cal Sheet'!F58 -> 0.37625779 | L72: No
B73: Emami Ltd | D73: NSE: EMAMILTD | E73: 60 | F73: 22475 | G73: =I73/(1+(H73*(1-'Input Sheet'!$C$17))) -> 0.048118786 | H73: ='Cal Sheet'!D59 -> 0.052210494 | I73: 0.05 | J73: ='Cal Sheet'!F59 -> 0.048385218 | L73: Yes
B74: Bajaj Consumer Care Ltd | D74: NSE: BAJAJCON | E74: 60 | F74: 3665 | G74: =I74/(1+(H74*(1-'Input Sheet'!$C$17))) -> 0.33966402 | H74: ='Cal Sheet'!D60 -> 0.001321004 | I74: 0.34 | J74: ='Cal Sheet'!F60 -> 0.001312336 | L74: Yes
B76: Median - Broad Set | G76: =MEDIAN(G67:G74) -> 0.27712815 | H76: =MEDIAN(H67:H74) -> 0.070658126 | I76: =MEDIAN(I67:I74) -> 0.285 | J76: =MEDIAN(J67:J74) -> 0.06479793
B77: Average - Broad Set | G77: =AVERAGE(G67:G74) -> 0.2540079 | H77: =AVERAGE(H67:H74) -> 0.20681363 | I77: =AVERAGE(I67:I74) -> 0.29125 | J77: =AVERAGE(J67:J74) -> 0.13703499
B79: Median - Considered Set | G79: =MEDIAN(G73:G74,G71,G67:G68) -> 0.23436276 | H79: =MEDIAN(H73:H74,H71,H67:H68) -> 0.052210494 | I79: =MEDIAN(I73:I74,I71,I67:I68) -> 0.25 | J79: =MEDIAN(J73:J74,J71,J67:J68) -> 0.048385218
B80: Average - Considered Set | G80: =AVERAGE(G73:G74,G71,G67:G68) -> 0.22854526 | H80: =AVERAGE(H73:H74,H71,H67:H68) -> 0.067628692 | I80: =AVERAGE(I73:I74,I71,I67:I68) -> 0.238 | J80: =AVERAGE(J73:J74,J71,J67:J68) -> 0.058043296
B84: Blume Beta Analysis - 5 Years Monthly
B86: Comparable Company | D86: Ticker | E86: No.of Weekly Observations | F86: Market Cap (Cr) | G86: Asset Beta | H86: 5 Years avg D/E | I86: Equity Beta | J86: 5 Years avg D/D+E | L86: Considered ?
B88: Dabur India | D88: NSE: DABUR | E88: 60 | F88: 91,904 | G88: =I88/(1+(H88*(1-'Input Sheet'!$C$17))) -> 0.45771046 | H88: 0.089105757 | I88: =0.33+0.633*I67 -> 0.48825 | J88: ='Cal Sheet'!F74 -> 0 | L88: Yes
B89: Hindustan Unilever | D89: NSE: HINDUNILVR | E89: 60 | F89: 569870 | G89: =I89/(1+(H89*(1-'Input Sheet'!$C$17))) -> 0.53238282 | H89: 0.00044444287 | I89: =0.33+0.633*I68 -> 0.53256 | J89: ='Cal Sheet'!F75 -> 0 | L89: Yes
B90: Sundrop Brands Ltd | D90: NSE: SUNDROP | E90: 60 | F90: 2857 | G90: =I90/(1+(H90*(1-'Input Sheet'!$C$17))) -> 0.56765397 | H90: 0.051465844 | I90: =0.33+0.633*I69 -> 0.58953 | J90: ='Cal Sheet'!F76 -> 0 | L90: No
B91: Gokul Agro Resources Ltd | D91: NSE: GOKULAGRO | E91: 60 | F91: 6071 | G91: =I91/(1+(H91*(1-'Input Sheet'!$C$17))) -> 0.31103684 | H91: 0.62499105 | I91: =0.33+0.633*I70 -> 0.4566 | J91: ='Cal Sheet'!F77 -> 0 | L91: No
B92: Godrej Consumer Products Ltd | D92: NSE: GODREJCP | E92: 60 | F92: 118072 | G92: =I92/(1+(H92*(1-'Input Sheet'!$C$17))) -> 0.41497746 | H92: 0.19506176 | I92: =0.33+0.633*I71 -> 0.47559 | J92: ='Cal Sheet'!F78 -> 0 | L92: Yes
B93: Britannia Industries Ltd | D93: NSE: BRITANNIA | E93: 60 | F93: 141739 | G93: =I93/(1+(H93*(1-'Input Sheet'!$C$17))) -> 0.44990966 | H93: 0.63990869 | I93: =0.33+0.633*I72 -> 0.66549 | J93: ='Cal Sheet'!F79 -> 0 | L93: No
B94: Emami Ltd | D94: NSE: EMAMILTD | E94: 60 | F94: 22475 | G94: =I94/(1+(H94*(1-'Input Sheet'!$C$17))) -> 0.34804318 | H94: 0.052210494 | I94: =0.33+0.633*I73 -> 0.36165 | J94: ='Cal Sheet'!F80 -> 0 | L94: Yes
B95: Bajaj Consumer Care Ltd | D95: NSE: BAJAJCON | E95: 60 | F95: 3665 | G95: =I95/(1+(H95*(1-'Input Sheet'!$C$17))) -> 0.54468122 | H95: 0.001321004 | I95: =0.33+0.633*I74 -> 0.54522 | J95: ='Cal Sheet'!F81 -> 0 | L95: Yes
B97: Median - Broad Set | G97: =MEDIAN(G88:G95) -> 0.45381006 | H97: =MEDIAN(H88:H95) -> 0.070658126 | I97: =MEDIAN(I88:I95) -> 0.510405 | J97: =MEDIAN(J88:J95) -> 0
B98: Average - Broad Set | G98: =AVERAGE(G88:G95) -> 0.45329945 | H98: =AVERAGE(H88:H95) -> 0.20681363 | I98: =AVERAGE(I88:I95) -> 0.51436125 | J98: =AVERAGE(J88:J95) -> 0
B100: Median - Considered Set | G100: =MEDIAN(G94:G95,G92,G88:G89) -> 0.45771046 | H100: =MEDIAN(H94:H95,H92,H88:H89) -> 0.052210494 | I100: =MEDIAN(I94:I95,I92,I88:I89) -> 0.48825 | J100: =MEDIAN(J94:J95,J92,J88:J89) -> 0
B101: Average - Considered Set | G101: =AVERAGE(G94:G95,G92,G88:G89) -> 0.45955903 | H101: =AVERAGE(H94:H95,H92,H88:H89) -> 0.067628692 | I101: =AVERAGE(I94:I95,I92,I88:I89) -> 0.480654 | J101: =AVERAGE(J94:J95,J92,J88:J89) -> 0
B104: We are taking 0.45 as asset beta of FMCG Company

Sheet Damodaran Data
B3: Country Data | G3: Company Data
B4: Country | C4: Africa | D4: Moody's rating | E4: Rating-based Default Spread | G4: For large non-financial service firms | L4: For smaller and riskier firms
B5: India | C5: Asia | D5: Baa3 | E5: 0.021609858 | G5: If interest coverage ratio is | L5: If interest coverage ratio is
B6: United Kingdom | C6: Western Europe | D6: Aa3 | E6: 0.0058935977 | G6: > | H6: ≤ to | I6: Rating is | J6: Spread is | L6: greater than | M6: ≤ to | N6: Rating is | O6: Spread is
B7: United States | C7: North America | D7: Aa1 | E7: 0.0027 | G7: -100000 | H7: 0.199999 | I7: D2/D | J7: 0.19 | L7: -100000 | M7: 0.499999 | N7: D2/D | O7: 0.19
B8: Abu Dhabi | C8: Middle East | D8: Aa2 | E8: 0.004853551 | G8: 0.2 | H8: 0.649999 | I8: C2/C | J8: 0.155 | L8: 0.5 | M8: 0.799999 | N8: C2/C | O8: 0.155
B9: Albania | C9: Eastern Europe & Russia | D9: Ba3 | E9: 0.035361586 | G9: 0.65 | H9: 0.799999 | I9: Ca2/CC | J9: 0.101 | L9: 0.8 | M9: 1.249999 | N9: Ca2/CC | O9: 0.101
B10: Andorra (Principality of) | C10: Western Europe | D10: Baa1 | E10: 0.015716261 | G10: 0.8 | H10: 1.249999 | I10: Caa/CCC | J10: 0.0728 | L10: 1.25 | M10: 1.499999 | N10: Caa/CCC | O10: 0.0728
B11: Angola | C11: Africa | D11: B3 | E11: 0.063905089 | G11: 1.25 | H11: 1.499999 | I11: B3/B- | J11: 0.0442 | L11: 1.5 | M11: 1.999999 | N11: B3/B- | O11: 0.0442
B12: Argentina | C12: Central and South America | D12: Caa3 | E12: 0.098342189 | G12: 1.5 | H12: 1.749999 | I12: B2/B | J12: 0.03 | L12: 2 | M12: 2.499999 | N12: B2/B | O12: 0.03
B13: Armenia | C13: Eastern Europe & Russia | D13: Ba3 | E13: 0.035361586 | G13: 1.75 | H13: 1.999999 | I13: B1/B+ | J13: 0.0261 | L13: 2.5 | M13: 2.999999 | N13: B1/B+ | O13: 0.0261
B14: Aruba | C14: Caribbean | D14: Baa3 | E14: 0.021609858 | G14: 2 | H14: 2.2499999 | I14: Ba2/BB | J14: 0.0183 | L14: 3 | M14: 3.499999 | N14: Ba2/BB | O14: 0.0183
B15: Australia | C15: Australia & New Zealand | D15: Aaa | E15: 0 | G15: 2.25 | H15: 2.49999 | I15: Ba1/BB+ | J15: 0.0155 | L15: 3.5 | M15: 3.9999999 | N15: Ba1/BB+ | O15: 0.0155
B16: Austria | C16: Western Europe | D16: Aa1 | E16: 0.0027 | G16: 2.5 | H16: 2.999999 | I16: Baa2/BBB | J16: 0.012 | L16: 4 | M16: 4.499999 | N16: Baa2/BBB | O16: 0.012
B17: Azerbaijan | C17: Eastern Europe & Russia | D17: Baa3 | E17: 0.021609858 | G17: 3 | H17: 4.249999 | I17: A3/A- | J17: 0.0095 | L17: 4.5 | M17: 5.999999 | N17: A3/A- | O17: 0.0095
B18: Bahamas | C18: Caribbean | D18: B1 | E18: 0.044259763 | G18: 4.25 | H18: 5.499999 | I18: A2/A | J18: 0.0085 | L18: 6 | M18: 7.499999 | N18: A2/A | O18: 0.0085
... B21: Barbados | C21: Caribbean | D21: B2 | E21: 0.054082426 | G21: 8.5 | H21: 100000 | I21: Aaa/AAA | J21: 0.0045 | L21: 12.5 | M21: 100000 | N21: Aaa/AAA | O21: 0.0045
B22: Belarus | C22: Eastern Europe & Russia | D22: C | E22: 0.175
B23: Belgium | C23: Western Europe | D23: Aa3 | E23: 0.0058935977
B24: Belize | C24: Central and South America | D24: Caa1 | E24: 0.073727752
B25: Benin | C25: Africa | D25: B1 | E25: 0.044259763
B26: Bermuda | C26: Caribbean | D26: A2 | E26: 0.0083203732
B27: Bolivia | C27: Central and South America | D27: Ca | E27: 0.11798751
B28: Bosnia and Herzegovina | C28: Eastern Europe & Russia | D28: B3 | E28: 0.063905089
B29: Botswana | C29: Africa | D29: A3 | E29: 0.011787195
B30: Brazil | C30: Central and South America | D30: Ba1 | E30: 0.024614437
B31: Bulgaria | C31: Eastern Europe & Russia | D31: Baa1 | E31: 0.015716261
B32: Burkina Faso | C32: Africa | D32: Caa1 | E32: 0.073727752
B33: Cambodia | C33: Asia | D33: B2 | E33: 0.054082426
... B161: Zambia | C161: Africa | D161: Caa2 | E161: 0.088519526

Sheet Assumptions Working 
A2: # | B2: Revenue Growth
B4: Company Historical Growth
K5: CAGR
B6: ='P&l 25-24'!B3 -> Particulars | C6: ='P&l 25-24'!D3 -> 43525 | D6: ='P&l 25-24'!E3 -> 43891 | E6: ='P&l 25-24'!F3 -> 44256 | F6: ='P&l 25-24'!G3 -> 44621 | G6: ='P&l 25-24'!H3 -> 44986 | H6: ='P&l 25-24'!I3 -> 45382 | I6: ='P&l 25-24'!J3 -> 45717 | K6: 3 Years | L6: 5 Years
B7: Revenue from operations (Net) | C7: 7334 | D7: 7315 | E7: 8048 | F7: 9512 | G7: 9764 | H7: 9653 | I7: 10831 | K7: =_xlfn.RRI(3,F7,I7) -> 0.044236585 | L7: =_xlfn.RRI(5,D7,I7) -> 0.081660188
B8: Sales Growth | C8: ='P&l 25-24'!D8 -> 0.16007593 | D8: ='P&l 25-24'!E8 -> -0.0025906736 | E8: ='P&l 25-24'!F8 -> 0.10020506 | F8: ='P&l 25-24'!G8 -> 0.18190855 | G8: ='P&l 25-24'!H8 -> 0.026492851 | H8: ='P&l 25-24'!I8 -> -0.011368292 | I8: ='P&l 25-24'!J8 -> 0.1220346
B11: FMCG (India) Growth
B13: Indian Brand Equity Foundation | C13: https://ibef.org/industry/fmcg-presentation
B15: Household FMCG ( April 2025) | C15: 17,792 crore (US$ 2.07 billion)
B16: Rural FMCG Consumption | C16: 35% of total FMCG sales | D16: 11% CAGR (premium segment)
B17: Indian Beauty and Personal Care (BPC) market | C17: $34 Bn by 2028 | D17: 10-11% Annual CAGR
B18: Overall FMCG Sector (India) | C18: US$ 615 billion (2027) | D18: 38.5% wil Grow till 2027
B19: Direct Selling Industry | C19: US$ 2.58 billion (FY24) | D19: 7.15% next (5-year CAGR)
B22: Crisil | C22: https://inciflo.com/blogs/fmcg-industry-growth-in-india/
B23: Indian FMCG industry | C23: $1trillion by 2033–34 | D23: 14–21%
B24: Rural markets | C24: 40% of FMCG sales by 2030
B25: Urban Markets | C25: 60% of FMCG sales by 2030
B26: E-commerce | C26: 15–18% FMCG sales by 2030,
B28: Imarc | C28: https://www.imarcgroup.com/india-fmcg-market
B29: 2024 Market Size | C29: USD 245.39 Billion
B30: 2033 Projected Market Size | C30: USD 1,108.48 Billion
B31: CAGR (2025-2033) | C31: 0.1733
B33: ZION Market Reserch | C33: https://www.zionmarketresearch.com/report/india-fmcg-market
B34: India FMCG market size | C34: USD 665.63 billion by 2032 | D34: (CAGR) 14.80%
B36: Beauty & Personal Care (India) Growth
B38: Statista | C38: https://www.statista.com/outlook/cmo/beauty-personal-care/india?srsltid=AfmBOorzt_p4jrJ6rhQpLXjwTHkLH4EGkU_rRtahTG4PhNxLzw7bm_L-
B39: Revenue | C39: US$33.08bn in 2025. | D39: 3.48% (CAGR 2025-2030)
B40: market volume | C40: US$14.80bn in 2025.
B41: United States | C41: (US$105bn in 2025)
B42: 9.4% of total revenue | C42: online sales by 2025.
B45: Indian Brand Equity Foundation | C45: https://www.ibef.org/news/india-you-e-beauty-the-blush-and-glow-of-the-new-billion-dollar-boom
AK46: BEAUTY AND PERSONAL CARE (BPC)
B47: India’s beauty and personal care market | C47: Rs. 2,95,358 crore (US$ 34 billion) by 2028, | D47: 10-11% Cagr Growth
B50: India Edible Oils (India) Growth
B52: Imarc | C52: https://www.imarcgroup.com/india-edible-oil-market
B54: 2024 Market Size | C54: 25.0 Million Tons
B55: 2033 Projected Market Size | C55: 28.2 Million Tons
B56: CAGR (2025-2033) | C56: 0.0131
B59: Industry Reports | C59: https://www.marketsandata.com/industry-reports/india-edible-oils-market
B61: FY2024 | C61: USD 19.86 billion
B62: FY2032. | C62: USD 26.19 billion
C63: CAGR of 3.52%
B66: Growth Factor
B68: We are confident of maintaining a double-digit growth momentum in the franchise throughout the year on the back of sharper brand activations supported by a strategic pivot from trade-led investments towards brand-building and therefore increasing SOV, especially in the mid and premium segments, along with enhanced direct reach through Project SETU, which invariably benefits VAHO.
B72: Project SETU aims to expand Marico’s direct reach from approximately 1 million outlets to 1.5 million by FY27. Project SETU was kicked off in 11 states during the year
B73: The company plans to grow its Foods business by over 25% per year, so that by FY27, the revenue will be about 8 times higher than in FY20, and roughly double the level achieved in FY24.
B74: The company’s digital-first brands performed better than expected in FY25, reaching ₹750 crore annualized revenue. Seeing this momentum, they’ve raised their FY27 target — instead of growing to 2x of FY24 levels, they now plan to reach 2.5x of FY24 revenue by FY27..
B76: Just Herbs and True Elements, though not yet at breakeven, will focus on sustainable 20% to 25% growth breakeven at the earliest over the next 18 to 24 months
B77: Which is Just Herbs and True Elements, we will now grow maybe 20% to 25% on a sustainable basis, but accelerate the journey to breakeven period so that in 18 to 24 months, we see some site of a breakeven
B78: Just Herbs and True Elements, though not yet at breakeven, will focus on sustainable 20-25% growth and leveraging scale and synergy to achieve breakeven at the earliest over the next 18 to 24 months
B79: 1. Saffola Soya Chunks track to becoming a 100+ crore brand in the medium term. 3-5 years
B80: 1. Plix holds the potential to scale to 1,000 Cr. in revenues in the medium term
B81: 1. Beardo brand has the potential to reach L500 cr. mark in the medium term.
B82: 1. Just Herbs - brand crossed 100 crores in sales
... B86: we are fairly confident about delivering 25%-plus growth in the Foods business
A104: # | B104: Gross Margin Growth
B106: Company Historical Growth
K107: CAGR
B108: Particulars | C108: ='P&l 25-24'!D3 -> 43525 | D108: ='P&l 25-24'!E3 -> 43891 | E108: ='P&l 25-24'!F3 -> 44256 | F108: ='P&l 25-24'!G3 -> 44621 | G108: ='P&l 25-24'!H3 -> 44986 | H108: ='P&l 25-24'!I3 -> 45382 | I108: ='P&l 25-24'!J3 -> 45717 | K108: Median | L108: Average
B109: Gross Margin | C109: ='P&l 25-24'!D23 -> 0.45227707 | D109: ='P&l 25-24'!E23 -> 0.48803828 | E109: ='P&l 25-24'!F23 -> 0.4694334 | F109: ='P&l 25-24'!G23 -> 0.42851135 | G109: ='P&l 25-24'!H23 -> 0.45196641 | H109: ='P&l 25-24'!I23 -> 0.50813219 | I109: ='P&l 25-24'!J23 -> 0.50253901 | K109: =MEDIAN(C109:I109) -> 0.4694334 | L109: =AVERAGE(C109:I109) -> 0.47155681
B110: Gross Margin Growth | C110: ='P&l 25-24'!D126 -> 0 | D110: =D109/C109-1 -> 0.079069258 | E110: =E109/D109-1 -> -0.03812176 | F110: =F109/E109-1 -> -0.087173272 | G110: =G109/F109-1 -> 0.05473613 | H110: =H109/G109-1 -> 0.12426981 | I110: =I109/H109-1 -> -0.01100733 | K110: =MEDIAN(D110:I110) -> 0.0218644
B113: Damodaran Website> Data> Current Data> Find margin > Cash Flow estimation
B116: Sector Data - Damodaran
B118: Just India
B119: Household Products | C119: 0.52
D120: Total Raw Material Suppliers - 682
B121: All Emarging Markets
B122: Household Products | C122: 0.47997573
B124: Gobal Market
B125: Household Products | C125: 0.51807656
B131: The price outlook is highly dependent on the specific commodity, particularly copra, which has recently experienced hyperinflation. Copra prices surged 18% QoQ and ~107% YoY, surpassing company expectations.
B133: In the period leading up to Q1 FY26, copra experienced hyperinflationary conditions due to a supply-demand gap caused by low crop yields and unseasonal weather. The company has taken multiple rounds of price increases in response, leading to an effective consumer price increase of over 60% point-to-point in some packs
A169: # | B169: SG&A Expenses
K170: CAGR
B171: Particulars | C171: 43525 | D171: 43891 | E171: 44256 | F171: 44621 | G171: 44986 | H171: 45382 | I171: 45717 | K171: 3 Years | L171: 5 Years
B172: Revenue from operations (Net) | C172: 7334 | D172: 7315 | E172: 8048 | F172: 9512 | G172: 9764 | H172: 9653 | I172: 10831 | K172: =_xlfn.RRI(3,F172,I172) -> 0.044236585 | L172: =_xlfn.RRI(5,D172,I172) -> 0.081660188
B173: Sales YoY% | C173: ='P&l 25-24'!D8 -> 0.16007593 | D173: ='P&l 25-24'!E8 -> -0.0025906736 | E173: ='P&l 25-24'!F8 -> 0.10020506 | F173: ='P&l 25-24'!G8 -> 0.18190855 | G173: ='P&l 25-24'!H8 -> 0.026492851 | H173: ='P&l 25-24'!I8 -> -0.011368292 | I173: ='P&l 25-24'!J8 -> 0.1220346
B175: SG&A Expenses | C175: =-'P&l 25-24'!D32 -> 1992 | D175: =-'P&l 25-24'!E32 -> 2130 | E175: =-'P&l 25-24'!F32 -> 2176 | F175: =-'P&l 25-24'!G32 -> 2395 | G175: =-'P&l 25-24'!H32 -> 2603 | H175: =-'P&l 25-24'!I32 -> 2879 | I175: =-'P&l 25-24'!J32 -> 3304 | K175: =_xlfn.RRI(3,F175,I175) -> 0.11321275 | L175: =_xlfn.RRI(5,D175,I175) -> 0.091772339
B176: SG&A YoY% | D176: =D175/C175-1 -> 0.069277108 | E176: =E175/D175-1 -> 0.021596244 | F176: =F175/E175-1 -> 0.10064338 | G176: =G175/F175-1 -> 0.086847599 | H176: =H175/G175-1 -> 0.1060315 | I176: =I175/H175-1 -> 0.1476207
B178: SG&A % Sales | C178: =C175/C172 -> 0.27161167 | D178: =D175/D172 -> 0.2911825 | E178: =E175/E172 -> 0.27037773 | F178: =F175/F172 -> 0.25178722 | G178: =G175/G172 -> 0.26659156 | H178: =H175/H172 -> 0.29824925 | I178: =I175/I172 -> 0.30505032 | K178: =MEDIAN(C178:I178) -> 0.27161167 | L178: =AVERAGE(C178:I178) -> 0.27926432
B182: Continued high A&P intensity (~9–10% of sales) as Marico accelerates new category building (Foods, Digital-first brands).
B183: YoY A&P +25%; focus on VAHO, Foods, and Premium Personal Care (PPC); cost optimization done in non-media spends (film shoots, celebrity costs, data purchases)
B184: So, in short, they are doing massively SG&A expenses for Project Setu and for the premium products of their VAHO, Foods and Premium Personal Care.
B185: The estimated investment for Project SETU is ₹80-100 crores over a 3-year period
B186: The management consistently positions A&P spending as a strategic investment essential for long-term growth and brand equity, explicitly prioritizing it over managing short-term margins
B187: Impact on Results: Management noted that if A&P had only grown in line with the top line in FY25, the consolidated EBITDA margin would have been 20.3%, indicating they over-invested in A&P relative to revenue growth to set up future expansion
B189: Shift from BTL to ATL: In the Value-Added Hair Oils (VAHO) segment, particularly the Bottom of Pyramid (BOP), management has taken a conscious decision to defocus on BTL (Below The Line) trade inputs, labeling competitive BTL fighting as a "suicidal strategy". They believe that this approach negatively impacts category growth and equit
B192: Consensus estimates across brokerages:
B193: FY25 EBITDA margin: ~19.7%
B194: FY26E: ~19–20%
B195: FY27E: ~20.5–21%
B198: Historical SG&A Expenses
B200: Particulars | C200: 2019 | D200: =C200+1 -> 2020 | E200: =D200+1 -> 2021 | F200: =E200+1 -> 2022 | G200: =F200+1 -> 2023 | H200: =G200+1 -> 2024 | I200: =H200+1 -> 2025
B202: Revenue | C202: =C172 -> 7334 | D202: =D172 -> 7315 | E202: =E172 -> 8048 | F202: =F172 -> 9512 | G202: =G172 -> 9764 | H202: =H172 -> 9653 | I202: =I172 -> 10831
B203: Employee Benefit Cost | C203: 466 | D203: 478 | E203: 570 | F203: 586 | G203: 653 | H203: 743 | I203: 831
B204: Advertisement and sales promotion | C204: 659 | D204: 727 | E204: 698 | F204: 796 | G204: 842 | H204: 952 | I204: 1128
B205: Freight forwarding and distribution expenses | C205: 287 | D205: 294 | E205: 305 | F205: 354 | G205: 387 | H205: 416 | I205: 449
B206: Processing and other manufacturing charges | C206: 250 | D206: 255 | E206: 240 | F206: 251 | G206: 238 | H206: 243 | I206: 274
B207: Rent and storage charges | C207: 11 | D207: 16 | E207: 20 | F207: 20 | G207: 20 | H207: 33 | I207: 43
B208: Legal & professional charges | C208: 48 | D208: 54 | E208: 61 | F208: 73 | G208: 101 | H208: 76 | I208: 88
...

Sheet ControlSheet
B2: ='Input Sheet'!C5 -> Marico Ltd
B3: Control Sheet
J4: Current Case | K4: 1
J7: Actual | K7: Explicit Forecast Period | P7: Maturity Period
B8: In INR crores unless started otherwise | E8: 2020 | F8: =E8+1 -> 2021 | G8: =F8+1 -> 2022 | H8: =G8+1 -> 2023 | I8: =H8+1 -> 2024 | J8: =I8+1 -> 2025 | K8: =J8+1 -> 2026 | L8: =K8+1 -> 2027 | M8: =L8+1 -> 2028 | ... T8: =S8+1 -> 2035
B10: Assumptions
A12: # | B12: Revenue
B14: Revenue - yoy % Growth
B15: Management Case | E15: ='P&l 25-24'!E8 -> -0.0025906736 | F15: ='P&l 25-24'!F8 -> 0.10020506 | G15: ='P&l 25-24'!G8 -> 0.18190855 | H15: ='P&l 25-24'!H8 -> 0.026492851 | I15: ='P&l 25-24'!I8 -> -0.011368292 | J15: ='P&l 25-24'!J8 -> 0.1220346 | K15: 0.14 | L15: =K15+($O$15-$K$15)/($O$8-$K$8) -> 0.135 | M15: =L15+($O$15-$K$15)/($O$8-$K$8) -> 0.13 | N15: =M15+($O$15-$K$15)/($O$8-$K$8) -> 0.125 | O15: 0.12 | P15: 0.12 | Q15: 0.12 | R15: 0.12 | S15: 0.12 | T15: 0.12
B16: Base Case | E16: =E15 -> -0.0025906736 | F16: =F15 -> 0.10020506 | G16: =G15 -> 0.18190855 | H16: =H15 -> 0.026492851 | I16: =I15 -> -0.011368292 | J16: =J15 -> 0.1220346 | K16: 0.11 | L16: 0.11 | M16: 0.11 | N16: 0.11 | O16: 0.11 | P16: 0.1 | Q16: 0.1 | R16: 0.1 | S16: 0.1 | T16: 0.1
B17: Down Case | E17: =E16 -> -0.0025906736 | F17: =F16 -> 0.10020506 | G17: =G16 -> 0.18190855 | H17: =H16 -> 0.026492851 | I17: =I16 -> -0.011368292 | J17: =J16 -> 0.1220346 | K17: 0.1 | L17: 0.1 | M17: 0.1 | N17: 0.1 | O17: 0.1 | P17: 0.08 | Q17: 0.08 | R17: 0.08 | S17: 0.08 | T17: 0.08
B18: ="Current Case - "&CHOOSE($K$4,B15,B16,B17) -> Current Case - Management Case | K18: =CHOOSE($K$4,K15,K16,K17) -> 0.14 | L18: =CHOOSE($K$4,L15,L16,L17) -> 0.135 | M18: =CHOOSE($K$4,M15,M16,M17) -> 0.13 | N18: =CHOOSE($K$4,N15,N16,N17) -> 0.125 | O18: =CHOOSE($K$4,O15,O16,O17) -> 0.12 | P18: =CHOOSE($K$4,P15,P16,P17) -> 0.12 | Q18: =CHOOSE($K$4,Q15,Q16,Q17) -> 0.12 | R18: =CHOOSE($K$4,R15,R16,R17) -> 0.12 | ... T18: =CHOOSE($K$4,T15,T16,T17) -> 0.12
A21: # | B21: COGS
B23: Gross Margin %
B24: Management Case | E24: ='P&l 25-24'!D23 -> 0.45227707 | F24: ='P&l 25-24'!E23 -> 0.48803828 | G24: ='P&l 25-24'!F23 -> 0.4694334 | H24: ='P&l 25-24'!G23 -> 0.42851135 | I24: ='P&l 25-24'!H23 -> 0.45196641 | J24: ='P&l 25-24'!I23 -> 0.50813219 | K24: 0.48 | L24: 0.48 | M24: 0.48 | N24: 0.5 | O24: 0.5 | P24: 0.5 | Q24: 0.5 | R24: 0.5 | S24: 0.5 | T24: 0.5
B25: Base Case | E25: =E24 -> 0.45227707 | F25: =F24 -> 0.48803828 | G25: =G24 -> 0.4694334 | H25: =H24 -> 0.42851135 | I25: =I24 -> 0.45196641 | J25: =J24 -> 0.50813219 | K25: 0.45 | L25: 0.45 | M25: 0.45 | N25: 0.45 | O25: 0.45 | P25: 0.48 | Q25: 0.48 | R25: 0.48 | S25: 0.48 | T25: 0.48
B26: Down Case | E26: =E25 -> 0.45227707 | F26: =F25 -> 0.48803828 | G26: =G25 -> 0.4694334 | H26: =H25 -> 0.42851135 | I26: =I25 -> 0.45196641 | J26: =J25 -> 0.50813219 | K26: 0.43 | L26: 0.43 | M26: 0.43 | N26: 0.43 | O26: 0.43 | P26: 0.46 | Q26: 0.46 | R26: 0.46 | S26: 0.46 | T26: 0.46
B27: ="Current Case - "&CHOOSE($K$4,B24,B25,B26) -> Current Case - Management Case | K27: =CHOOSE($K$4,K24,K25,K26) -> 0.48 | L27: =CHOOSE($K$4,L24,L25,L26) -> 0.48 | M27: =CHOOSE($K$4,M24,M25,M26) -> 0.48 | N27: =CHOOSE($K$4,N24,N25,N26) -> 0.5 | O27: =CHOOSE($K$4,O24,O25,O26) -> 0.5 | P27: =CHOOSE($K$4,P24,P25,P26) -> 0.5 | Q27: =CHOOSE($K$4,Q24,Q25,Q26) -> 0.5 | R27: =CHOOSE($K$4,R24,R25,R26) -> 0.5 | ... T27: =CHOOSE($K$4,T24,T25,T26) -> 0.5
B29: Current Case - COGS % Sales | K29: =1-K27 -> 0.52 | L29: =1-L27 -> 0.52 | M29: =1-M27 -> 0.52 | N29: =1-N27 -> 0.5 | O29: =1-O27 -> 0.5 | P29: =1-P27 -> 0.5 | Q29: =1-Q27 -> 0.5 | R29: =1-R27 -> 0.5 | ... T29: =1-T27 -> 0.5
A31: # | B31: Selling, General and Administrative (SG&A) Expenses
B33: Employee Benefit Cost % Revenue
B34: Management Case | E34: ='Assumptions Working '!D245 -> 0.065345181 | F34: ='Assumptions Working '!E245 -> 0.07082505 | G34: ='Assumptions Working '!F245 -> 0.061606392 | H34: ='Assumptions Working '!G245 -> 0.066878329 | I34: ='Assumptions Working '!H245 -> 0.07697089 | J34: ='Assumptions Working '!I245 -> 0.076724218 | K34: 0.076 | L34: 0.076 | M34: 0.076 | N34: 0.076 | O34: 0.076 | P34: 0.076 | Q34: 0.076 | R34: 0.076 | S34: 0.076 | T34: 0.076
B35: Base Case | E35: =E34 -> 0.065345181 | F35: =F34 -> 0.07082505 | G35: =G34 -> 0.061606392 | H35: =H34 -> 0.066878329 | I35: =I34 -> 0.07697089 | J35: =J34 -> 0.076724218 | K35: 0.07 | L35: 0.07 | M35: 0.07 | N35: 0.07 | O35: 0.07 | P35: 0.07 | Q35: 0.07 | R35: 0.07 | S35: 0.07 | T35: 0.07
B36: Down Case | E36: =E35 -> 0.065345181 | F36: =F35 -> 0.07082505 | G36: =G35 -> 0.061606392 | H36: =H35 -> 0.066878329 | I36: =I35 -> 0.07697089 | J36: =J35 -> 0.076724218 | K36: 0.08 | L36: 0.08 | M36: 0.08 | N36: 0.08 | O36: 0.08 | P36: 0.08 | Q36: 0.08 | R36: 0.08 | S36: 0.08 | T36: 0.08
B37: ="Current Case - "&CHOOSE($K$4,B34,B35,B36) -> Current Case - Management Case | K37: =CHOOSE($K$4,K34,K35,K36) -> 0.076 | L37: =CHOOSE($K$4,L34,L35,L36) -> 0.076 | M37: =CHOOSE($K$4,M34,M35,M36) -> 0.076 | N37: =CHOOSE($K$4,N34,N35,N36) -> 0.076 | O37: =CHOOSE($K$4,O34,O35,O36) -> 0.076 | P37: =CHOOSE($K$4,P34,P35,P36) -> 0.076 | Q37: =CHOOSE($K$4,Q34,Q35,Q36) -> 0.076 | R37: =CHOOSE($K$4,R34,R35,R36) -> 0.076 | ... T37: =CHOOSE($K$4,T34,T35,T36) -> 0.076
B39: Advertisement and sales promotion % Revenue
B40: Management Case | E40: ='Assumptions Working '!D248 -> 0.099384826 | F40: ='Assumptions Working '!E248 -> 0.086729622 | G40: ='Assumptions Working '!F248 -> 0.083683768 | H40: ='Assumptions Working '!G248 -> 0.08623515 | I40: ='Assumptions Working '!H248 -> 0.09862219 | J40: ='Assumptions Working '!I248 -> 0.10414551 | K40: 0.115 | L40: 0.115 | M40: 0.115 | N40: 0.115 | O40: 0.115 | P40: 0.115 | Q40: 0.115 | R40: 0.115 | S40: 0.115 | T40: 0.115
B41: Base Case | E41: =E40 -> 0.099384826 | F41: =F40 -> 0.086729622 | G41: =G40 -> 0.083683768 | H41: =H40 -> 0.08623515 | I41: =I40 -> 0.09862219 | J41: =J40 -> 0.10414551 | K41: 0.09 | L41: 0.09 | M41: 0.09 | N41: 0.09 | O41: 0.09 | P41: 0.09 | Q41: 0.09 | R41: 0.09 | S41: 0.09 | T41: 0.09
B42: Down Case | E42: =E41 -> 0.099384826 | F42: =F41 -> 0.086729622 | G42: =G41 -> 0.083683768 | H42: =H41 -> 0.08623515 | I42: =I41 -> 0.09862219 | J42: =J41 -> 0.10414551 | K42: 0.1 | L42: 0.1 | M42: 0.1 | N42: 0.1 | O42: 0.1 | P42: 0.1 | Q42: 0.1 | R42: 0.1 | S42: 0.1 | T42: 0.1
B43: ="Current Case - "&CHOOSE($K$4,B40,B41,B42) -> Current Case - Management Case | K43: =CHOOSE($K$4,K40,K41,K42) -> 0.115 | L43: =CHOOSE($K$4,L40,L41,L42) -> 0.115 | M43: =CHOOSE($K$4,M40,M41,M42) -> 0.115 | N43: =CHOOSE($K$4,N40,N41,N42) -> 0.115 | O43: =CHOOSE($K$4,O40,O41,O42) -> 0.115 | P43: =CHOOSE($K$4,P40,P41,P42) -> 0.115 | Q43: =CHOOSE($K$4,Q40,Q41,Q42) -> 0.115 | R43: =CHOOSE($K$4,R40,R41,R42) -> 0.115 | ... T43: =CHOOSE($K$4,T40,T41,T42) -> 0.115
B45: Freight and distribution expenses % Revenue
B46: Management Case | E46: ='Assumptions Working '!D251 -> 0.040191388 | F46: ='Assumptions Working '!E251 -> 0.037897614 | G46: ='Assumptions Working '!F251 -> 0.037216148 | H46: ='Assumptions Working '!G251 -> 0.039635395 | I46: ='Assumptions Working '!H251 -> 0.043095411 | J46: ='Assumptions Working '!I251 -> 0.041455083 | K46: 0.04 | L46: 0.04 | M46: 0.04 | N46: 0.04 | O46: 0.04 | P46: 0.04 | Q46: 0.04 | R46: 0.04 | S46: 0.04 | T46: 0.04
B47: Base Case | E47: =E46 -> 0.040191388 | F47: =F46 -> 0.037897614 | G47: =G46 -> 0.037216148 | H47: =H46 -> 0.039635395 | I47: =I46 -> 0.043095411 | J47: =J46 -> 0.041455083 | K47: 0.036 | L47: 0.036 | M47: 0.036 | N47: 0.036 | O47: 0.036 | P47: 0.036 | Q47: 0.036 | R47: 0.036 | S47: 0.036 | T47: 0.036
B48: Down Case | E48: =E47 -> 0.040191388 | F48: =F47 -> 0.037897614 | G48: =G47 -> 0.037216148 | H48: =H47 -> 0.039635395 | I48: =I47 -> 0.043095411 | J48: =J47 -> 0.041455083 | K48: 0.036 | L48: 0.036 | M48: 0.036 | N48: 0.036 | O48: 0.036 | P48: 0.036 | Q48: 0.036 | R48: 0.036 | S48: 0.036 | T48: 0.036
B49: ="Current Case - "&CHOOSE($K$4,B46,B47,B48) -> Current Case - Management Case | K49: =CHOOSE($K$4,K46,K47,K48) -> 0.04 | L49: =CHOOSE($K$4,L46,L47,L48) -> 0.04 | M49: =CHOOSE($K$4,M46,M47,M48) -> 0.04 | N49: =CHOOSE($K$4,N46,N47,N48) -> 0.04 | O49: =CHOOSE($K$4,O46,O47,O48) -> 0.04 | P49: =CHOOSE($K$4,P46,P47,P48) -> 0.04 | Q49: =CHOOSE($K$4,Q46,Q47,Q48) -> 0.04 | R49: =CHOOSE($K$4,R46,R47,R48) -> 0.04 | ... T49: =CHOOSE($K$4,T46,T47,T48) -> 0.04
B51: Other Misc SG&A Expenses % Revenue
B52: Management Case | E52: ='Assumptions Working '!D254 -> 0.086261107 | F52: ='Assumptions Working '!E254 -> 0.074925447 | G52: ='Assumptions Working '!F254 -> 0.069280908 | H52: ='Assumptions Working '!G254 -> 0.073842687 | I52: ='Assumptions Working '!H254 -> 0.079560758 | J52: ='Assumptions Working '!I254 -> 0.08272551 | K52: 0.08 | L52: 0.08 | M52: 0.08 | N52: 0.08 | O52: 0.08 | P52: 0.08 | Q52: 0.08 | R52: 0.08 | S52: 0.08 | T52: 0.08
B53: Base Case | E53: =E52 -> 0.086261107 | F53: =F52 -> 0.074925447 | G53: =G52 -> 0.069280908 | H53: =H52 -> 0.073842687 | I53: =I52 -> 0.079560758 | J53: =J52 -> 0.08272551 | K53: 0.0729 | L53: 0.0729 | M53: 0.0729 | N53: 0.0729 | O53: 0.0729 | P53: 0.0729 | Q53: 0.0729 | R53: 0.0729 | S53: 0.0729 | T53: 0.0729
B54: Down Case | E54: =E53 -> 0.086261107 | F54: =F53 -> 0.074925447 | G54: =G53 -> 0.069280908 | H54: =H53 -> 0.073842687 | I54: =I53 -> 0.079560758 | J54: =J53 -> 0.08272551 | K54: 0.07 | L54: 0.07 | M54: 0.07 | N54: 0.07 | O54: 0.07 | P54: 0.07 | Q54: 0.07 | R54: 0.07 | S54: 0.07 | T54: 0.07
B55: ="Current Case - "&CHOOSE($K$4,B52,B53,B54) -> Current Case - Management Case | K55: =CHOOSE($K$4,K52,K53,K54) -> 0.08 | L55: =CHOOSE($K$4,L52,L53,L54) -> 0.08 | M55: =CHOOSE($K$4,M52,M53,M54) -> 0.08 | N55: =CHOOSE($K$4,N52,N53,N54) -> 0.08 | O55: =CHOOSE($K$4,O52,O53,O54) -> 0.08 | P55: =CHOOSE($K$4,P52,P53,P54) -> 0.08 | Q55: =CHOOSE($K$4,Q52,Q53,Q54) -> 0.08 | R55: =CHOOSE($K$4,R52,R53,R54) -> 0.08 | ... T55: =CHOOSE($K$4,T52,T53,T54) -> 0.08
B57: Total SG&A Expenses % Revenue | E57: =E52+E46+E40+E34 -> 0.2911825 | F57: =F52+F46+F40+F34 -> 0.27037773 | G57: =G52+G46+G40+G34 -> 0.25178722 | H57: =H52+H46+H40+H34 -> 0.26659156 | I57: =I52+I46+I40+I34 -> 0.29824925 | J57: =J52+J46+J40+J34 -> 0.30505032 | K57: =K52+K46+K40+K34 -> 0.311 | L57: =L52+L46+L40+L34 -> 0.311 | ... T57: =T52+T46+T40+T34 -> 0.311
A59: # | B59: Non Current Assets
B61: Fixed Assets
B63: Right of Use Asset Growth %
B64: Management Case | K64: 0 | L64: 0 | M64: 0 | N64: 0 | O64: 0 | P64: 0 | Q64: 0 | R64: 0 | S64: 0 | T64: 0
B65: Best Case | K65: 0 | L65: 0 | M65: 0 | N65: 0 | O65: 0 | P65: 0 | Q65: 0 | R65: 0 | S65: 0 | T65: 0
B66: Down Case | K66: 0 | L66: 0 | M66: 0 | N66: 0 | O66: 0 | P66: 0 | Q66: 0 | R66: 0 | S66: 0 | T66: 0
B67: ="Current Case - "&CHOOSE($K$4,B64,B65,B66) -> Current Case - Management Case | K67: =CHOOSE($K$4,K64,K65,K66) -> 0 | L67: =CHOOSE($K$4,L64,L65,L66) -> 0 | M67: =CHOOSE($K$4,M64,M65,M66) -> 0 | N67: =CHOOSE($K$4,N64,N65,N66) -> 0 | O67: =CHOOSE($K$4,O64,O65,O66) -> 0 | P67: =CHOOSE($K$4,P64,P65,P66) -> 0 | Q67: =CHOOSE($K$4,Q64,Q65,Q66) -> 0 | R67: =CHOOSE($K$4,R64,R65,R66) -> 0 | ... T67: =CHOOSE($K$4,T64,T65,T66) -> 0
B69: Capital Working in Progress Growth %
B70: Management Case | K70: 0 | L70: 0 | M70: 0 | N70: 0 | O70: 0 | P70: 0 | Q70: 0 | R70: 0 | S70: 0 | T70: 0
B71: Best Case | K71: 0 | L71: 0 | M71: 0 | N71: 0 | O71: 0 | P71: 0 | Q71: 0 | R71: 0 | S71: 0 | T71: 0
B72: Down Case | K72: 0 | L72: 0 | M72: 0 | N72: 0 | O72: 0 | P72: 0 | Q72: 0 | R72: 0 | S72: 0 | T72: 0
B73: ="Current Case - "&CHOOSE($K$4,B70,B71,B72) -> Current Case - Management Case | K73: =CHOOSE($K$4,K70,K71,K72) -> 0 | L73: =CHOOSE($K$4,L70,L71,L72) -> 0 | M73: =CHOOSE($K$4,M70,M71,M72) -> 0 | N73: =CHOOSE($K$4,N70,N71,N72) -> 0 | O73: =CHOOSE($K$4,O70,O71,O72) -> 0 | P73: =CHOOSE($K$4,P70,P71,P72) -> 0 | Q73: =CHOOSE($K$4,Q70,Q71,Q72) -> 0 | R73: =CHOOSE($K$4,R70,R71,R72) -> 0 | ... T73: =CHOOSE($K$4,T70,T71,T72) -> 0
B75: Investment Property Growth %
B76: Management Case | K76: 0 | L76: 0 | M76: 0 | N76: 0 | O76: 0 | P76: 0 | Q76: 0 | R76: 0 | S76: 0 | T76: 0
B77: Best Case | K77: 0 | L77: 0 | M77: 0 | N77: 0 | O77: 0 | P77: 0 | Q77: 0 | R77: 0 | S77: 0 | T77: 0
B78: Down Case | K78: 0 | L78: 0 | M78: 0 | N78: 0 | O78: 0 | P78: 0 | Q78: 0 | R78: 0 | S78: 0 | T78: 0
B79: ="Current Case - "&CHOOSE($K$4,B76,B77,B78) -> Current Case - Management Case | K79: =CHOOSE($K$4,K76,K77,K78) -> 0 | L79: =CHOOSE($K$4,L76,L77,L78) -> 0 | M79: =CHOOSE($K$4,M76,M77,M78) -> 0 | N79: =CHOOSE($K$4,N76,N77,N78) -> 0 | O79: =CHOOSE($K$4,O76,O77,O78) -> 0 | P79: =CHOOSE($K$4,P76,P77,P78) -> 0 | Q79: =CHOOSE($K$4,Q76,Q77,Q78) -> 0 | R79: =CHOOSE($K$4,R76,R77,R78) -> 0 | ... T79: =CHOOSE($K$4,T76,T77,T78) -> 0
B81: Intangible Non Current Assets
B83: Intangible Asset (Excluding Goodwill) Growth %
B84: Management Case | K84: 0 | L84: 0 | M84: 0 | N84: 0 | O84: 0 | P84: 0 | Q84: 0 | R84: 0 | S84: 0 | T84: 0
B85: Best Case | K85: 0 | L85: 0 | M85: 0 | N85: 0 | O85: 0 | P85: 0 | Q85: 0 | R85: 0 | S85: 0 | T85: 0
B86: Down Case | K86: 0 | L86: 0 | M86: 0 | N86: 0 | O86: 0 | P86: 0 | Q86: 0 | R86: 0 | S86: 0 | T86: 0
B87: ="Current Case - "&CHOOSE($K$4,B84,B85,B86) -> Current Case - Management Case | K87: =CHOOSE($K$4,K84,K85,K86) -> 0 | L87: =CHOOSE($K$4,L84,L85,L86) -> 0 | M87: =CHOOSE($K$4,M84,M85,M86) -> 0 | N87: =CHOOSE($K$4,N84,N85,N86) -> 0 | O87: =CHOOSE($K$4,O84,O85,O86) -> 0 | P87: =CHOOSE($K$4,P84,P85,P86) -> 0 | Q87: =CHOOSE($K$4,Q84,Q85,Q86) -> 0 | R87: =CHOOSE($K$4,R84,R85,R86) -> 0 | ... T87: =CHOOSE($K$4,T84,T85,T86) -> 0
B89: Goodwill Growth %
B90: Management Case | K90: 0 | L90: 0 | M90: 0 | N90: 0 | O90: 0 | P90: 0 | Q90: 0 | R90: 0 | S90: 0 | T90: 0
B91: Best Case | K91: 0 | L91: 0 | M91: 0 | N91: 0 | O91: 0 | P91: 0 | Q91: 0 | R91: 0 | S91: 0 | T91: 0
B92: Down Case | K92: 0 | L92: 0 | M92: 0 | N92: 0 | O92: 0 | P92: 0 | Q92: 0 | R92: 0 | S92: 0 | T92: 0
B93: ="Current Case - "&CHOOSE($K$4,B90,B91,B92) -> Current Case - Management Case | K93: =CHOOSE($K$4,K90,K91,K92) -> 0 | L93: =CHOOSE($K$4,L90,L91,L92) -> 0 | M93: =CHOOSE($K$4,M90,M91,M92) -> 0 | N93: =CHOOSE($K$4,N90,N91,N92) -> 0 | O93: =CHOOSE($K$4,O90,O91,O92) -> 0 | P93: =CHOOSE($K$4,P90,P91,P92) -> 0 | Q93: =CHOOSE($K$4,Q90,Q91,Q92) -> 0 | R93: =CHOOSE($K$4,R90,R91,R92) -> 0 | ... T93: =CHOOSE($K$4,T90,T91,T92) -> 0
B95: Non Current Financial Assets Growth %
B96: Management Case | K96: 0 | L96: 0 | M96: 0 | N96: 0 | O96: 0 | P96: 0 | Q96: 0 | R96: 0 | S96: 0 | T96: 0
B97: Best Case | K97: 0 | L97: 0 | M97: 0 | N97: 0 | O97: 0 | P97: 0 | Q97: 0 | R97: 0 | S97: 0 | T97: 0
B98: Down Case | K98: 0 | L98: 0 | M98: 0 | N98: 0 | O98: 0 | P98: 0 | Q98: 0 | R98: 0 | S98: 0 | T98: 0
B99: ="Current Case - "&CHOOSE($K$4,B96,B97,B98) -> Current Case - Management Case | K99: =CHOOSE($K$4,K96,K97,K98) -> 0 | L99: =CHOOSE($K$4,L96,L97,L98) -> 0 | M99: =CHOOSE($K$4,M96,M97,M98) -> 0 | N99: =CHOOSE($K$4,N96,N97,N98) -> 0 | O99: =CHOOSE($K$4,O96,O97,O98) -> 0 | P99: =CHOOSE($K$4,P96,P97,P98) -> 0 | Q99: =CHOOSE($K$4,Q96,Q97,Q98) -> 0 | R99: =CHOOSE($K$4,R96,R97,R98) -> 0 | ... T99: =CHOOSE($K$4,T96,T97,T98) -> 0
B101: Other Non Current asset % Revenue
B102: Management Case | K102: 0 | L102: 0 | M102: 0 | N102: 0 | O102: 0 | P102: 0 | Q102: 0 | R102: 0 | S102: 0 | T102: 0
B103: Best Case | K103: 0 | L103: 0 | M103: 0 | N103: 0 | O103: 0 | P103: 0 | Q103: 0 | R103: 0 | S103: 0 | T103: 0
B104: Down Case | K104: 0 | L104: 0 | M104: 0 | N104: 0 | O104: 0 | P104: 0 | Q104: 0 | R104: 0 | S104: 0 | T104: 0
B105: ="Current Case - "&CHOOSE($K$4,B102,B103,B104) -> Current Case - Management Case | K105: =CHOOSE($K$4,K102,K103,K104) -> 0 | L105: =CHOOSE($K$4,L102,L103,L104) -> 0 | M105: =CHOOSE($K$4,M102,M103,M104) -> 0 | N105: =CHOOSE($K$4,N102,N103,N104) -> 0 | O105: =CHOOSE($K$4,O102,O103,O104) -> 0 | P105: =CHOOSE($K$4,P102,P103,P104) -> 0 | Q105: =CHOOSE($K$4,Q102,Q103,Q104) -> 0 | R105: =CHOOSE($K$4,R102,R103,R104) -> 0 | ... T105: =CHOOSE($K$4,T102,T103,T104) -> 0
B107: Non current tax assets (net) % Revenue
B108: Management Case | K108: 0 | L108: 0 | M108: 0 | N108: 0 | O108: 0 | P108: 0 | Q108: 0 | R108: 0 | S108: 0 | T108: 0
B109: Best Case | K109: 0 | L109: 0 | M109: 0 | N109: 0 | O109: 0 | P109: 0 | Q109: 0 | R109: 0 | S109: 0 | T109: 0
B110: Down Case | K110: 0 | L110: 0 | M110: 0 | N110: 0 | O110: 0 | P110: 0 | Q110: 0 | R110: 0 | S110: 0 | T110: 0
B111: ="Current Case - "&CHOOSE($K$4,B108,B109,B110) -> Current Case - Management Case | K111: =CHOOSE($K$4,K108,K109,K110) -> 0 | L111: =CHOOSE($K$4,L108,L109,L110) -> 0 | M111: =CHOOSE($K$4,M108,M109,M110) -> 0 | N111: =CHOOSE($K$4,N108,N109,N110) -> 0 | O111: =CHOOSE($K$4,O108,O109,O110) -> 0 | P111: =CHOOSE($K$4,P108,P109,P110) -> 0 | Q111: =CHOOSE($K$4,Q108,Q109,Q110) -> 0 | R111: =CHOOSE($K$4,R108,R109,R110) -> 0 | ... T111: =CHOOSE($K$4,T108,T109,T110) -> 0
B113: Deferred Assets Growth %
B114: Management Case | K114: 0 | L114: 0 | M114: 0 | N114: 0 | O114: 0 | P114: 0 | Q114: 0 | R114: 0 | S114: 0 | T114: 0
B115: Best Case | K115: 0 | L115: 0 | M115: 0 | N115: 0 | O115: 0 | P115: 0 | Q115: 0 | R115: 0 | S115: 0 | T115: 0
B116: Down Case | K116: 0 | L116: 0 | M116: 0 | N116: 0 | O116: 0 | P116: 0 | Q116: 0 | R116: 0 | S116: 0 | T116: 0
B117: ="Current Case - "&CHOOSE($K$4,B114,B115,B116) -> Current Case - Management Case | K117: =CHOOSE($K$4,K114,K115,K116) -> 0 | L117: =CHOOSE($K$4,L114,L115,L116) -> 0 | M117: =CHOOSE($K$4,M114,M115,M116) -> 0 | N117: =CHOOSE($K$4,N114,N115,N116) -> 0 | O117: =CHOOSE($K$4,O114,O115,O116) -> 0 | P117: =CHOOSE($K$4,P114,P115,P116) -> 0 | Q117: =CHOOSE($K$4,Q114,Q115,Q116) -> 0 | R117: =CHOOSE($K$4,R114,R115,R116) -> 0 | ... T117: =CHOOSE($K$4,T114,T115,T116) -> 0
A119: # | B119: Tax Rate
B121: Marginal Tax Rate
B122: Management Case | K122: 0.2512 | L122: 0.2512 | M122: 0.2512 | N122: 0.2512 | O122: 0.2512 | P122: 0.2512 | Q122: 0.2512 | R122: 0.2512 | S122: 0.2512 | T122: 0.2512
B123: Best Case | K123: 0.2512 | L123: 0.2512 | M123: 0.2512 | N123: 0.2512 | O123: 0.2512 | P123: 0.2512 | Q123: 0.2512 | R123: 0.2512 | S123: 0.2512 | T123: 0.2512
B124: Down Case | K124: 0.2512 | L124: 0.2512 | M124: 0.2512 | N124: 0.2512 | O124: 0.2512 | P124: 0.2512 | Q124: 0.2512 | R124: 0.2512 | S124: 0.2512 | T124: 0.2512
B125: ="Current Case - "&CHOOSE($K$4,B122,B123,B124) -> Current Case - Management Case | K125: =CHOOSE($K$4,K122,K123,K124) -> 0.2512 | L125: =CHOOSE($K$4,L122,L123,L124) -> 0.2512 | M125: =CHOOSE($K$4,M122,M123,M124) -> 0.2512 | N125: =CHOOSE($K$4,N122,N123,N124) -> 0.2512 | O125: =CHOOSE($K$4,O122,O123,O124) -> 0.2512 | P125: =CHOOSE($K$4,P122,P123,P124) -> 0.2512 | Q125: =CHOOSE($K$4,Q122,Q123,Q124) -> 0.2512 | R125: =CHOOSE($K$4,R122,R123,R124) -> 0.2512 | ... T125: =CHOOSE($K$4,T122,T123,T124) -> 0.2512
A127: # | B127: Short Term Loan Borrowings
B129: Growth YoY%
B130: Management Case | K130: 0.04 | L130: 0.04 | M130: 0.03 | N130: 0.03 | O130: 0.03 | P130: 0.0251 | Q130: 0.025 | R130: 0.025 | S130: 0.025 | T130: 0.025
B131: Best Case | K131: 0.04 | L131: 0.04 | M131: 0.04 | N131: 0.04 | O131: 0.04 | P131: 0.04 | Q131: 0.04 | R131: 0.04 | S131: 0.04 | T131: 0.04
B132: Down Case | K132: 0.04 | L132: 0.04 | M132: 0.04 | N132: 0.04 | O132: 0.04 | P132: 0.04 | Q132: 0.04 | R132: 0.04 | S132: 0.04 | T132: 0.04
...

Sheet Schedules
B2: ='Input Sheet'!C5 -> Marico Ltd
B3: Schedules
I4: Current Case
I8: Actual | J8: Explicit Forecast Period | O8: Maturity Period
B9: In INR crores unless started otherwise | D9: =ControlSheet!E8 -> 2020 | E9: =ControlSheet!F8 -> 2021 | F9: =ControlSheet!G8 -> 2022 | G9: =ControlSheet!H8 -> 2023 | H9: =ControlSheet!I8 -> 2024 | I9: =ControlSheet!J8 -> 2025 | J9: =ControlSheet!K8 -> 2026 | K9: =ControlSheet!L8 -> 2027 | ... S9: =ControlSheet!T8 -> 2035
A11: # | B11: Revenue Schedules
B13: Revenue | D13: ='P&l 25-24'!E6 -> 7315 | E13: ='P&l 25-24'!F6 -> 8048 | F13: ='P&l 25-24'!G6 -> 9512 | G13: ='P&l 25-24'!H6 -> 9764 | H13: ='P&l 25-24'!I6 -> 9653 | I13: ='P&l 25-24'!J6 -> 10831 | J13: =I13*(1+J15) -> 12347.34 | K13: =J13*(1+K15) -> 14014.231 | L13: =K13*(1+L15) -> 15836.081 | M13: =L13*(1+M15) -> 17815.591 | N13: =M13*(1+N15) -> 19953.462 | O13: =N13*(1+O15) -> 22347.877 | P13: =O13*(1+P15) -> 25029.623 | Q13: =P13*(1+Q15) -> 28033.177 | ... S13: =R13*(1+S15) -> 35164.818
B15: Growth YoY | E15: =E13/D13-1 -> 0.10020506 | F15: =F13/E13-1 -> 0.18190855 | G15: =G13/F13-1 -> 0.026492851 | H15: =H13/G13-1 -> -0.011368292 | I15: =I13/H13-1 -> 0.1220346 | J15: =ControlSheet!K18 -> 0.14 | K15: =ControlSheet!L18 -> 0.135 | L15: =ControlSheet!M18 -> 0.13 | M15: =ControlSheet!N18 -> 0.125 | N15: =ControlSheet!O18 -> 0.12 | O15: =ControlSheet!P18 -> 0.12 | P15: =ControlSheet!Q18 -> 0.12 | Q15: =ControlSheet!R18 -> 0.12 | ... S15: =ControlSheet!T18 -> 0.12
A17: # | B17: COGS Schedules
B20: COGS | D20: ='P&l 25-24'!E16*-1 -> 3745 | E20: ='P&l 25-24'!F16*-1 -> 4270 | F20: ='P&l 25-24'!G16*-1 -> 5436 | G20: ='P&l 25-24'!H16*-1 -> 5351 | H20: ='P&l 25-24'!I16*-1 -> 4748 | I20: ='P&l 25-24'!J16*-1 -> 5388 | J20: =J13*J22 -> 6420.6168 | K20: =K13*K22 -> 7287.4001 | L20: =L13*L22 -> 8234.7621 | M20: =M13*M22 -> 8907.7955 | N20: =N13*N22 -> 9976.731 | O20: =O13*O22 -> 11173.939 | P20: =P13*P22 -> 12514.811 | Q20: =Q13*Q22 -> 14016.589 | ... S20: =S13*S22 -> 17582.409
B22: COGS % Sales | D22: =D20/D13 -> 0.51196172 | E22: =E20/E13 -> 0.5305666 | F22: =F20/F13 -> 0.57148865 | G22: =G20/G13 -> 0.54803359 | H22: =H20/H13 -> 0.49186781 | I22: =I20/I13 -> 0.49746099 | J22: =ControlSheet!K29 -> 0.52 | K22: =ControlSheet!L29 -> 0.52 | L22: =ControlSheet!M29 -> 0.52 | M22: =ControlSheet!N29 -> 0.5 | N22: =ControlSheet!O29 -> 0.5 | O22: =ControlSheet!P29 -> 0.5 | P22: =ControlSheet!Q29 -> 0.5 | Q22: =ControlSheet!R29 -> 0.5 | ... S22: =ControlSheet!T29 -> 0.5
A24: # | B24: SG&A (Excluding Depreciation & Interest Expenses) Schedules
B26: Employee Benefit Cost
B28: Employee Benefit Cost | D28: ='Assumptions Working '!D203 -> 478 | E28: ='Assumptions Working '!E203 -> 570 | F28: ='Assumptions Working '!F203 -> 586 | G28: ='Assumptions Working '!G203 -> 653 | H28: ='Assumptions Working '!H203 -> 743 | I28: ='Assumptions Working '!I203 -> 831 | J28: =J$13*J29 -> 938.39784 | K28: =K$13*K29 -> 1065.0815 | L28: =L$13*L29 -> 1203.5421 | M28: =M$13*M29 -> 1353.9849 | N28: =N$13*N29 -> 1516.4631 | O28: =O$13*O29 -> 1698.4387 | P28: =P$13*P29 -> 1902.2513 | Q28: =Q$13*Q29 -> 2130.5215 | ... S28: =S$13*S29 -> 2672.5261
B29: Employee Benefit Cost % Revenue | D29: ='Assumptions Working '!D245 -> 0.065345181 | E29: ='Assumptions Working '!E245 -> 0.07082505 | F29: ='Assumptions Working '!F245 -> 0.061606392 | G29: ='Assumptions Working '!G245 -> 0.066878329 | H29: ='Assumptions Working '!H245 -> 0.07697089 | I29: ='Assumptions Working '!I245 -> 0.076724218 | J29: =ControlSheet!K37 -> 0.076 | K29: =ControlSheet!L37 -> 0.076 | L29: =ControlSheet!M37 -> 0.076 | M29: =ControlSheet!N37 -> 0.076 | N29: =ControlSheet!O37 -> 0.076 | O29: =ControlSheet!P37 -> 0.076 | P29: =ControlSheet!Q37 -> 0.076 | Q29: =ControlSheet!R37 -> 0.076 | ... S29: =ControlSheet!T37 -> 0.076
B31: Advertisement and sales promotion
B33: Advertisement and sales promotion | D33: ='Assumptions Working '!D204 -> 727 | E33: ='Assumptions Working '!E204 -> 698 | F33: ='Assumptions Working '!F204 -> 796 | G33: ='Assumptions Working '!G204 -> 842 | H33: ='Assumptions Working '!H204 -> 952 | I33: ='Assumptions Working '!I204 -> 1128 | J33: =J$13*J34 -> 1419.9441 | K33: =K$13*K34 -> 1611.6366 | L33: =L$13*L34 -> 1821.1493 | M33: =M$13*M34 -> 2048.793 | N33: =N$13*N34 -> 2294.6481 | O33: =O$13*O34 -> 2570.0059 | P33: =P$13*P34 -> 2878.4066 | Q33: =Q$13*Q34 -> 3223.8154 | ... S33: =S$13*S34 -> 4043.954
B34: Advertisement and sales promotion % Revenue | D34: ='Assumptions Working '!D248 -> 0.099384826 | E34: ='Assumptions Working '!E248 -> 0.086729622 | F34: ='Assumptions Working '!F248 -> 0.083683768 | G34: ='Assumptions Working '!G248 -> 0.08623515 | H34: ='Assumptions Working '!H248 -> 0.09862219 | I34: ='Assumptions Working '!I248 -> 0.10414551 | J34: =ControlSheet!K43 -> 0.115 | K34: =ControlSheet!L43 -> 0.115 | L34: =ControlSheet!M43 -> 0.115 | M34: =ControlSheet!N43 -> 0.115 | N34: =ControlSheet!O43 -> 0.115 | O34: =ControlSheet!P43 -> 0.115 | P34: =ControlSheet!Q43 -> 0.115 | Q34: =ControlSheet!R43 -> 0.115 | ... S34: =ControlSheet!T43 -> 0.115
B36: Freight and distribution expenses
B38: Freight and distribution expenses | D38: ='Assumptions Working '!D205 -> 294 | E38: ='Assumptions Working '!E205 -> 305 | F38: ='Assumptions Working '!F205 -> 354 | G38: ='Assumptions Working '!G205 -> 387 | H38: ='Assumptions Working '!H205 -> 416 | I38: ='Assumptions Working '!I205 -> 449 | J38: =J$13*J39 -> 493.8936 | K38: =K$13*K39 -> 560.56924 | L38: =L$13*L39 -> 633.44324 | M38: =M$13*M39 -> 712.62364 | N38: =N$13*N39 -> 798.13848 | O38: =O$13*O39 -> 893.9151 | P38: =P$13*P39 -> 1001.1849 | Q38: =Q$13*Q39 -> 1121.3271 | ... S38: =S$13*S39 -> 1406.5927
B39: Freight and distribution expenses % Revenue | D39: ='Assumptions Working '!D251 -> 0.040191388 | E39: ='Assumptions Working '!E251 -> 0.037897614 | F39: ='Assumptions Working '!F251 -> 0.037216148 | G39: ='Assumptions Working '!G251 -> 0.039635395 | H39: ='Assumptions Working '!H251 -> 0.043095411 | I39: ='Assumptions Working '!I251 -> 0.041455083 | J39: =ControlSheet!K49 -> 0.04 | K39: =ControlSheet!L49 -> 0.04 | L39: =ControlSheet!M49 -> 0.04 | M39: =ControlSheet!N49 -> 0.04 | N39: =ControlSheet!O49 -> 0.04 | O39: =ControlSheet!P49 -> 0.04 | P39: =ControlSheet!Q49 -> 0.04 | Q39: =ControlSheet!R49 -> 0.04 | ... S39: =ControlSheet!T49 -> 0.04
B41: Other Misc SG&A Expenses
B43: Other Misc SG&A Expenses | D43: ='Assumptions Working '!D253 -> 631 | E43: ='Assumptions Working '!E253 -> 603 | F43: ='Assumptions Working '!F253 -> 659 | G43: ='Assumptions Working '!G253 -> 721 | H43: ='Assumptions Working '!H253 -> 768 | I43: ='Assumptions Working '!I253 -> 896 | J43: =J$13*J44 -> 987.7872 | K43: =K$13*K44 -> 1121.1385 | L43: =L$13*L44 -> 1266.8865 | M43: =M$13*M44 -> 1425.2473 | N43: =N$13*N44 -> 1596.277 | O43: =O$13*O44 -> 1787.8302 | P43: =P$13*P44 -> 2002.3698 | Q43: =Q$13*Q44 -> 2242.6542 | ... S43: =S$13*S44 -> 2813.1854
B44: Other Misc SG&A Expenses % Revenue | D44: ='Assumptions Working '!C254 -> 0.07908372 | E44: ='Assumptions Working '!D254 -> 0.086261107 | F44: ='Assumptions Working '!E254 -> 0.074925447 | G44: ='Assumptions Working '!F254 -> 0.069280908 | H44: ='Assumptions Working '!G254 -> 0.073842687 | I44: ='Assumptions Working '!H254 -> 0.079560758 | J44: =ControlSheet!K55 -> 0.08 | K44: =ControlSheet!L55 -> 0.08 | L44: =ControlSheet!M55 -> 0.08 | M44: =ControlSheet!N55 -> 0.08 | N44: =ControlSheet!O55 -> 0.08 | O44: =ControlSheet!P55 -> 0.08 | P44: =ControlSheet!Q55 -> 0.08 | Q44: =ControlSheet!R55 -> 0.08 | ... S44: =ControlSheet!T55 -> 0.08
B46: Total SG&A (Excluding Depreciation & Interest Expenses) Schedules | D46: =D43+D38+D33+D28 -> 2130 | E46: =E43+E38+E33+E28 -> 2176 | F46: =F43+F38+F33+F28 -> 2395 | G46: =G43+G38+G33+G28 -> 2603 | H46: =H43+H38+H33+H28 -> 2879 | I46: =I43+I38+I33+I28 -> 3304 | J46: =J43+J38+J33+J28 -> 3840.0227 | K46: =K43+K38+K33+K28 -> 4358.4258 | ... S46: =S43+S38+S33+S28 -> 10936.258
B47: Total SG&A % Sales | D47: =D46/D$13 -> 0.2911825 | E47: =E46/E$13 -> 0.27037773 | F47: =F46/F$13 -> 0.25178722 | G47: =G46/G$13 -> 0.26659156 | H47: =H46/H$13 -> 0.29824925 | I47: =I46/I$13 -> 0.30505032 | J47: =J46/J$13 -> 0.311 | K47: =K46/K$13 -> 0.311 | ... S47: =S46/S$13 -> 0.311
A49: # | B49: Non Current Asset Schedules
B51: Property, Plant & Equipments
B53: Opening PP&E | D53: ='Balance Sheet'!C8 -> 572 | E53: ='Balance Sheet'!D8 -> 654 | F53: ='Balance Sheet'!E8 -> 572 | G53: ='Balance Sheet'!F8 -> 600 | H53: ='Balance Sheet'!G8 -> 633 | I53: ='Balance Sheet'!H8 -> 700 | J53: ='Balance Sheet'!I8 -> 710 | K53: =J56 -> 780.38694 | L53: =K56 -> 862.49563 | M53: =L56 -> 956.8621 | N53: =M56 -> 1063.8974 | O53: =N56 -> 1165.2318 | P53: =O56 -> 1280.1345 | Q53: =P56 -> 1433.5947 | R53: =Q56 -> 1631.374 | S53: =R56 -> 1806.8016
B54: ADD: Capex during the Year | J54: ='Assumptions Working '!C524 -> 197.55744 | K54: ='Assumptions Working '!D524 -> 224.22769 | L54: ='Assumptions Working '!E524 -> 253.37729 | M54: ='Assumptions Working '!F524 -> 285.04946 | N54: ='Assumptions Working '!G524 -> 299.30193 | O54: ='Assumptions Working '!H524 -> 335.21816 | P54: ='Assumptions Working '!I524 -> 400.47396 | Q54: ='Assumptions Working '!J524 -> 476.56402 | ... S54: ='Assumptions Working '!L524 -> 439.56022
B55: Less: Depreciation | I55: 114 | J55: =I55+J54/$C$109 -> 127.1705 | K55: =J55+K54/$C$109 -> 142.11901 | L55: =K55+L54/$C$109 -> 159.01083 | M55: =L55+M54/$C$109 -> 178.01413 | N55: =M55+N54/$C$109 -> 197.96759 | O55: =N55+O54/$C$109 -> 220.31547 | P55: =O55+P54/$C$109 -> 247.01373 | Q55: =P55+Q54/$C$109 -> 278.78466 | ... S55: =R55+S54/$C$109 -> 340.53241
B56: Closing PPE | J56: =J53+J54-J55 -> 780.38694 | K56: =K53+K54-K55 -> 862.49563 | L56: =L53+L54-L55 -> 956.8621 | M56: =M53+M54-M55 -> 1063.8974 | N56: =N53+N54-N55 -> 1165.2318 | O56: =O53+O54-O55 -> 1280.1345 | P56: =P53+P54-P55 -> 1433.5947 | Q56: =Q53+Q54-Q55 -> 1631.374 | ... S56: =S53+S54-S55 -> 1905.8294
B57: YoY Growth % | K57: =K56/J56-1 -> 0.10521535 | L57: =L56/K56-1 -> 0.10941095 | M57: =M56/L56-1 -> 0.11186077 | N57: =N56/M56-1 -> 0.095248225 | O57: =O56/N56-1 -> 0.098609306 | P57: =P56/O56-1 -> 0.11987821 | Q57: =Q56/P56-1 -> 0.13796044 | R57: =R56/Q56-1 -> 0.10753363 | S57: =S56/R56-1 -> 0.054808348
B59: Right of Use Asset
B60: Right of Use Asset | D60: ='Balance Sheet'!C10 -> 153 | E60: ='Balance Sheet'!D10 -> 146 | F60: ='Balance Sheet'!E10 -> 180 | G60: ='Balance Sheet'!F10 -> 178 | H60: ='Balance Sheet'!G10 -> 175 | I60: ='Balance Sheet'!H10 -> 209 | J60: ='Balance Sheet'!I10 -> 230 | K60: =J63 -> 177 | L60: =K63 -> 124 | M60: =L63 -> 71 | N60: =M63 -> 18 | O60: =N63 -> 0 | P60: =O63 -> 0 | Q60: =P63 -> 0 | R60: =Q63 -> 0 | S60: =R63 -> 0
B61: Additional during the Year | J61: 0 | K61: 0 | L61: 0 | M61: 0 | N61: 0 | O61: 0 | P61: 0 | Q61: 0 | R61: 0 | S61: 0
B62: Less: Depreciation | I62: 53 | J62: =I62+J61/$C$109 -> 53 | K62: =J62+K61/$C$109 -> 53 | L62: =K62+L61/$C$109 -> 53 | M62: =L62+M61/$C$109 -> 53 | N62: 18 | O62: 0 | P62: 0 | Q62: 0 | R62: 0 | S62: 0
B63: Closing ROU Asset | J63: =J60+J61-J62 -> 177 | K63: =K60+K61-K62 -> 124 | L63: =L60+L61-L62 -> 71 | M63: =M60+M61-M62 -> 18 | N63: =N60+N61-N62 -> 0 | O63: =O60+O61-O62 -> 0 | P63: =P60+P61-P62 -> 0 | Q63: =Q60+Q61-Q62 -> 0 | ... S63: =S60+S61-S62 -> 0
B64: YoY Growth % | K64: =K63/J63-1 -> -0.29943503 | L64: =L63/K63-1 -> -0.42741935 | M64: =M63/L63-1 -> -0.74647887 | N64: =N63/M63-1 -> -1 | O64: =IF(N63=0, 0, (O63/N63)-1) -> 0 | P64: =IF(O63=0, 0, (P63/O63)-1) -> 0 | Q64: =IF(P63=0, 0, (Q63/P63)-1) -> 0 | R64: =IF(Q63=0, 0, (R63/Q63)-1) -> 0 | S64: =IF(R63=0, 0, (S63/R63)-1) -> 0
B66: YoY Growth % | J66: =ControlSheet!K69 -> 0 | K66: =ControlSheet!L69 -> 0 | L66: =ControlSheet!M69 -> 0 | M66: =ControlSheet!N69 -> 0 | N66: =ControlSheet!O69 -> 0 | O66: =ControlSheet!P69 -> 0 | P66: =ControlSheet!Q69 -> 0 | Q66: =ControlSheet!R69 -> 0 | ... S66: =ControlSheet!T69 -> 0
B68: Capital Working In Progress
B69: Capital Working In Progress | D69: ='Balance Sheet'!D9 -> 58 | E69: ='Balance Sheet'!E9 -> 24 | F69: ='Balance Sheet'!F9 -> 39 | G69: ='Balance Sheet'!G9 -> 67 | H69: ='Balance Sheet'!H9 -> 44 | I69: ='Balance Sheet'!I9 -> 40 | J69: =I69*(1+J70) -> 40 | K69: =J69*(1+K70) -> 40 | L69: =K69*(1+L70) -> 40 | M69: =L69*(1+M70) -> 40 | N69: =M69*(1+N70) -> 40 | O69: =N69*(1+O70) -> 40 | P69: =O69*(1+P70) -> 40 | Q69: =P69*(1+Q70) -> 40 | ... S69: =R69*(1+S70) -> 40
B70: YoY Growth % | J70: =ControlSheet!K73 -> 0 | K70: =ControlSheet!L73 -> 0 | L70: =ControlSheet!M73 -> 0 | M70: =ControlSheet!N73 -> 0 | N70: =ControlSheet!O73 -> 0 | O70: =ControlSheet!P73 -> 0 | P70: =ControlSheet!Q73 -> 0 | Q70: =ControlSheet!R73 -> 0 | ... S70: =ControlSheet!T73 -> 0
B72: Intangible Assets (excluding goodwill)
B73: Intangible Assets (excluding goodwill) | J73: ='Balance Sheet'!I13 -> 946 | K73: =J76 -> 935 | L73: =K76 -> 924 | M73: =L76 -> 913 | N73: =M76 -> 902 | O73: =N76 -> 891 | P73: =O76 -> 880 | Q73: =P76 -> 869 | R73: =Q76 -> 858 | S73: =R76 -> 847
B74: Additional during the Year | J74: =J73*J79 -> 0 | K74: =K73*K79 -> 0 | L74: =L73*L79 -> 0 | M74: =M73*M79 -> 0 | N74: =N73*N79 -> 0 | O74: =O73*O79 -> 0 | P74: =P73*P79 -> 0 | Q74: =Q73*Q79 -> 0 | ... S74: =S73*S79 -> 0
B75: Less: Depreciation | I75: 11 | J75: =I75+J74/$C$109 -> 11 | K75: =J75+K74/$C$109 -> 11 | L75: =K75+L74/$C$109 -> 11 | M75: =L75+M74/$C$109 -> 11 | N75: =M75+N74/$C$109 -> 11 | O75: =N75+O74/$C$109 -> 11 | P75: =O75+P74/$C$109 -> 11 | Q75: =P75+Q74/$C$109 -> 11 | ... S75: =R75+S74/$C$109 -> 11
B76: Closing Intangible Assets | J76: =J73+J74-J75 -> 935 | K76: =K73+K74-K75 -> 924 | L76: =L73+L74-L75 -> 913 | M76: =M73+M74-M75 -> 902 | N76: =N73+N74-N75 -> 891 | O76: =O73+O74-O75 -> 880 | P76: =P73+P74-P75 -> 869 | Q76: =Q73+Q74-Q75 -> 858 | ... S76: =S73+S74-S75 -> 836
B77: YoY Intangible Assets Growth % | K77: =K76/J76-1 -> -0.011764706 | L77: =L76/K76-1 -> -0.011904762 | M77: =M76/L76-1 -> -0.012048193 | N77: =N76/M76-1 -> -0.012195122 | O77: =O76/N76-1 -> -0.012345679 | P77: =P76/O76-1 -> -0.0125 | Q77: =Q76/P76-1 -> -0.012658228 | R77: =R76/Q76-1 -> -0.012820513 | S77: =S76/R76-1 -> -0.012987013
B79: YoY Growth % | J79: =ControlSheet!K87 -> 0 | K79: =ControlSheet!L87 -> 0 | L79: =ControlSheet!M87 -> 0 | M79: =ControlSheet!N87 -> 0 | N79: =ControlSheet!O87 -> 0 | O79: =ControlSheet!P87 -> 0 | P79: =ControlSheet!Q87 -> 0 | Q79: =ControlSheet!R87 -> 0 | ... S79: =ControlSheet!T87 -> 0
B81: Investment Property
B82: Investment Property | D82: ='Balance Sheet'!D11 -> 17 | E82: ='Balance Sheet'!E11 -> 17 | F82: ='Balance Sheet'!F11 -> 22 | G82: ='Balance Sheet'!G11 -> 16 | H82: ='Balance Sheet'!H11 -> 15 | I82: ='Balance Sheet'!I11 -> 15 | J82: =I82*(1+J83) -> 15 | K82: =J82*(1+K83) -> 15 | L82: =K82*(1+L83) -> 15 | M82: =L82*(1+M83) -> 15 | N82: =M82*(1+N83) -> 15 | O82: =N82*(1+O83) -> 15 | P82: =O82*(1+P83) -> 15 | Q82: =P82*(1+Q83) -> 15 | ... S82: =R82*(1+S83) -> 15
B83: YoY Growth % | E83: =E82/D82-1 -> 0 | F83: =F82/E82-1 -> 0.29411765 | G83: =G82/F82-1 -> -0.27272727 | H83: =H82/G82-1 -> -0.0625 | I83: =I82/H82-1 -> 0 | J83: =ControlSheet!K79 -> 0 | K83: =ControlSheet!L79 -> 0 | L83: =ControlSheet!M79 -> 0 | M83: =ControlSheet!N79 -> 0 | N83: =ControlSheet!O79 -> 0 | O83: =ControlSheet!P79 -> 0 | P83: =ControlSheet!Q79 -> 0 | Q83: =ControlSheet!R79 -> 0 | ... S83: =ControlSheet!T79 -> 0
B85: Intangible Non Current Asset
B87: Goodwill
B88: Goodwill | D88: ='Balance Sheet'!D12 -> 538 | E88: ='Balance Sheet'!E12 -> 613 | F88: ='Balance Sheet'!F12 -> 654 | G88: ='Balance Sheet'!G12 -> 862 | H88: ='Balance Sheet'!H12 -> 863 | I88: ='Balance Sheet'!I12 -> 857 | J88: =I88*(1+J89) -> 857 | K88: =J88*(1+K89) -> 857 | L88: =K88*(1+L89) -> 857 | M88: =L88*(1+M89) -> 857 | N88: =M88*(1+N89) -> 857 | O88: =N88*(1+O89) -> 857 | P88: =O88*(1+P89) -> 857 | Q88: =P88*(1+Q89) -> 857 | ... S88: =R88*(1+S89) -> 857
B89: YoY Growth % | E89: =E88/D88-1 -> 0.1394052 | F89: =F88/E88-1 -> 0.066884176 | G89: =G88/F88-1 -> 0.31804281 | H89: =H88/G88-1 -> 0.0011600928 | I89: =I88/H88-1 -> -0.0069524913 | J89: =ControlSheet!K93 -> 0 | K89: =ControlSheet!L93 -> 0 | L89: =ControlSheet!M93 -> 0 | M89: =ControlSheet!N93 -> 0 | N89: =ControlSheet!O93 -> 0 | O89: =ControlSheet!P93 -> 0 | P89: =ControlSheet!Q93 -> 0 | Q89: =ControlSheet!R93 -> 0 | ... S89: =ControlSheet!T93 -> 0
B91: Non Current Financial Assets
B92: Non Current Financial Asset | D92: ='Balance Sheet'!D15 -> 107 | E92: ='Balance Sheet'!E15 -> 271 | F92: ='Balance Sheet'!F15 -> 208 | G92: ='Balance Sheet'!G15 -> 554 | H92: ='Balance Sheet'!H15 -> 447 | I92: ='Balance Sheet'!I15 -> 243 | J92: =I92*(1+J93) -> 243 | K92: =J92*(1+K93) -> 243 | L92: =K92*(1+L93) -> 243 | M92: =L92*(1+M93) -> 243 | N92: =M92*(1+N93) -> 243 | O92: =N92*(1+O93) -> 243 | P92: =O92*(1+P93) -> 243 | Q92: =P92*(1+Q93) -> 243 | ... S92: =R92*(1+S93) -> 243
B93: YoY Growth % | E93: =E92/D92-1 -> 1.5327103 | F93: =F92/E92-1 -> -0.23247232 | G93: =G92/F92-1 -> 1.6634615 | H93: =H92/G92-1 -> -0.19314079 | I93: =I92/H92-1 -> -0.45637584 | J93: =ControlSheet!K99 -> 0 | K93: =ControlSheet!L99 -> 0 | L93: =ControlSheet!M99 -> 0 | M93: =ControlSheet!N99 -> 0 | N93: =ControlSheet!O99 -> 0 | O93: =ControlSheet!P99 -> 0 | P93: =ControlSheet!Q99 -> 0 | Q93: =ControlSheet!R99 -> 0 | ... S93: =ControlSheet!T99 -> 0
B95: Other Non Current asset
B96: Non Current Financial Asset | D96: ='Balance Sheet'!D22 -> 26 | E96: ='Balance Sheet'!E22 -> 26 | F96: ='Balance Sheet'!F22 -> 30 | G96: ='Balance Sheet'!G22 -> 46 | H96: ='Balance Sheet'!H22 -> 40 | I96: ='Balance Sheet'!I22 -> 49 | J96: =I96*(1+J97) -> 49 | K96: =J96*(1+K97) -> 49 | L96: =K96*(1+L97) -> 49 | M96: =L96*(1+M97) -> 49 | N96: =M96*(1+N97) -> 49 | O96: =N96*(1+O97) -> 49 | P96: =O96*(1+P97) -> 49 | Q96: =P96*(1+Q97) -> 49 | ... S96: =R96*(1+S97) -> 49
B97: % of Revenue | E97: =E96/D96-1 -> 0 | F97: =F96/E96-1 -> 0.15384615 | G97: =G96/F96-1 -> 0.53333333 | H97: =H96/G96-1 -> -0.13043478 | I97: =I96/H96-1 -> 0.225 | J97: =ControlSheet!K105 -> 0 | K97: =ControlSheet!L105 -> 0 | L97: =ControlSheet!M105 -> 0 | M97: =ControlSheet!N105 -> 0 | N97: =ControlSheet!O105 -> 0 | O97: =ControlSheet!P105 -> 0 | P97: =ControlSheet!Q105 -> 0 | Q97: =ControlSheet!R105 -> 0 | ... S97: =ControlSheet!T105 -> 0
B99: Non current tax assets (net)
B100: Non Current Financial Asset | D100: ='Balance Sheet'!D21 -> 45 | E100: ='Balance Sheet'!E21 -> 55 | F100: ='Balance Sheet'!F21 -> 57 | G100: ='Balance Sheet'!G21 -> 67 | H100: ='Balance Sheet'!H21 -> 95 | I100: ='Balance Sheet'!I21 -> 108 | J100: =I100*(1+J101) -> 108 | K100: =J100*(1+K101) -> 108 | L100: =K100*(1+L101) -> 108 | M100: =L100*(1+M101) -> 108 | N100: =M100*(1+N101) -> 108 | O100: =N100*(1+O101) -> 108 | P100: =O100*(1+P101) -> 108 | Q100: =P100*(1+Q101) -> 108 | ... S100: =R100*(1+S101) -> 108
B101: % of Revenue | E101: =E100/E13 -> 0.006833996 | F101: =F100/F13 -> 0.0059924306 | G101: =G100/G13 -> 0.0068619418 | H101: =H100/H13 -> 0.0098415001 | I101: =I100/I13 -> 0.0099713785 | J101: =ControlSheet!K111 -> 0 | K101: =ControlSheet!L111 -> 0 | L101: =ControlSheet!M111 -> 0 | M101: =ControlSheet!N111 -> 0 | N101: =ControlSheet!O111 -> 0 | O101: =ControlSheet!P111 -> 0 | P101: =ControlSheet!Q111 -> 0 | Q101: =ControlSheet!R111 -> 0 | ... S101: =ControlSheet!T111 -> 0
B103: Deferred Tax Assets
B104: Non Current Financial Asset | D104: ='Balance Sheet'!D20 -> 159 | E104: ='Balance Sheet'!E20 -> 186 | F104: ='Balance Sheet'!F20 -> 187 | G104: ='Balance Sheet'!G20 -> 146 | H104: ='Balance Sheet'!H20 -> 68 | I104: ='Balance Sheet'!I20 -> 57 | J104: =I104*(1+J105) -> 57 | K104: =J104*(1+K105) -> 57 | L104: =K104*(1+L105) -> 57 | M104: =L104*(1+M105) -> 57 | N104: =M104*(1+N105) -> 57 | O104: =N104*(1+O105) -> 57 | P104: =O104*(1+P105) -> 57 | Q104: =P104*(1+Q105) -> 57 | ... S104: =R104*(1+S105) -> 57
B105: YoY Growth % | E105: =E104/D104-1 -> 0.16981132 | F105: =F104/E104-1 -> 0.0053763441 | G105: =G104/F104-1 -> -0.21925134 | H105: =H104/G104-1 -> -0.53424658 | I105: =I104/H104-1 -> -0.16176471 | J105: =ControlSheet!K117 -> 0 | K105: =ControlSheet!L117 -> 0 | L105: =ControlSheet!M117 -> 0 | M105: =ControlSheet!N117 -> 0 | N105: =ControlSheet!O117 -> 0 | O105: =ControlSheet!P117 -> 0 | P105: =ControlSheet!Q117 -> 0 | Q105: =ControlSheet!R117 -> 0 | ... S105: =ControlSheet!T117 -> 0
A107: # | B107: Depreciation Schedules
C109: 15
B110: Total Depreciation | J110: =SUM(J55,J62,J75,) -> 191.1705 | K110: =SUM(K55,K62,K75,) -> 206.11901 | L110: =SUM(L55,L62,L75,) -> 223.01083 | M110: =SUM(M55,M62,M75,) -> 242.01413 | N110: =SUM(N55,N62,N75,) -> 226.96759 | O110: =SUM(O55,O62,O75,) -> 231.31547 | P110: =SUM(P55,P62,P75,) -> 258.01373 | Q110: =SUM(Q55,Q62,Q75,) -> 289.78466 | ... S110: =SUM(S55,S62,S75,) -> 351.53241
B111: Total Net Depreciable Fixed Asset | J111: =SUM(J56,J63,J76) -> 1892.3869 | K111: =SUM(K56,K63,K76) -> 1910.4956 | L111: =SUM(L56,L63,L76) -> 1940.8621 | M111: =SUM(M56,M63,M76) -> 1983.8974 | N111: =SUM(N56,N63,N76) -> 2056.2318 | O111: =SUM(O56,O63,O76) -> 2160.1345 | P111: =SUM(P56,P63,P76) -> 2302.5947 | Q111: =SUM(Q56,Q63,Q76) -> 2489.374 | ... S111: =SUM(S56,S63,S76) -> 2741.8294
B113: Depreciation % Sales | J113: =J110/J13 -> 0.015482727 | K113: =K110/K13 -> 0.014707836 | L113: =L110/L13 -> 0.014082451 | M113: =M110/M13 -> 0.013584401 | N113: =N110/N13 -> 0.011374848 | O113: =O110/O13 -> 0.010350668 | P113: =P110/P13 -> 0.010308335 | Q113: =Q110/Q13 -> 0.010337204 | ... S113: =S110/S13 -> 0.0099967078
B114: Depreciation % Net Fixed Assets | J114: =J110/J111 -> 0.10102083 | K114: =K110/K111 -> 0.10788772 | L114: =L110/L111 -> 0.11490297 | M114: =M110/M111 -> 0.12198923 | N114: =N110/N111 -> 0.11038035 | O114: =O110/O111 -> 0.10708383 | P114: =P110/P111 -> 0.11205347 | Q114: =Q110/Q111 -> 0.11640865 | ... S114: =S110/S111 -> 0.1282109
B116: Depreciation Waterfall Schedule
B118: =I9 -> 2025 | I118: =SUM(I55,I62,I75) -> 178 | J118: =I118 -> 178 | K118: =J118 -> 178 | L118: =K118 -> 178 | M118: =L118 -> 178 | N118: =M118 -> 178 | O118: =N118 -> 178 | P118: =O118 -> 178 | Q118: =P118 -> 178 | ... S118: =R118 -> 178
B119: =B118+1 -> 2026 | J119: =J110-J118 -> 13.170496 | K119: =K110-K118 -> 28.119009 | L119: =L110-L118 -> 45.010829 | M119: =M110-M118 -> 64.014126 | N119: =N110-N118 -> 48.967588 | O119: =O110-O118 -> 53.315465 | P119: =P110-P118 -> 80.013729 | Q119: =Q110-Q118 -> 111.78466 | ... S119: =S110-S118 -> 173.53241
B120: =B119+1 -> 2027 | K120: =K110-J110 -> 14.948513 | L120: =L110-K110 -> 16.89182 | M120: =M110-L110 -> 19.003297 | N120: =N110-M110 -> -15.046538 | O120: =O110-N110 -> 4.3478774 | P120: =P110-O110 -> 26.698264 | Q120: =Q110-P110 -> 31.770934 | R120: =R110-Q110 -> 32.443731 | S120: =S110-R110 -> 29.304015
B121: =B120+1 -> 2028 | L121: =L110-K110 -> 16.89182 | M121: =M110-L110 -> 19.003297 | N121: =N110-M110 -> -15.046538 | O121: =O110-N110 -> 4.3478774 | P121: =P110-O110 -> 26.698264 | Q121: =Q110-P110 -> 31.770934 | R121: =R110-Q110 -> 32.443731 | S121: =S110-R110 -> 29.304015
B122: =B121+1 -> 2029 | M122: =M110-L110 -> 19.003297 | N122: =N110-M110 -> -15.046538 | O122: =O110-N110 -> 4.3478774 | P122: =P110-O110 -> 26.698264 | Q122: =Q110-P110 -> 31.770934 | R122: =R110-Q110 -> 32.443731 | S122: =S110-R110 -> 29.304015
B123: =B122+1 -> 2030 | N123: =N110-M110 -> -15.046538 | O123: =O110-N110 -> 4.3478774 | P123: =P110-O110 -> 26.698264 | Q123: =Q110-P110 -> 31.770934 | R123: =R110-Q110 -> 32.443731 | S123: =S110-R110 -> 29.304015
B124: Total Depreciation | I124: =SUM(I118:I123) -> 178 | J124: =SUM(J118:J123) -> 191.1705 | K124: =SUM(K118:K123) -> 221.06752 | L124: =SUM(L118:L123) -> 256.79447 | M124: =SUM(M118:M123) -> 299.02402 | N124: =SUM(N118:N123) -> 166.78144 | O124: =SUM(O118:O123) -> 248.70697 | P124: =SUM(P118:P123) -> 364.80679 | ... S124: =SUM(S118:S123) -> 468.74847
A127: # | B127: Tax Expense Schedules
B129: Revenue | I129: ='3 Statement Model'!I13 -> 10831 | J129: ='3 Statement Model'!J13 -> 12347.34 | K129: ='3 Statement Model'!K13 -> 14014.231 | L129: ='3 Statement Model'!L13 -> 15836.081 | M129: ='3 Statement Model'!M13 -> 17815.591 | N129: ='3 Statement Model'!N13 -> 19953.462 | O129: ='3 Statement Model'!O13 -> 22347.877 | P129: ='3 Statement Model'!P13 -> 25029.623 | ... S129: ='3 Statement Model'!S13 -> 35164.818
B130: Less: Cost of Goods Sold | I130: ='3 Statement Model'!I14*-1 -> -5388 | J130: ='3 Statement Model'!J14*-1 -> -6420.6168 | K130: ='3 Statement Model'!K14*-1 -> -7287.4001 | L130: ='3 Statement Model'!L14*-1 -> -8234.7621 | M130: ='3 Statement Model'!M14*-1 -> -8907.7955 | N130: ='3 Statement Model'!N14*-1 -> -9976.731 | O130: ='3 Statement Model'!O14*-1 -> -11173.939 | P130: ='3 Statement Model'!P14*-1 -> -12514.811 | ... S130: ='3 Statement Model'!S14*-1 -> -17582.409
B131: Less: SG&A Expenses | I131: =SUM('3 Statement Model'!I20:I23)*-1 -> -3304 | J131: =SUM('3 Statement Model'!J20:J23)*-1 -> -3840.0227 | K131: =SUM('3 Statement Model'!K20:K23)*-1 -> -4358.4258 | L131: =SUM('3 Statement Model'!L20:L23)*-1 -> -4925.0212 | M131: =SUM('3 Statement Model'!M20:M23)*-1 -> -5540.6488 | N131: =SUM('3 Statement Model'!N20:N23)*-1 -> -6205.5267 | O131: =SUM('3 Statement Model'!O20:O23)*-1 -> -6950.1899 | P131: =SUM('3 Statement Model'!P20:P23)*-1 -> -7784.2127 | ... S131: =SUM('3 Statement Model'!S20:S23)*-1 -> -10936.258
B132: Less: Depreciation & Amortization | I132: ='3 Statement Model'!I29*-1 -> -178 | J132: ='3 Statement Model'!J29*-1 -> -191.1705 | K132: ='3 Statement Model'!K29*-1 -> -206.11901 | L132: ='3 Statement Model'!L29*-1 -> -223.01083 | M132: ='3 Statement Model'!M29*-1 -> -242.01413 | N132: ='3 Statement Model'!N29*-1 -> -226.96759 | O132: ='3 Statement Model'!O29*-1 -> -231.31547 | P132: ='3 Statement Model'!P29*-1 -> -258.01373 | ... S132: ='3 Statement Model'!S29*-1 -> -351.53241
B133: Less: Interest Expenses | I133: ='3 Statement Model'!I34*-1 -> -53 | J133: ='3 Statement Model'!J34*-1 -> -54.55585 | K133: ='3 Statement Model'!K34*-1 -> -65.903927 | L133: ='3 Statement Model'!L34*-1 -> -64.728229 | M133: ='3 Statement Model'!M34*-1 -> -63.096885 | N133: ='3 Statement Model'!N34*-1 -> -70.816974 | O133: ='3 Statement Model'!O34*-1 -> -72.470974 | P133: ='3 Statement Model'!P34*-1 -> -74.167018 | ... S133: ='3 Statement Model'!S34*-1 -> -104.00309
B134: Add: Other Income | I134: ='3 Statement Model'!I35 -> 208 | J134: ='3 Statement Model'!J35 -> 185.2101 | K134: ='3 Statement Model'!K35 -> 210.21346 | L134: ='3 Statement Model'!L35 -> 237.54121 | M134: ='3 Statement Model'!M35 -> 267.23387 | N134: ='3 Statement Model'!N35 -> 299.30193 | O134: ='3 Statement Model'!O35 -> 335.21816 | P134: ='3 Statement Model'!P35 -> 375.44434 | ... S134: ='3 Statement Model'!S35 -> 527.47227
B135: Earning Before Tax | I135: =SUM(I129:I134) -> 2116 | J135: =SUM(J129:J134) -> 2026.1842 | K135: =SUM(K129:K134) -> 2306.5955 | L135: =SUM(L129:L134) -> 2626.0998 | M135: =SUM(M129:M134) -> 3329.2696 | N135: =SUM(N129:N134) -> 3772.7217 | O135: =SUM(O129:O134) -> 4255.1805 | P135: =SUM(P129:P134) -> 4773.8623 | ... S135: =SUM(S129:S134) -> 6718.0873
B136: Less: Tax Expenses | I136: ='3 Statement Model'!I38 -> 458 | J136: =J135*J139 -> 508.97747 | K136: =K135*K139 -> 579.4168 | L136: =L135*L139 -> 659.67628 | M136: =M135*M139 -> 836.31251 | N136: =N135*N139 -> 947.70769 | O136: =O135*O139 -> 1068.9014 | P136: =P135*P139 -> 1199.1942 | Q136: =Q135*Q139 -> 1342.9335 | ... S136: =S135*S139 -> 1687.5835
B137: Net Income | I137: =SUM(I135:I136) -> 2574 | J137: =SUM(J135:J136) -> 2535.1617 | K137: =SUM(K135:K136) -> 2886.0124 | L137: =SUM(L135:L136) -> 3285.7761 | M137: =SUM(M135:M136) -> 4165.5821 | N137: =SUM(N135:N136) -> 4720.4294 | O137: =SUM(O135:O136) -> 5324.0819 | P137: =SUM(P135:P136) -> 5973.0565 | ... S137: =SUM(S135:S136) -> 8405.6709
B139: Marginal Tax Rate | I139: =I136/I135 -> 0.21644612 | J139: =ControlSheet!K125 -> 0.2512 | K139: =ControlSheet!L125 -> 0.2512 | L139: =ControlSheet!M125 -> 0.2512 | M139: =ControlSheet!N125 -> 0.2512 | N139: =ControlSheet!O125 -> 0.2512 | O139: =ControlSheet!P125 -> 0.2512 | P139: =ControlSheet!Q125 -> 0.2512 | Q139: =ControlSheet!R125 -> 0.2512 | ... S139: =ControlSheet!T125 -> 0.2512
A141: # | B141: Other Equity Schedules
B143: Other Equity - Beginning of the Year | J143: ='3 Statement Model'!I81 -> 3846 | K143: =J146 -> 4149.4413 | L143: =K146 -> 4494.8771 | M143: =L146 -> 4888.1618 | N143: =M146 -> 5386.7532 | O143: =N146 -> 5810.5053 | P143: =O146 -> 6288.4472 | Q143: =P146 -> 6824.6474 | R143: =Q146 -> 7425.1183 | S143: =R146 -> 8097.9075
B144: Add: Net Profit | J144: ='3 Statement Model'!J39 -> 1517.2067 | K144: ='3 Statement Model'!K39 -> 1727.1787 | L144: ='3 Statement Model'!L39 -> 1966.4236 | M144: ='3 Statement Model'!M39 -> 2492.957 | N144: ='3 Statement Model'!N39 -> 2825.014 | O144: ='3 Statement Model'!O39 -> 3186.2792 | P144: ='3 Statement Model'!P39 -> 3574.6681 | Q144: ='3 Statement Model'!Q39 -> 4003.1394 | ... S144: ='3 Statement Model'!S39 -> 5030.5038
B145: Less: Dividend Paid | J145: =-J144*J148 -> -1213.7654 | K145: =-K144*K148 -> -1381.743 | L145: =-L144*L148 -> -1573.1388 | M145: =-M144*M148 -> -1994.3656 | N145: =-N144*N148 -> -2401.2619 | O145: =-O144*O148 -> -2708.3373 | P145: =-P144*P148 -> -3038.4679 | Q145: =-Q144*Q148 -> -3402.6685 | ... S145: =-S144*S148 -> -4275.9282
B146: Retained Earning - Ending of the Year | J146: =SUM(J143:J145) -> 4149.4413 | K146: =SUM(K143:K145) -> 4494.8771 | L146: =SUM(L143:L145) -> 4888.1618 | M146: =SUM(M143:M145) -> 5386.7532 | N146: =SUM(N143:N145) -> 5810.5053 | O146: =SUM(O143:O145) -> 6288.4472 | P146: =SUM(P143:P145) -> 6824.6474 | Q146: =SUM(Q143:Q145) -> 7425.1183 | ... S146: =SUM(S143:S145) -> 8852.4831
B148: Dividend Payout Rate % | J148: =ControlSheet!K165 -> 0.8 | K148: =ControlSheet!L165 -> 0.8 | L148: =ControlSheet!M165 -> 0.8 | M148: =ControlSheet!N165 -> 0.8 | N148: =ControlSheet!O165 -> 0.85 | O148: =ControlSheet!P165 -> 0.85 | P148: =ControlSheet!Q165 -> 0.85 | Q148: =ControlSheet!R165 -> 0.85 | ... S148: =ControlSheet!T165 -> 0.85
...

Sheet 3 Statement Model
B2: ='Input Sheet'!C5 -> Marico Ltd
B3: 3 Statement Model
K4: Current Case
D8: Actual | J8: Explicit Forecast Period | O8: Maturity Period | U8: 5 Year | V8: 3 Year
B9: In INR crores unless started otherwise | D9: =Schedules!D9 -> 2020 | E9: =Schedules!E9 -> 2021 | F9: =Schedules!F9 -> 2022 | G9: =Schedules!G9 -> 2023 | H9: =Schedules!H9 -> 2024 | I9: =Schedules!I9 -> 2025 | J9: =I9+1 -> 2026 | K9: =J9+1 -> 2027 | L9: =K9+1 -> 2028 | M9: =L9+1 -> 2029 | N9: =M9+1 -> 2030 | O9: =N9+1 -> 2031 | P9: =O9+1 -> 2032 | Q9: =P9+1 -> 2033 | ... S9: =R9+1 -> 2035
A11: # | B11: Income Statement
B13: Revenue | D13: =Schedules!D13 -> 7315 | E13: =Schedules!E13 -> 8048 | F13: =Schedules!F13 -> 9512 | G13: =Schedules!G13 -> 9764 | H13: =Schedules!H13 -> 9653 | I13: =Schedules!I13 -> 10831 | J13: =Schedules!J13 -> 12347.34 | K13: =Schedules!K13 -> 14014.231 | ... S13: =Schedules!S13 -> 35164.818 | U13: =_xlfn.RRI(5,I13,N13) -> 0.12997788 | V13: =_xlfn.RRI(3,K13,N13) -> 0.12499259
B14: Less: Cost of Goods Sold | D14: =Schedules!D20 -> 3745 | E14: =Schedules!E20 -> 4270 | F14: =Schedules!F20 -> 5436 | G14: =Schedules!G20 -> 5351 | H14: =Schedules!H20 -> 4748 | I14: =Schedules!I20 -> 5388 | J14: =Schedules!J20 -> 6420.6168 | K14: =Schedules!K20 -> 7287.4001 | ... S14: =Schedules!S20 -> 17582.409 | U14: =_xlfn.RRI(5,I14,N14) -> 0.13112899 | V14: =_xlfn.RRI(3,K14,N14) -> 0.11038065
B15: Gross Profit | D15: =D13-D14 -> 3570 | E15: =E13-E14 -> 3778 | F15: =F13-F14 -> 4076 | G15: =G13-G14 -> 4413 | H15: =H13-H14 -> 4905 | I15: =I13-I14 -> 5443 | J15: =J13-J14 -> 5926.7232 | K15: =K13-K14 -> 6726.8308 | ... S15: =S13-S14 -> 17582.409 | U15: =_xlfn.RRI(5,I15,N15) -> 0.12883375 | V15: =_xlfn.RRI(3,K15,N15) -> 0.14040537
B17: Gross Margin | D17: =D15/D13 -> 0.48803828 | E17: =E15/E13 -> 0.4694334 | F17: =F15/F13 -> 0.42851135 | G17: =G15/G13 -> 0.45196641 | H17: =H15/H13 -> 0.50813219 | I17: =I15/I13 -> 0.50253901 | J17: =J15/J13 -> 0.48 | K17: =K15/K13 -> 0.48 | ... S17: =S15/S13 -> 0.5
B19: Less: SG&A Expenses (Excluding Depreciation & Interest)
B20: =Schedules!B26 -> Employee Benefit Cost | D20: =Schedules!D28 -> 478 | E20: =Schedules!E28 -> 570 | F20: =Schedules!F28 -> 586 | G20: =Schedules!G28 -> 653 | H20: =Schedules!H28 -> 743 | I20: =Schedules!I28 -> 831 | J20: =Schedules!J28 -> 938.39784 | K20: =Schedules!K28 -> 1065.0815 | ... S20: =Schedules!S28 -> 2672.5261 | U20: =_xlfn.RRI(5,I20,N20) -> 0.12783655 | V20: =_xlfn.RRI(3,K20,N20) -> 0.12499259
B21: =Schedules!B31 -> Advertisement and sales promotion | D21: =Schedules!D33 -> 727 | E21: =Schedules!E33 -> 698 | F21: =Schedules!F33 -> 796 | G21: =Schedules!G33 -> 842 | H21: =Schedules!H33 -> 952 | I21: =Schedules!I33 -> 1128 | J21: =Schedules!J33 -> 1419.9441 | K21: =Schedules!K33 -> 1611.6366 | ... S21: =Schedules!S33 -> 4043.954 | U21: =_xlfn.RRI(5,I21,N21) -> 0.15260739 | V21: =_xlfn.RRI(3,K21,N21) -> 0.12499259
B22: =Schedules!B36 -> Freight and distribution expenses | D22: =Schedules!D38 -> 294 | E22: =Schedules!E38 -> 305 | F22: =Schedules!F38 -> 354 | G22: =Schedules!G38 -> 387 | H22: =Schedules!H38 -> 416 | I22: =Schedules!I38 -> 449 | J22: =Schedules!J38 -> 493.8936 | K22: =Schedules!K38 -> 560.56924 | ... S22: =Schedules!S38 -> 1406.5927 | U22: =_xlfn.RRI(5,I22,N22) -> 0.1219316 | V22: =_xlfn.RRI(3,K22,N22) -> 0.12499259
B23: =Schedules!B41 -> Other Misc SG&A Expenses | D23: =Schedules!D43 -> 631 | E23: =Schedules!E43 -> 603 | F23: =Schedules!F43 -> 659 | G23: =Schedules!G43 -> 721 | H23: =Schedules!H43 -> 768 | I23: =Schedules!I43 -> 896 | J23: =Schedules!J43 -> 987.7872 | K23: =Schedules!K43 -> 1121.1385 | ... S23: =Schedules!S43 -> 2813.1854 | U23: =_xlfn.RRI(5,I23,N23) -> 0.12243202 | V23: =_xlfn.RRI(3,K23,N23) -> 0.12499259
B25: EBITDA | D25: =D15-SUM(D20:D23) -> 1440 | E25: =E15-SUM(E20:E23) -> 1602 | F25: =F15-SUM(F20:F23) -> 1681 | G25: =G15-SUM(G20:G23) -> 1810 | H25: =H15-SUM(H20:H23) -> 2026 | I25: =I15-SUM(I20:I23) -> 2139 | J25: =J15-SUM(J20:J23) -> 2086.7005 | K25: =K15-SUM(K20:K23) -> 2368.405 | ... S25: =S15-SUM(S20:S23) -> 6646.1506 | U25: =_xlfn.RRI(5,I25,N25) -> 0.12009241 | V25: =_xlfn.RRI(3,K25,N25) -> 0.16772711
B27: EBITDA | D27: =D25/D13 -> 0.19685578 | E27: =E25/E13 -> 0.19905567 | F27: =F25/F13 -> 0.17672414 | G27: =G25/G13 -> 0.18537485 | H27: =H25/H13 -> 0.20988294 | I27: =I25/I13 -> 0.19748869 | J27: =J25/J13 -> 0.169 | K27: =K25/K13 -> 0.169 | ... S27: =S25/S13 -> 0.189
B29: Less: Depreciation & Amortization | D29: ='P&l 25-24'!E36*-1 -> 140 | E29: ='P&l 25-24'!F36*-1 -> 139 | F29: ='P&l 25-24'!G36*-1 -> 139 | G29: ='P&l 25-24'!H36*-1 -> 155 | H29: ='P&l 25-24'!I36*-1 -> 158 | I29: ='P&l 25-24'!J36*-1 -> 178 | J29: =Schedules!J110 -> 191.1705 | K29: =Schedules!K110 -> 206.11901 | L29: =Schedules!L110 -> 223.01083 | M29: =Schedules!M110 -> 242.01413 | N29: =Schedules!N110 -> 226.96759 | O29: =Schedules!O110 -> 231.31547 | P29: =Schedules!P110 -> 258.01373 | Q29: =Schedules!Q110 -> 289.78466 | ... S29: =Schedules!S110 -> 351.53241 | U29: =_xlfn.RRI(5,I29,N29) -> 0.049805317 | V29: =_xlfn.RRI(3,K29,N29) -> 0.03263918
B30: EBIT | D30: =D25-D29 -> 1300 | E30: =E25-E29 -> 1463 | F30: =F25-F29 -> 1542 | G30: =G25-G29 -> 1655 | H30: =H25-H29 -> 1868 | I30: =I25-I29 -> 1961 | J30: =J25-J29 -> 1895.53 | K30: =K25-K29 -> 2162.286 | ... S30: =S25-S29 -> 6294.6181 | U30: =_xlfn.RRI(5,I30,N30) -> 0.12566464 | V30: =_xlfn.RRI(3,K30,N30) -> 0.17906169
B32: EBIT Margin | D32: =D30/D13 -> 0.17771702 | E32: =E30/E13 -> 0.18178429 | F32: =F30/F13 -> 0.16211102 | G32: =G30/G13 -> 0.1695002 | H32: =H30/H13 -> 0.19351497 | I32: =I30/I13 -> 0.18105438 | J32: =J30/J13 -> 0.15351727 | K32: =K30/K13 -> 0.15429216 | ... S32: =S30/S13 -> 0.17900329
B34: Less: Interest | D34: ='P&l 25-24'!E39*-1 -> 50 | E34: ='P&l 25-24'!F39*-1 -> 34 | F34: ='P&l 25-24'!G39*-1 -> 39 | G34: ='P&l 25-24'!H39*-1 -> 56 | H34: ='P&l 25-24'!I39*-1 -> 73 | I34: ='P&l 25-24'!J39*-1 -> 53 | J34: =Schedules!J244 -> 54.55585 | K34: =Schedules!K244 -> 65.903927 | L34: =Schedules!L244 -> 64.728229 | M34: =Schedules!M244 -> 63.096885 | N34: =Schedules!N244 -> 70.816974 | O34: =Schedules!O244 -> 72.470974 | P34: =Schedules!P244 -> 74.167018 | Q34: =Schedules!Q244 -> 82.910625 | ... S34: =Schedules!S244 -> 104.00309 | U34: =_xlfn.RRI(5,I34,N34) -> 0.059674051 | V34: =_xlfn.RRI(3,K34,N34) -> 0.024256411
B35: Add: Other Income | D35: ='P&l 25-24'!E40 -> 124 | E35: ='P&l 25-24'!F40 -> 94 | F35: ='P&l 25-24'!G40 -> 98 | G35: ='P&l 25-24'!H40 -> 144 | H35: ='P&l 25-24'!I40 -> 142 | I35: ='P&l 25-24'!J40 -> 208 | J35: =Schedules!J250 -> 185.2101 | K35: =Schedules!K250 -> 210.21346 | L35: =Schedules!L250 -> 237.54121 | M35: =Schedules!M250 -> 267.23387 | N35: =Schedules!N250 -> 299.30193 | O35: =Schedules!O250 -> 335.21816 | P35: =Schedules!P250 -> 375.44434 | Q35: =Schedules!Q250 -> 420.49766 | ... S35: =Schedules!S250 -> 527.47227 | U35: =_xlfn.RRI(5,I35,N35) -> 0.075497082 | V35: =_xlfn.RRI(3,K35,N35) -> 0.12499259
B36: EBT | D36: =D30-D34+D35 -> 1374 | E36: =E30-E34+E35 -> 1523 | F36: =F30-F34+F35 -> 1601 | G36: =G30-G34+G35 -> 1743 | H36: =H30-H34+H35 -> 1937 | I36: =I30-I34+I35 -> 2116 | J36: =J30-J34+J35 -> 2026.1842 | K36: =K30-K34+K35 -> 2306.5955 | ... S36: =S30-S34+S35 -> 6718.0873 | U36: =_xlfn.RRI(5,I36,N36) -> 0.12260719 | V36: =_xlfn.RRI(3,K36,N36) -> 0.17822375
B38: Less: Taxes | D38: ='P&l 25-24'!E44*-1 -> 331 | E38: ='P&l 25-24'!F44*-1 -> 324 | F38: ='P&l 25-24'!G44*-1 -> 346 | G38: ='P&l 25-24'!H44*-1 -> 421 | H38: ='P&l 25-24'!I44*-1 -> 435 | I38: ='P&l 25-24'!J44*-1 -> 458 | J38: =Schedules!J136 -> 508.97747 | K38: =Schedules!K136 -> 579.4168 | L38: =Schedules!L136 -> 659.67628 | M38: =Schedules!M136 -> 836.31251 | N38: =Schedules!N136 -> 947.70769 | O38: =Schedules!O136 -> 1068.9014 | P38: =Schedules!P136 -> 1199.1942 | Q38: =Schedules!Q136 -> 1342.9335 | ... S38: =Schedules!S136 -> 1687.5835 | U38: =_xlfn.RRI(5,I38,N38) -> 0.156543 | V38: =_xlfn.RRI(3,K38,N38) -> 0.17822375
B39: Net Income | D39: =D36-D38 -> 1043 | E39: =E36-E38 -> 1199 | F39: =F36-F38 -> 1255 | G39: =G36-G38 -> 1322 | H39: =H36-H38 -> 1502 | I39: =I36-I38 -> 1658 | J39: =J36-J38 -> 1517.2067 | K39: =K36-K38 -> 1727.1787 | ... S39: =S36-S38 -> 5030.5038 | U39: =_xlfn.RRI(5,I39,N39) -> 0.1124672 | V39: =_xlfn.RRI(3,K39,N39) -> 0.17822375
B41: Sales Growth % | D41: NM | E41: =E13/D13-1 -> 0.10020506 | F41: =F13/E13-1 -> 0.18190855 | G41: =G13/F13-1 -> 0.026492851 | H41: =H13/G13-1 -> -0.011368292 | I41: =I13/H13-1 -> 0.1220346 | J41: =J13/I13-1 -> 0.14 | K41: =K13/J13-1 -> 0.135 | L41: =L13/K13-1 -> 0.13 | ... S41: =S13/R13-1 -> 0.12
B42: Gross Profit Margin % | D42: =D15/D13 -> 0.48803828 | E42: =E15/E13 -> 0.4694334 | F42: =F15/F13 -> 0.42851135 | G42: =G15/G13 -> 0.45196641 | H42: =H15/H13 -> 0.50813219 | I42: =I15/I13 -> 0.50253901 | J42: =J15/J13 -> 0.48 | K42: =K15/K13 -> 0.48 | ... S42: =S15/S13 -> 0.5
B43: EBITDA Margin % | D43: =D25/D13 -> 0.19685578 | E43: =E25/E13 -> 0.19905567 | F43: =F25/F13 -> 0.17672414 | G43: =G25/G13 -> 0.18537485 | H43: =H25/H13 -> 0.20988294 | I43: =I25/I13 -> 0.19748869 | J43: =J25/J13 -> 0.169 | K43: =K25/K13 -> 0.169 | ... S43: =S25/S13 -> 0.189
B44: EBIT Margin % | D44: =D30/D13 -> 0.17771702 | E44: =E30/E13 -> 0.18178429 | F44: =F30/F13 -> 0.16211102 | G44: =G30/G13 -> 0.1695002 | H44: =H30/H13 -> 0.19351497 | I44: =I30/I13 -> 0.18105438 | J44: =J30/J13 -> 0.15351727 | K44: =K30/K13 -> 0.15429216 | ... S44: =S30/S13 -> 0.17900329
B45: Actual Tax Rate % | D45: =D38/D36 -> 0.24090247 | E45: =E38/E36 -> 0.21273802 | F45: =F38/F36 -> 0.21611493 | G45: =G38/G36 -> 0.24153758 | H45: =H38/H36 -> 0.22457408 | I45: =I38/I36 -> 0.21644612 | J45: =J38/J36 -> 0.2512 | K45: =K38/K36 -> 0.2512 | ... S45: =S38/S36 -> 0.2512
B46: Net Income Margin % | D46: =D39/D13 -> 0.14258373 | E46: =E39/E13 -> 0.14898111 | F46: =F39/F13 -> 0.1319386 | G46: =G39/G13 -> 0.13539533 | H46: =H39/H13 -> 0.1555993 | I46: =I39/I13 -> 0.15307912 | J46: =J39/J13 -> 0.12287721 | K46: =K39/K13 -> 0.12324463 | ... S46: =S39/S13 -> 0.14305502
B47: Interest Coverage Ratio | D47: =D30/D34 -> 26 | E47: =E30/E34 -> 43.029412 | F47: =F30/F34 -> 39.538462 | G47: =G30/G34 -> 29.553571 | H47: =H30/H34 -> 25.589041 | I47: =I30/I34 -> 37 | J47: =J30/J34 -> 34.744761 | K47: =K30/K34 -> 32.809669 | ... S47: =S30/S34 -> 60.523377
A49: # | B49: Balance Sheet
B51: Assets
B53: Non Current Assets
B54: Property, Plant & Equipment | D54: ='Balance Sheet'!D8 -> 654 | E54: ='Balance Sheet'!E8 -> 572 | F54: ='Balance Sheet'!F8 -> 600 | G54: ='Balance Sheet'!G8 -> 633 | H54: ='Balance Sheet'!H8 -> 700 | I54: ='Balance Sheet'!I8 -> 710 | J54: =Schedules!J56 -> 780.38694 | K54: =Schedules!K56 -> 862.49563 | L54: =Schedules!L56 -> 956.8621 | M54: =Schedules!M56 -> 1063.8974 | N54: =Schedules!N56 -> 1165.2318 | O54: =Schedules!O56 -> 1280.1345 | P54: =Schedules!P56 -> 1433.5947 | Q54: =Schedules!Q56 -> 1631.374 | ... S54: =Schedules!S56 -> 1905.8294
B55: Capital work-in-progress | D55: ='Balance Sheet'!D9 -> 58 | E55: ='Balance Sheet'!E9 -> 24 | F55: ='Balance Sheet'!F9 -> 39 | G55: ='Balance Sheet'!G9 -> 67 | H55: ='Balance Sheet'!H9 -> 44 | I55: ='Balance Sheet'!I9 -> 40 | J55: =Schedules!J69 -> 40 | K55: =Schedules!K69 -> 40 | L55: =Schedules!L69 -> 40 | M55: =Schedules!M69 -> 40 | N55: =Schedules!N69 -> 40 | O55: =Schedules!O69 -> 40 | P55: =Schedules!P69 -> 40 | Q55: =Schedules!Q69 -> 40 | ... S55: =Schedules!S69 -> 40
B56: Right of use assets | D56: ='Balance Sheet'!D10 -> 146 | E56: ='Balance Sheet'!E10 -> 180 | F56: ='Balance Sheet'!F10 -> 178 | G56: ='Balance Sheet'!G10 -> 175 | H56: ='Balance Sheet'!H10 -> 209 | I56: ='Balance Sheet'!I10 -> 230 | J56: =Schedules!J63 -> 177 | K56: =Schedules!K63 -> 124 | L56: =Schedules!L63 -> 71 | M56: =Schedules!M63 -> 18 | N56: =Schedules!N63 -> 0 | O56: =Schedules!O63 -> 0 | P56: =Schedules!P63 -> 0 | Q56: =Schedules!Q63 -> 0 | ... S56: =Schedules!S63 -> 0
B57: Investment Property | D57: ='Balance Sheet'!D11 -> 17 | E57: ='Balance Sheet'!E11 -> 17 | F57: ='Balance Sheet'!F11 -> 22 | G57: ='Balance Sheet'!G11 -> 16 | H57: ='Balance Sheet'!H11 -> 15 | I57: ='Balance Sheet'!I11 -> 15 | J57: =Schedules!J82 -> 15 | K57: =Schedules!K82 -> 15 | L57: =Schedules!L82 -> 15 | M57: =Schedules!M82 -> 15 | N57: =Schedules!N82 -> 15 | O57: =Schedules!O82 -> 15 | P57: =Schedules!P82 -> 15 | Q57: =Schedules!Q82 -> 15 | ... S57: =Schedules!S82 -> 15
B58: Goodwill | D58: ='Balance Sheet'!D12 -> 538 | E58: ='Balance Sheet'!E12 -> 613 | F58: ='Balance Sheet'!F12 -> 654 | G58: ='Balance Sheet'!G12 -> 862 | H58: ='Balance Sheet'!H12 -> 863 | I58: ='Balance Sheet'!I12 -> 857 | J58: =Schedules!J88 -> 857 | K58: =Schedules!K88 -> 857 | L58: =Schedules!L88 -> 857 | M58: =Schedules!M88 -> 857 | N58: =Schedules!N88 -> 857 | O58: =Schedules!O88 -> 857 | P58: =Schedules!P88 -> 857 | Q58: =Schedules!Q88 -> 857 | ... S58: =Schedules!S88 -> 857
B59: Intangible Assets | D59: ='Balance Sheet'!D13 -> 70 | E59: ='Balance Sheet'!E13 -> 230 | F59: ='Balance Sheet'!F13 -> 306 | G59: ='Balance Sheet'!G13 -> 560 | H59: ='Balance Sheet'!H13 -> 937 | I59: ='Balance Sheet'!I13 -> 946 | J59: =Schedules!J76 -> 935 | K59: =Schedules!K76 -> 924 | L59: =Schedules!L76 -> 913 | M59: =Schedules!M76 -> 902 | N59: =Schedules!N76 -> 891 | O59: =Schedules!O76 -> 880 | P59: =Schedules!P76 -> 869 | Q59: =Schedules!Q76 -> 858 | ... S59: =Schedules!S76 -> 836
B60: Non Current Financial Assets | D60: ='Balance Sheet'!D15 -> 107 | E60: ='Balance Sheet'!E15 -> 271 | F60: ='Balance Sheet'!F15 -> 208 | G60: ='Balance Sheet'!G15 -> 554 | H60: ='Balance Sheet'!H15 -> 447 | I60: ='Balance Sheet'!I15 -> 243 | J60: =Schedules!J92 -> 243 | K60: =Schedules!K92 -> 243 | L60: =Schedules!L92 -> 243 | M60: =Schedules!M92 -> 243 | N60: =Schedules!N92 -> 243 | O60: =Schedules!O92 -> 243 | P60: =Schedules!P92 -> 243 | Q60: =Schedules!Q92 -> 243 | ... S60: =Schedules!S92 -> 243
B61: Other Non Current assets | D61: ='Balance Sheet'!D22 -> 26 | E61: ='Balance Sheet'!E22 -> 26 | F61: ='Balance Sheet'!F22 -> 30 | G61: ='Balance Sheet'!G22 -> 46 | H61: ='Balance Sheet'!H22 -> 40 | I61: ='Balance Sheet'!I22 -> 49 | J61: =Schedules!J96 -> 49 | K61: =Schedules!J96 -> 49 | L61: =Schedules!K96 -> 49 | M61: =Schedules!L96 -> 49 | N61: =Schedules!M96 -> 49 | O61: =Schedules!N96 -> 49 | P61: =Schedules!O96 -> 49 | Q61: =Schedules!P96 -> 49 | R61: =Schedules!Q96 -> 49 | S61: =Schedules!R96 -> 49
B62: Non current tax assets (net) | D62: ='Balance Sheet'!D21 -> 45 | E62: ='Balance Sheet'!E21 -> 55 | F62: ='Balance Sheet'!F21 -> 57 | G62: ='Balance Sheet'!G21 -> 67 | H62: ='Balance Sheet'!H21 -> 95 | I62: ='Balance Sheet'!I21 -> 108 | J62: =Schedules!J100 -> 108 | K62: =Schedules!K100 -> 108 | L62: =Schedules!L100 -> 108 | M62: =Schedules!M100 -> 108 | N62: =Schedules!N100 -> 108 | O62: =Schedules!O100 -> 108 | P62: =Schedules!P100 -> 108 | Q62: =Schedules!Q100 -> 108 | ... S62: =Schedules!S100 -> 108
B63: Deferred tax assets | D63: ='Balance Sheet'!D20 -> 159 | E63: ='Balance Sheet'!E20 -> 186 | F63: ='Balance Sheet'!F20 -> 187 | G63: ='Balance Sheet'!G20 -> 146 | H63: ='Balance Sheet'!H20 -> 68 | I63: ='Balance Sheet'!I20 -> 57 | J63: =Schedules!J104 -> 57 | K63: =Schedules!K104 -> 57 | L63: =Schedules!L104 -> 57 | M63: =Schedules!M104 -> 57 | N63: =Schedules!N104 -> 57 | O63: =Schedules!O104 -> 57 | P63: =Schedules!P104 -> 57 | Q63: =Schedules!Q104 -> 57 | ... S63: =Schedules!S104 -> 57
B64: Total Non Current Assets | D64: =SUM(D54:D63) -> 1820 | E64: =SUM(E54:E63) -> 2174 | F64: =SUM(F54:F63) -> 2281 | G64: =SUM(G54:G63) -> 3126 | H64: =SUM(H54:H63) -> 3418 | I64: =SUM(I54:I63) -> 3255 | J64: =SUM(J54:J63) -> 3261.3869 | K64: =SUM(K54:K63) -> 3279.4956 | ... S64: =SUM(S54:S63) -> 4110.8294
B66: Current Assets
B67: Cash | D67: =D148 -> 93 | E67: =E148 -> 109 | F67: =F148 -> 276 | G67: =G148 -> 207 | H67: =H148 -> 228 | I67: =I148 -> 321 | J67: =J148 -> 385.08676 | K67: =K148 -> 422.63104 | ... S67: =S148 -> 1088.2576
B68: Bank | D68: ='Balance Sheet'!D38 -> 186 | E68: ='Balance Sheet'!E38 -> 835 | F68: ='Balance Sheet'!F38 -> 303 | G68: ='Balance Sheet'!G38 -> 549 | H68: ='Balance Sheet'!H38 -> 715 | I68: ='Balance Sheet'!I38 -> 456 | J68: =Schedules!J205 -> 456 | K68: =Schedules!K205 -> 456 | L68: =Schedules!L205 -> 456 | M68: =Schedules!M205 -> 456 | N68: =Schedules!N205 -> 456 | O68: =Schedules!O205 -> 456 | P68: =Schedules!P205 -> 456 | Q68: =Schedules!Q205 -> 456 | ... S68: =Schedules!S205 -> 456
B69: Inventory | D69: ='Balance Sheet'!D26 -> 1380 | E69: ='Balance Sheet'!E26 -> 1126 | F69: ='Balance Sheet'!F26 -> 1412 | G69: ='Balance Sheet'!G26 -> 1225 | H69: ='Balance Sheet'!H26 -> 1336 | I69: ='Balance Sheet'!I26 -> 1235 | J69: =Schedules!J161 -> 1589.9315 | K69: =Schedules!K161 -> 1804.5722 | L69: =Schedules!L161 -> 1995.7801 | M69: =Schedules!M161 -> 2245.2526 | N69: =Schedules!N161 -> 2514.6829 | O69: =Schedules!O161 -> 2693.9907 | P69: =Schedules!P161 -> 3017.2696 | Q69: =Schedules!Q161 -> 3225.7355 | ... S69: =Schedules!S161 -> 3853.6787
B70: Debtors | D70: ='Balance Sheet'!D27 -> 539 | E70: ='Balance Sheet'!E27 -> 388 | F70: ='Balance Sheet'!F27 -> 652 | G70: ='Balance Sheet'!G27 -> 1015 | H70: ='Balance Sheet'!H27 -> 1069 | I70: ='Balance Sheet'!I27 -> 1271 | J70: =Schedules!J155 -> 1522.2748 | K70: =Schedules!K155 -> 1727.7819 | L70: =Schedules!L155 -> 1822.234 | M70: =Schedules!M155 -> 2050.0132 | N70: =Schedules!N155 -> 2296.0148 | O70: =Schedules!O155 -> 2449.0825 | P70: =Schedules!P155 -> 2742.9723 | Q70: =Schedules!Q155 -> 2995.3258 | ... S70: =Schedules!S155 -> 3757.3367
B71: Other Current Assets | D71: ='Balance Sheet'!D29 -> 984 | E71: ='Balance Sheet'!E29 -> 878 | F71: ='Balance Sheet'!F29 -> 862 | G71: ='Balance Sheet'!G29 -> 824 | H71: ='Balance Sheet'!H29 -> 655 | I71: ='Balance Sheet'!I29 -> 1800 | J71: =Schedules!J167 -> 1728.6276 | K71: =Schedules!K167 -> 1961.9923 | L71: =Schedules!L167 -> 2058.6905 | M71: =Schedules!M167 -> 2137.8709 | N71: =Schedules!N167 -> 2194.8808 | O71: =Schedules!O167 -> 2458.2665 | P71: =Schedules!P167 -> 2502.9623 | Q71: =Schedules!Q167 -> 2803.3177 | ... S71: =Schedules!S167 -> 3516.4818
B72: Total Current Assets | D72: =SUM(D67:D71) -> 3182 | E72: =SUM(E67:E71) -> 3336 | F72: =SUM(F67:F71) -> 3505 | G72: =SUM(G67:G71) -> 3820 | H72: =SUM(H67:H71) -> 4003 | I72: =SUM(I67:I71) -> 5083 | J72: =SUM(J67:J71) -> 5681.9206 | K72: =SUM(K67:K71) -> 6372.9775 | ... S72: =SUM(S67:S71) -> 12671.755
B74: Total Assets | D74: =D72+D64 -> 5002 | E74: =E72+E64 -> 5510 | F74: =F72+F64 -> 5786 | G74: =G72+G64 -> 6946 | H74: =H72+H64 -> 7421 | I74: =I72+I64 -> 8338 | J74: =J72+J64 -> 8943.3076 | K74: =K72+K64 -> 9652.4731 | ... S74: =S72+S64 -> 16782.584
B77: EQUITY AND LIABILITIES
B79: Equity
B80: Equity share capital | D80: ='Balance Sheet'!D46 -> 129 | E80: ='Balance Sheet'!E46 -> 129 | F80: ='Balance Sheet'!F46 -> 129 | G80: ='Balance Sheet'!G46 -> 129 | H80: ='Balance Sheet'!H46 -> 129 | I80: ='Balance Sheet'!I46 -> 129 | J80: =I80 -> 129 | K80: =J80 -> 129 | L80: =K80 -> 129 | M80: =L80 -> 129 | N80: =M80 -> 129 | O80: =N80 -> 129 | P80: =O80 -> 129 | Q80: =P80 -> 129 | ... S80: =R80 -> 129
B81: Other equity | D81: =SUM('Balance Sheet'!D48:D50) -> 2894 | E81: =SUM('Balance Sheet'!E48:E50) -> 3111 | F81: =SUM('Balance Sheet'!F48:F50) -> 3219 | G81: =SUM('Balance Sheet'!G48:G50) -> 3670 | H81: =SUM('Balance Sheet'!H48:H50) -> 3703 | I81: =SUM('Balance Sheet'!I48:I50) -> 3846 | J81: =Schedules!J146 -> 4149.4413 | K81: =Schedules!K146 -> 4494.8771 | L81: =Schedules!L146 -> 4888.1618 | M81: =Schedules!M146 -> 5386.7532 | N81: =Schedules!N146 -> 5810.5053 | O81: =Schedules!O146 -> 6288.4472 | P81: =Schedules!P146 -> 6824.6474 | Q81: =Schedules!Q146 -> 7425.1183 | ... S81: =Schedules!S146 -> 8852.4831
B82: Total Shareholder's Equity | D82: =SUM(D80:D81) -> 3023 | E82: =SUM(E80:E81) -> 3240 | F82: =SUM(F80:F81) -> 3348 | G82: =SUM(G80:G81) -> 3799 | H82: =SUM(H80:H81) -> 3832 | I82: =SUM(I80:I81) -> 3975 | J82: =SUM(J80:J81) -> 4278.4413 | K82: =SUM(K80:K81) -> 4623.8771 | ... S82: =SUM(S80:S81) -> 8981.4831
B83: Minority Interest | D83: ='Balance Sheet'!D53 -> 13 | E83: ='Balance Sheet'!E53 -> 18 | F83: ='Balance Sheet'!F53 -> 57 | G83: ='Balance Sheet'!G53 -> 157 | H83: ='Balance Sheet'!H53 -> 337 | I83: ='Balance Sheet'!I53 -> 291 | J83: =I83 -> 291 | K83: =J83 -> 291 | L83: =K83 -> 291 | M83: =L83 -> 291 | N83: =M83 -> 291 | O83: =N83 -> 291 | P83: =O83 -> 291 | Q83: =P83 -> 291 | ... S83: =R83 -> 291
B84: Total equity | D84: =SUM(D82:D83) -> 3036 | E84: =SUM(E82:E83) -> 3258 | F84: =SUM(F82:F83) -> 3405 | G84: =SUM(G82:G83) -> 3956 | H84: =SUM(H82:H83) -> 4169 | I84: =SUM(I82:I83) -> 4266 | J84: =SUM(J82:J83) -> 4569.4413 | K84: =SUM(K82:K83) -> 4914.8771 | ... S84: =SUM(S82:S83) -> 9272.4831
B86: Non-current liabilities
B88: Long Term Borrowings | D88: ='Balance Sheet'!D60 -> 10 | E88: ='Balance Sheet'!E60 -> 8 | F88: ='Balance Sheet'!F60 -> 0 | G88: ='Balance Sheet'!G60 -> 2 | H88: ='Balance Sheet'!H60 -> 0 | I88: ='Balance Sheet'!I60 -> 0 | J88: =Schedules!J230 -> 0 | K88: =Schedules!K230 -> 0 | L88: =Schedules!L230 -> 0 | M88: =Schedules!M230 -> 0 | N88: =Schedules!N230 -> 0 | O88: =Schedules!O230 -> 0 | P88: =Schedules!P230 -> 0 | Q88: =Schedules!Q230 -> 0 | ... S88: =Schedules!S230 -> 0
B89: Lease Liabilities | D89: ='Balance Sheet'!D61 -> 0 | E89: ='Balance Sheet'!E61 -> 0 | F89: ='Balance Sheet'!F61 -> 91 | G89: ='Balance Sheet'!G61 -> 91 | H89: ='Balance Sheet'!H61 -> 104 | I89: ='Balance Sheet'!I61 -> 124 | J89: =I89 -> 124 | K89: =J89 -> 124 | L89: =K89 -> 124 | M89: =L89 -> 124 | N89: =M89 -> 124 | O89: =N89 -> 124 | P89: =O89 -> 124 | Q89: =P89 -> 124 | ... S89: =R89 -> 124
B90: Other Provisions | D90: ='Balance Sheet'!D62 -> 144 | E90: ='Balance Sheet'!E62 -> 122 | F90: ='Balance Sheet'!F62 -> 1 | G90: ='Balance Sheet'!G62 -> 266 | H90: ='Balance Sheet'!H62 -> 405 | I90: ='Balance Sheet'!I62 -> 1211 | J90: =I90 -> 1211 | K90: =J90 -> 1211 | L90: =K90 -> 1211 | M90: =L90 -> 1211 | N90: =M90 -> 1211 | O90: =N90 -> 1211 | P90: =O90 -> 1211 | Q90: =P90 -> 1211 | ... S90: =R90 -> 1211
B91: Others Financial Liabilities - Long-term | D91: ='Balance Sheet'!D63 -> 0 | E91: ='Balance Sheet'!E63 -> 1 | F91: ='Balance Sheet'!F63 -> 0 | G91: ='Balance Sheet'!G63 -> 4 | H91: ='Balance Sheet'!H63 -> 1 | I91: ='Balance Sheet'!I63 -> 1 | J91: =I91 -> 1 | K91: =J91 -> 1 | L91: =K91 -> 1 | M91: =L91 -> 1 | N91: =M91 -> 1 | O91: =N91 -> 1 | P91: =O91 -> 1 | Q91: =P91 -> 1 | ... S91: =R91 -> 1
B92: Employee benefit obligations (net) | D92: ='Balance Sheet'!D64 -> 21 | E92: ='Balance Sheet'!E64 -> 24 | F92: ='Balance Sheet'!F64 -> 27 | G92: ='Balance Sheet'!G64 -> 20 | H92: ='Balance Sheet'!H64 -> 19 | I92: ='Balance Sheet'!I64 -> 27 | J92: =I92 -> 27 | K92: =J92 -> 27 | L92: =K92 -> 27 | M92: =L92 -> 27 | N92: =M92 -> 27 | O92: =N92 -> 27 | P92: =O92 -> 27 | Q92: =P92 -> 27 | ... S92: =R92 -> 27
B93: Deferred Tax Liabilities (Net) | D93: ='Balance Sheet'!D65 -> 6 | E93: ='Balance Sheet'!E65 -> 84 | F93: ='Balance Sheet'!F65 -> 109 | G93: ='Balance Sheet'!G65 -> 178 | H93: ='Balance Sheet'!H65 -> 279 | I93: ='Balance Sheet'!I65 -> 248 | J93: =I93 -> 248 | K93: =J93 -> 248 | L93: =K93 -> 248 | M93: =L93 -> 248 | N93: =M93 -> 248 | O93: =N93 -> 248 | P93: =O93 -> 248 | Q93: =P93 -> 248 | ... S93: =R93 -> 248
B94: Total non-current liabilities | D94: =SUM(D88:D93) -> 181 | E94: =SUM(E88:E93) -> 239 | F94: =SUM(F88:F93) -> 228 | G94: =SUM(G88:G93) -> 561 | H94: =SUM(H88:H93) -> 808 | I94: =SUM(I88:I93) -> 1611 | J94: =SUM(J88:J93) -> 1611 | K94: =SUM(K88:K93) -> 1611 | ... S94: =SUM(S88:S93) -> 1611
B96: Current Liabilities
B98: Trade Payables | D98: ='Balance Sheet'!D69 -> 978 | E98: ='Balance Sheet'!E69 -> 1134 | F98: ='Balance Sheet'!F69 -> 1344 | G98: ='Balance Sheet'!G69 -> 1452 | H98: ='Balance Sheet'!H69 -> 1581 | I98: ='Balance Sheet'!I69 -> 1363 | J98: =Schedules!J172 -> 1549.9726 | K98: =Schedules!K172 -> 1847.0268 | L98: =Schedules!L172 -> 2096.3754 | M98: =Schedules!M172 -> 2301.2212 | N98: =Schedules!N172 -> 2489.3018 | O98: =Schedules!O172 -> 2788.018 | P98: =Schedules!P172 -> 3061.3531 | Q98: =Schedules!Q172 -> 3428.7154 | ... S98: =Schedules!S172 -> 4300.9806
B99: Short Term Borrowings | D99: ='Balance Sheet'!D71 -> 325 | E99: ='Balance Sheet'!E71 -> 340 | F99: ='Balance Sheet'!F71 -> 345 | G99: ='Balance Sheet'!G71 -> 473 | H99: ='Balance Sheet'!H71 -> 383 | I99: ='Balance Sheet'!I71 -> 379 | J99: =Schedules!J233 -> 493.8936 | K99: =Schedules!K233 -> 560.56924 | L99: =Schedules!L233 -> 475.08243 | M99: =Schedules!M233 -> 534.46773 | N99: =Schedules!N233 -> 598.60386 | O99: =Schedules!O233 -> 560.93172 | P99: =Schedules!P233 -> 625.74057 | Q99: =Schedules!Q233 -> 700.82943 | ... S99: =Schedules!S233 -> 879.12044
B100: Lease Liabilities | D100: ='Balance Sheet'!D72 -> 0 | E100: ='Balance Sheet'!E72 -> 0 | F100: ='Balance Sheet'!F72 -> 43 | G100: ='Balance Sheet'!G72 -> 42 | H100: ='Balance Sheet'!H72 -> 41 | I100: ='Balance Sheet'!I72 -> 51 | J100: =Schedules!J181 -> 51 | K100: =Schedules!K181 -> 51 | L100: =Schedules!L181 -> 51 | M100: =Schedules!M181 -> 51 | N100: =Schedules!N181 -> 51 | O100: =Schedules!O181 -> 51 | P100: =Schedules!P181 -> 51 | Q100: =Schedules!Q181 -> 51 | ... S100: =Schedules!S181 -> 51
B101: Others Financial Liabilities - Short-term | D101: ='Balance Sheet'!D73 -> 79 | E101: ='Balance Sheet'!E73 -> 82 | F101: ='Balance Sheet'!F73 -> 45 | G101: ='Balance Sheet'!G73 -> 40 | H101: ='Balance Sheet'!H73 -> 59 | I101: ='Balance Sheet'!I73 -> 231 | J101: =Schedules!J185 -> 231 | K101: =Schedules!K185 -> 231 | L101: =Schedules!L185 -> 231 | M101: =Schedules!M185 -> 231 | N101: =Schedules!N185 -> 231 | O101: =Schedules!O185 -> 231 | P101: =Schedules!P185 -> 231 | Q101: =Schedules!Q185 -> 231 | ... S101: =Schedules!S185 -> 231
B102: Other Current Liabilities | D102: ='Balance Sheet'!D74 -> 217 | E102: ='Balance Sheet'!E74 -> 287 | F102: ='Balance Sheet'!F74 -> 224 | G102: ='Balance Sheet'!G74 -> 217 | H102: ='Balance Sheet'!H74 -> 211 | I102: ='Balance Sheet'!I74 -> 232 | J102: =Schedules!J189 -> 232 | K102: =Schedules!K189 -> 232 | L102: =Schedules!L189 -> 232 | M102: =Schedules!M189 -> 232 | N102: =Schedules!N189 -> 232 | O102: =Schedules!O189 -> 232 | P102: =Schedules!P189 -> 232 | Q102: =Schedules!Q189 -> 232 | ... S102: =Schedules!S189 -> 232
B103: Provisions | D103: ='Balance Sheet'!D75 -> 58 | E103: ='Balance Sheet'!E75 -> 20 | F103: ='Balance Sheet'!F75 -> 21 | G103: ='Balance Sheet'!G75 -> 44 | H103: ='Balance Sheet'!H75 -> 7 | I103: ='Balance Sheet'!I75 -> 21 | J103: =Schedules!J193 -> 21 | K103: =Schedules!K193 -> 21 | L103: =Schedules!L193 -> 21 | M103: =Schedules!M193 -> 21 | N103: =Schedules!N193 -> 21 | O103: =Schedules!O193 -> 21 | P103: =Schedules!P193 -> 21 | Q103: =Schedules!Q193 -> 21 | ... S103: =Schedules!S193 -> 21
B104: Employee benefit obligations (net) | D104: ='Balance Sheet'!D76 -> 54 | E104: ='Balance Sheet'!E76 -> 78 | F104: ='Balance Sheet'!F76 -> 64 | G104: ='Balance Sheet'!G76 -> 74 | H104: ='Balance Sheet'!H76 -> 79 | I104: ='Balance Sheet'!I76 -> 92 | J104: =Schedules!J197 -> 92 | K104: =Schedules!K197 -> 92 | L104: =Schedules!L197 -> 92 | M104: =Schedules!M197 -> 92 | N104: =Schedules!N197 -> 92 | O104: =Schedules!O197 -> 92 | P104: =Schedules!P197 -> 92 | Q104: =Schedules!Q197 -> 92 | ... S104: =Schedules!S197 -> 92
B105: Current Tax Liabilities - Short-term | D105: ='Balance Sheet'!D77 -> 74 | E105: ='Balance Sheet'!E77 -> 72 | F105: ='Balance Sheet'!F77 -> 67 | G105: ='Balance Sheet'!G77 -> 87 | H105: ='Balance Sheet'!H77 -> 83 | I105: ='Balance Sheet'!I77 -> 92 | J105: =Schedules!J201 -> 92 | K105: =Schedules!K201 -> 92 | L105: =Schedules!L201 -> 92 | M105: =Schedules!M201 -> 92 | N105: =Schedules!N201 -> 92 | O105: =Schedules!O201 -> 92 | P105: =Schedules!P201 -> 92 | Q105: =Schedules!Q201 -> 92 | ... S105: =Schedules!S201 -> 92
B106: Total Current Liabilites | D106: =SUM(D98:D105) -> 1785 | E106: =SUM(E98:E105) -> 2013 | F106: =SUM(F98:F105) -> 2153 | G106: =SUM(G98:G105) -> 2429 | H106: =SUM(H98:H105) -> 2444 | I106: =SUM(I98:I105) -> 2461 | J106: =SUM(J98:J105) -> 2762.8662 | K106: =SUM(K98:K105) -> 3126.596 | ... S106: =SUM(S98:S105) -> 5899.1011
B108: Total Equity and Liabilites | D108: =D106+D94+D84 -> 5002 | E108: =E106+E94+E84 -> 5510 | F108: =F106+F94+F84 -> 5786 | G108: =G106+G94+G84 -> 6946 | H108: =H106+H94+H84 -> 7421 | I108: =I106+I94+I84 -> 8338 | J108: =J106+J94+J84 -> 8943.3076 | K108: =K106+K94+K84 -> 9652.4731 | ... S108: =S106+S94+S84 -> 16782.584
B110: Net Working Capital | D110: =D72-D106 -> 1397 | E110: =E72-E106 -> 1323 | F110: =F72-F106 -> 1352 | G110: =G72-G106 -> 1391 | H110: =H72-H106 -> 1559 | I110: =I72-I106 -> 2622 | J110: =J72-J106 -> 2919.0544 | K110: =K72-K106 -> 3246.3815 | ... S110: =S72-S106 -> 6772.6536
B111: Debtors Days | D111: =Schedules!D156 -> 0 | E111: =Schedules!E156 -> 21.021061 | F111: =Schedules!F156 -> 19.953743 | G111: =Schedules!G156 -> 31.158081 | H111: =Schedules!H156 -> 39.400186 | I111: =Schedules!I156 -> 39.428492 | J111: =Schedules!J156 -> 45 | K111: =Schedules!K156 -> 45 | ... S111: =Schedules!S156 -> 39
B112: Inventory Days | D112: =Schedules!D162 -> 0 | E112: =Schedules!E162 -> 56.827162 | F112: =Schedules!F162 -> 48.694807 | G112: =Schedules!G162 -> 49.288458 | H112: =Schedules!H162 -> 48.418367 | I112: =Schedules!I162 -> 43.320792 | J112: =Schedules!J162 -> 47 | K112: =Schedules!K162 -> 47 | ... S112: =Schedules!S162 -> 40
B113: Trade Payable Days | D113: =Schedules!D173 -> 0 | E113: =Schedules!E173 -> 90.266979 | F113: =Schedules!F173 -> 83.192605 | G113: =Schedules!G173 -> 95.359746 | H113: =Schedules!H173 -> 116.58014 | I113: =Schedules!I173 -> 99.717892 | J113: =Schedules!J173 -> 105 | K113: =Schedules!K173 -> 105 | ... S113: =Schedules!S173 -> 100
B115: Cash Flow Statement
B117: Profit Before Tax | D117: =D36 -> 1374 | E117: =E36 -> 1523 | F117: =F36 -> 1601 | G117: =G36 -> 1743 | H117: =H36 -> 1937 | I117: =I36 -> 2116 | J117: =J36 -> 2026.1842 | K117: =K36 -> 2306.5955 | ... S117: =S36 -> 6718.0873
B118: Add: Depreciation | D118: =D29 -> 140 | E118: =E29 -> 139 | F118: =F29 -> 139 | G118: =G29 -> 155 | H118: =H29 -> 158 | I118: =I29 -> 178 | J118: =J29 -> 191.1705 | K118: =K29 -> 206.11901 | ... S118: =S29 -> 351.53241
B119: Add: Interest Expenses | D119: =D34 -> 50 | E119: =E34 -> 34 | F119: =F34 -> 39 | G119: =G34 -> 56 | H119: =H34 -> 73 | I119: =I34 -> 53 | J119: =J34 -> 54.55585 | K119: =K34 -> 65.903927 | ... S119: =S34 -> 104.00309
B120: Add: Other Iteams | D120: =SUM('Cash Flow'!D9,'Cash Flow'!D11:D18) -> -89 | E120: =SUM('Cash Flow'!E9,'Cash Flow'!E11:E18) -> -73 | F120: =SUM('Cash Flow'!F9,'Cash Flow'!F11:F18) -> -70 | G120: =SUM('Cash Flow'!G9,'Cash Flow'!G11:G18) -> -107 | H120: =SUM('Cash Flow'!H9,'Cash Flow'!H11:H18) -> -128 | I120: =SUM('Cash Flow'!I9,'Cash Flow'!I11:I18) -> -128 | J120: 0 | K120: 0 | L120: 0 | M120: 0 | N120: 0 | O120: 0 | P120: 0 | Q120: 0 | R120: 0 | S120: 0
B121: Less: Change in Working Capital | D121: ='Cash Flow'!D35 -> 33 | E121: ='Cash Flow'!E35 -> 730 | F121: ='Cash Flow'!F35 -> -342 | G121: ='Cash Flow'!G35 -> -59 | H121: ='Cash Flow'!H35 -> -226 | I121: ='Cash Flow'!I35 -> -293 | J121: =Schedules!J225*-1 -> -347.86124 | K121: =Schedules!K225*-1 -> -356.45842 | L121: =Schedules!L225*-1 -> -133.00952 | M121: =Schedules!M225*-1 -> -351.58634 | N121: =Schedules!N225*-1 -> -384.36121 | O121: =Schedules!O225*-1 -> -297.04496 | P121: =Schedules!P225*-1 -> -388.52944 | Q121: =Schedules!Q225*-1 -> -393.81246 | ... S121: =Schedules!S225*-1 -> -697.00463
B122: Less: Tax Paid | D122: ='Cash Flow'!D39 -> -290 | E122: ='Cash Flow'!E39 -> -285 | F122: ='Cash Flow'!F39 -> -351 | G122: ='Cash Flow'!G39 -> -369 | H122: ='Cash Flow'!H39 -> -378 | I122: ='Cash Flow'!I39 -> -484 | J122: =J38*-1 -> -508.97747 | K122: =K38*-1 -> -579.4168 | L122: =L38*-1 -> -659.67628 | M122: =M38*-1 -> -836.31251 | N122: =N38*-1 -> -947.70769 | O122: =O38*-1 -> -1068.9014 | P122: =P38*-1 -> -1199.1942 | Q122: =Q38*-1 -> -1342.9335 | ... S122: =S38*-1 -> -1687.5835
B123: Cash Flow from Operation (A) | D123: =SUM(D117:D122) -> 1218 | E123: =SUM(E117:E122) -> 2068 | F123: =SUM(F117:F122) -> 1016 | G123: =SUM(G117:G122) -> 1419 | H123: =SUM(H117:H122) -> 1436 | I123: =SUM(I117:I122) -> 1442 | J123: =SUM(J117:J122) -> 1415.0718 | K123: =SUM(K117:K122) -> 1642.7433 | ... S123: =SUM(S117:S122) -> 4789.0346
B125: Net Purchased of Fixed Assets | D125: =SUM('Cash Flow'!D44,'Cash Flow'!D46) -> -186 | E125: =SUM('Cash Flow'!E44,'Cash Flow'!E46) -> -137 | F125: =SUM('Cash Flow'!F44,'Cash Flow'!F46) -> -129 | G125: =SUM('Cash Flow'!G44,'Cash Flow'!G46) -> -157 | H125: =SUM('Cash Flow'!H44,'Cash Flow'!H46) -> -135 | I125: =SUM('Cash Flow'!I44,'Cash Flow'!I46) -> -122 | J125: =Schedules!J54*-1 -> -197.55744 | K125: =Schedules!K54*-1 -> -224.22769 | L125: =Schedules!L54*-1 -> -253.37729 | M125: =Schedules!M54*-1 -> -285.04946 | N125: =Schedules!N54*-1 -> -299.30193 | O125: =Schedules!O54*-1 -> -335.21816 | P125: =Schedules!P54*-1 -> -400.47396 | Q125: =Schedules!Q54*-1 -> -476.56402 | ... S125: =Schedules!S54*-1 -> -439.56022
B126: Net Purchase of Investments | D126: =SUM('Cash Flow'!D47:D49) -> -189 | E126: =SUM('Cash Flow'!E47:E49) -> 165 | F126: =SUM('Cash Flow'!F47:F49) -> -146 | G126: =SUM('Cash Flow'!G47:G49) -> -130 | H126: =SUM('Cash Flow'!H47:H49) -> 380 | I126: =SUM('Cash Flow'!I47:I49) -> -912 | J126: 0 | K126: 0 | L126: 0 | M126: 0 | N126: 0 | O126: 0 | P126: 0 | Q126: 0 | R126: 0 | S126: 0
B127: Interest Received | D127: ='Cash Flow'!D52 -> 72 | E127: ='Cash Flow'!E52 -> 52 | F127: ='Cash Flow'!F52 -> 57 | G127: ='Cash Flow'!G52 -> 48 | H127: ='Cash Flow'!H52 -> 66 | I127: ='Cash Flow'!I52 -> 70 | J127: 0 | K127: 0 | L127: 0 | M127: 0 | N127: 0 | O127: 0 | P127: 0 | Q127: 0 | R127: 0 | S127: 0
B128: Acquisition of Companies | D128: ='Cash Flow'!D45 -> -3 | E128: ='Cash Flow'!E45 -> -132 | F128: ='Cash Flow'!F45 -> -41 | G128: ='Cash Flow'!G45 -> -277 | H128: ='Cash Flow'!H45 -> -103 | I128: ='Cash Flow'!I45 -> 0 | J128: 0 | K128: 0 | L128: 0 | M128: 0 | N128: 0 | O128: 0 | P128: 0 | Q128: 0 | R128: 0 | S128: 0
B129: Others | D129: =SUM('Cash Flow'!D50:D51) -> 262 | E129: =SUM('Cash Flow'!E50:E51) -> -886 | F129: =SUM('Cash Flow'!F50:F51) -> 698 | G129: =SUM('Cash Flow'!G50:G51) -> -349 | H129: =SUM('Cash Flow'!H50:H51) -> -32 | I129: =SUM('Cash Flow'!I50:I51) -> 343 | J129: 0 | K129: 0 | L129: 0 | M129: 0 | N129: 0 | O129: 0 | P129: 0 | Q129: 0 | R129: 0 | S129: 0
B130: Cash Flow from Investing Activities | D130: =SUM(D125:D129) -> -44 | E130: =SUM(E125:E129) -> -938 | F130: =SUM(F125:F129) -> 439 | G130: =SUM(G125:G129) -> -865 | H130: =SUM(H125:H129) -> 176 | I130: =SUM(I125:I129) -> -621 | J130: =SUM(J125:J129) -> -197.55744 | K130: =SUM(K125:K129) -> -224.22769 | ... S130: =SUM(S125:S129) -> -439.56022
B132: Net Proceeds from Long term Borrowings | D132: ='Cash Flow'!D56 -> 0 | E132: ='Cash Flow'!E56 -> 0 | F132: ='Cash Flow'!F56 -> 0 | G132: ='Cash Flow'!G56 -> 0 | H132: ='Cash Flow'!H56 -> 0 | I132: ='Cash Flow'!I56 -> 0 | J132: =J88-I88 -> 0 | K132: =K88-J88 -> 0 | L132: =L88-K88 -> 0 | M132: =M88-L88 -> 0 | N132: =N88-M88 -> 0 | O132: =O88-N88 -> 0 | P132: =P88-O88 -> 0 | Q132: =Q88-P88 -> 0 | ... S132: =S88-R88 -> 0
B133: Net Proceeds from Short term Borrowings | D133: ='Cash Flow'!D59 -> -15 | E133: ='Cash Flow'!E59 -> 13 | F133: ='Cash Flow'!F59 -> -3 | G133: ='Cash Flow'!G59 -> 128 | H133: ='Cash Flow'!H59 -> -91 | I133: ='Cash Flow'!I59 -> -5 | J133: =J99-I99 -> 114.8936 | K133: =K99-J99 -> 66.675636 | L133: =L99-K99 -> -85.486808 | M133: =M99-L99 -> 59.385303 | N133: =N99-M99 -> 64.136128 | O133: =O99-N99 -> -37.672136 | P133: =P99-O99 -> 64.808844 | Q133: =Q99-P99 -> 75.088868 | ... S133: =S99-R99 -> 94.191476
...

Sheet Ratio Analysis
B2: ='Input Sheet'!C5 -> Marico Ltd
B3: Ratio Analysis
H4: Current Case
I8: Explicit Forecast Period | N8: Maturity Period
B9: In INR crores unless started otherwise | D9: ='3 Statement Model'!E9 -> 2021 | E9: ='3 Statement Model'!F9 -> 2022 | F9: ='3 Statement Model'!G9 -> 2023 | G9: ='3 Statement Model'!H9 -> 2024 | H9: ='3 Statement Model'!I9 -> 2025 | I9: =H9+1 -> 2026 | J9: =I9+1 -> 2027 | K9: =J9+1 -> 2028 | L9: =K9+1 -> 2029 | M9: =L9+1 -> 2030 | N9: =M9+1 -> 2031 | O9: =N9+1 -> 2032 | P9: =O9+1 -> 2033 | ... R9: =Q9+1 -> 2035
A11: # | B11: Liquidity Ratio
B13: Current Asset | D13: ='3 Statement Model'!E72 -> 3336 | E13: ='3 Statement Model'!F72 -> 3505 | F13: ='3 Statement Model'!G72 -> 3820 | G13: ='3 Statement Model'!H72 -> 4003 | H13: ='3 Statement Model'!I72 -> 5083 | I13: ='3 Statement Model'!J72 -> 5681.9206 | J13: ='3 Statement Model'!K72 -> 6372.9775 | K13: ='3 Statement Model'!L72 -> 6899.7575 | ... R13: ='3 Statement Model'!S72 -> 12671.755
B14: Current Liabilities | D14: ='3 Statement Model'!E106 -> 2013 | E14: ='3 Statement Model'!F106 -> 2153 | F14: ='3 Statement Model'!G106 -> 2429 | G14: ='3 Statement Model'!H106 -> 2444 | H14: ='3 Statement Model'!I106 -> 2461 | I14: ='3 Statement Model'!J106 -> 2762.8662 | J14: ='3 Statement Model'!K106 -> 3126.596 | K14: ='3 Statement Model'!L106 -> 3290.4578 | ... R14: ='3 Statement Model'!S106 -> 5899.1011
B15: Current Ratio | D15: =D13/D14 -> 1.657228 | E15: =E13/E14 -> 1.627961 | F15: =F13/F14 -> 1.5726636 | G15: =G13/G14 -> 1.6378887 | H15: =H13/H14 -> 2.0654206 | I15: =I13/I14 -> 2.0565312 | J15: =J13/J14 -> 2.0383118 | K15: =K13/K14 -> 2.096899 | ... R15: =R13/R14 -> 2.1480823
B17: Current Asset | D17: ='3 Statement Model'!E72 -> 3336 | E17: ='3 Statement Model'!F72 -> 3505 | F17: ='3 Statement Model'!G72 -> 3820 | G17: ='3 Statement Model'!H72 -> 4003 | H17: ='3 Statement Model'!I72 -> 5083 | I17: ='3 Statement Model'!J72 -> 5681.9206 | J17: ='3 Statement Model'!K72 -> 6372.9775 | K17: ='3 Statement Model'!L72 -> 6899.7575 | ... R17: ='3 Statement Model'!S72 -> 12671.755
B18: Inventory | D18: ='3 Statement Model'!E69 -> 1126 | E18: ='3 Statement Model'!F69 -> 1412 | F18: ='3 Statement Model'!G69 -> 1225 | G18: ='3 Statement Model'!H69 -> 1336 | H18: ='3 Statement Model'!I69 -> 1235 | I18: ='3 Statement Model'!J69 -> 1589.9315 | J18: ='3 Statement Model'!K69 -> 1804.5722 | K18: ='3 Statement Model'!L69 -> 1995.7801 | ... R18: ='3 Statement Model'!S69 -> 3853.6787
B19: Prepaid Expenses | D19: 0 | E19: 0 | F19: 0 | G19: 0 | H19: 0 | I19: 0 | J19: 0 | K19: 0 | L19: 0 | M19: 0 | N19: 0 | O19: 0 | P19: 0 | Q19: 0 | R19: 0
B20: Current Liabilities | D20: ='3 Statement Model'!E106 -> 2013 | E20: ='3 Statement Model'!F106 -> 2153 | F20: ='3 Statement Model'!G106 -> 2429 | G20: ='3 Statement Model'!H106 -> 2444 | H20: ='3 Statement Model'!I106 -> 2461 | I20: ='3 Statement Model'!J106 -> 2762.8662 | J20: ='3 Statement Model'!K106 -> 3126.596 | K20: ='3 Statement Model'!L106 -> 3290.4578 | ... R20: ='3 Statement Model'!S106 -> 5899.1011
B21: Quick Ratio (Acid Test) | D21: =(D17-D18-D19)/D20 -> 1.0978639 | E21: =(E17-E18-E19)/E20 -> 0.97213191 | F21: =(F17-F18-F19)/F20 -> 1.0683409 | G21: =(G17-G18-G19)/G20 -> 1.0912439 | H21: =(H17-H18-H19)/H20 -> 1.563592 | I21: =(I17-I18-I19)/I20 -> 1.4810667 | J21: =(J17-J18-J19)/J20 -> 1.4611435 | K21: =(K17-K18-K19)/K20 -> 1.4903633 | ... R21: =(R17-R18-R19)/R20 -> 1.4948169
B23: Inventory Days | D23: ='3 Statement Model'!E112 -> 56.827162 | E23: ='3 Statement Model'!F112 -> 48.694807 | F23: ='3 Statement Model'!G112 -> 49.288458 | G23: ='3 Statement Model'!H112 -> 48.418367 | H23: ='3 Statement Model'!I112 -> 43.320792 | I23: ='3 Statement Model'!J112 -> 47 | J23: ='3 Statement Model'!K112 -> 47 | K23: ='3 Statement Model'!L112 -> 46 | ... R23: ='3 Statement Model'!S112 -> 40
B24: Debtor Days | D24: ='3 Statement Model'!E111 -> 21.021061 | E24: ='3 Statement Model'!F111 -> 19.953743 | F24: ='3 Statement Model'!G111 -> 31.158081 | G24: ='3 Statement Model'!H111 -> 39.400186 | H24: ='3 Statement Model'!I111 -> 39.428492 | I24: ='3 Statement Model'!J111 -> 45 | J24: ='3 Statement Model'!K111 -> 45 | K24: ='3 Statement Model'!L111 -> 42 | ... R24: ='3 Statement Model'!S111 -> 39
B25: Creditor Days | D25: ='3 Statement Model'!E113 -> 90.266979 | E25: ='3 Statement Model'!F113 -> 83.192605 | F25: ='3 Statement Model'!G113 -> 95.359746 | G25: ='3 Statement Model'!H113 -> 116.58014 | H25: ='3 Statement Model'!I113 -> 99.717892 | I25: ='3 Statement Model'!J113 -> 105 | J25: ='3 Statement Model'!K113 -> 105 | K25: ='3 Statement Model'!L113 -> 105 | ... R25: ='3 Statement Model'!S113 -> 100
B26: Cash Conversion Days | D26: =D23+D24-D25 -> -12.418756 | E26: =E23+E24-E25 -> -14.544056 | F26: =F23+F24-F25 -> -14.913208 | G26: =G23+G24-G25 -> -28.761585 | H26: =H23+H24-H25 -> -16.968607 | I26: =I23+I24-I25 -> -13 | J26: =J23+J24-J25 -> -13 | K26: =K23+K24-K25 -> -17 | ... R26: =R23+R24-R25 -> -21
A28: # | B28: Leverage Ratio / Solvency Ratio
B30: Total Debt | D30: =SUM('3 Statement Model'!E88,'3 Statement Model'!E99) -> 348 | E30: =SUM('3 Statement Model'!F88,'3 Statement Model'!F99) -> 345 | F30: =SUM('3 Statement Model'!G88,'3 Statement Model'!G99) -> 475 | G30: =SUM('3 Statement Model'!H88,'3 Statement Model'!H99) -> 383 | H30: =SUM('3 Statement Model'!I88,'3 Statement Model'!I99) -> 379 | I30: =SUM('3 Statement Model'!J88,'3 Statement Model'!J99) -> 493.8936 | J30: =SUM('3 Statement Model'!K88,'3 Statement Model'!K99) -> 560.56924 | K30: =SUM('3 Statement Model'!L88,'3 Statement Model'!L99) -> 475.08243 | ... R30: =SUM('3 Statement Model'!S88,'3 Statement Model'!S99) -> 879.12044
B31: Total Equity | D31: ='3 Statement Model'!E84 -> 3258 | E31: ='3 Statement Model'!F84 -> 3405 | F31: ='3 Statement Model'!G84 -> 3956 | G31: ='3 Statement Model'!H84 -> 4169 | H31: ='3 Statement Model'!I84 -> 4266 | I31: ='3 Statement Model'!J84 -> 4569.4413 | J31: ='3 Statement Model'!K84 -> 4914.8771 | K31: ='3 Statement Model'!L84 -> 5308.1618 | ... R31: ='3 Statement Model'!S84 -> 9272.4831
B32: Debt to Equity Ratio | D32: =D30/D31 -> 0.106814 | E32: =E30/E31 -> 0.10132159 | F32: =F30/F31 -> 0.12007078 | G32: =G30/G31 -> 0.091868554 | H32: =H30/H31 -> 0.088842007 | I32: =I30/I31 -> 0.10808621 | J32: =J30/J31 -> 0.1140556 | K32: =K30/K31 -> 0.089500367 | ... R32: =R30/R31 -> 0.094809604
B34: Total Debt | D34: =SUM('3 Statement Model'!E88,'3 Statement Model'!E99) -> 348 | E34: =SUM('3 Statement Model'!F88,'3 Statement Model'!F99) -> 345 | F34: =SUM('3 Statement Model'!G88,'3 Statement Model'!G99) -> 475 | G34: =SUM('3 Statement Model'!H88,'3 Statement Model'!H99) -> 383 | H34: =SUM('3 Statement Model'!I88,'3 Statement Model'!I99) -> 379 | I34: =SUM('3 Statement Model'!J88,'3 Statement Model'!J99) -> 493.8936 | J34: =SUM('3 Statement Model'!K88,'3 Statement Model'!K99) -> 560.56924 | K34: =SUM('3 Statement Model'!L88,'3 Statement Model'!L99) -> 475.08243 | ... R34: =SUM('3 Statement Model'!S88,'3 Statement Model'!S99) -> 879.12044
B35: Total Asset | D35: ='3 Statement Model'!E74 -> 5510 | E35: ='3 Statement Model'!F74 -> 5786 | F35: ='3 Statement Model'!G74 -> 6946 | G35: ='3 Statement Model'!H74 -> 7421 | H35: ='3 Statement Model'!I74 -> 8338 | I35: ='3 Statement Model'!J74 -> 8943.3076 | J35: ='3 Statement Model'!K74 -> 9652.4731 | K35: ='3 Statement Model'!L74 -> 10209.62 | ... R35: ='3 Statement Model'!S74 -> 16782.584
B36: Debt to Asset Ratio | D36: =D34/D35 -> 0.063157895 | E36: =E34/E35 -> 0.059626685 | F36: =F34/F35 -> 0.068384682 | G36: =G34/G35 -> 0.051610295 | H36: =H34/H35 -> 0.045454545 | I36: =I34/I35 -> 0.055224937 | J36: =J34/J35 -> 0.058075193 | K36: =K34/K35 -> 0.046532824 | ... R36: =R34/R35 -> 0.052382901
B38: Total Equity | D38: ='3 Statement Model'!E84 -> 3258 | E38: ='3 Statement Model'!F84 -> 3405 | F38: ='3 Statement Model'!G84 -> 3956 | G38: ='3 Statement Model'!H84 -> 4169 | H38: ='3 Statement Model'!I84 -> 4266 | I38: ='3 Statement Model'!J84 -> 4569.4413 | J38: ='3 Statement Model'!K84 -> 4914.8771 | K38: ='3 Statement Model'!L84 -> 5308.1618 | ... R38: ='3 Statement Model'!S84 -> 9272.4831
B39: Total Asset | D39: ='3 Statement Model'!E74 -> 5510 | E39: ='3 Statement Model'!F74 -> 5786 | F39: ='3 Statement Model'!G74 -> 6946 | G39: ='3 Statement Model'!H74 -> 7421 | H39: ='3 Statement Model'!I74 -> 8338 | I39: ='3 Statement Model'!J74 -> 8943.3076 | J39: ='3 Statement Model'!K74 -> 9652.4731 | K39: ='3 Statement Model'!L74 -> 10209.62 | ... R39: ='3 Statement Model'!S74 -> 16782.584
B40: Equity To Asset Ratio | D40: =D38/D39 -> 0.59128857 | E40: =E38/E39 -> 0.58848946 | F40: =F38/F39 -> 0.56953642 | G40: =G38/G39 -> 0.56178413 | H40: =H38/H39 -> 0.51163349 | I40: =I38/I39 -> 0.51093416 | J40: =J38/J39 -> 0.5091832 | K40: =K38/K39 -> 0.51991769 | ... R40: =R38/R39 -> 0.55250628
A42: # | B42: Profitability Ratio
B44: Gross Profit | D44: ='3 Statement Model'!E15 -> 3778 | E44: ='3 Statement Model'!F15 -> 4076 | F44: ='3 Statement Model'!G15 -> 4413 | G44: ='3 Statement Model'!H15 -> 4905 | H44: ='3 Statement Model'!I15 -> 5443 | I44: ='3 Statement Model'!J15 -> 5926.7232 | J44: ='3 Statement Model'!K15 -> 6726.8308 | K44: ='3 Statement Model'!L15 -> 7601.3188 | ... R44: ='3 Statement Model'!S15 -> 17582.409
B45: Total Sales | D45: ='3 Statement Model'!E13 -> 8048 | E45: ='3 Statement Model'!F13 -> 9512 | F45: ='3 Statement Model'!G13 -> 9764 | G45: ='3 Statement Model'!H13 -> 9653 | H45: ='3 Statement Model'!I13 -> 10831 | I45: ='3 Statement Model'!J13 -> 12347.34 | J45: ='3 Statement Model'!K13 -> 14014.231 | K45: ='3 Statement Model'!L13 -> 15836.081 | ... R45: ='3 Statement Model'!S13 -> 35164.818
B46: Gross Profit Margin | D46: =D44/D45 -> 0.4694334 | E46: =E44/E45 -> 0.42851135 | F46: =F44/F45 -> 0.45196641 | G46: =G44/G45 -> 0.50813219 | H46: =H44/H45 -> 0.50253901 | I46: =I44/I45 -> 0.48 | J46: =J44/J45 -> 0.48 | K46: =K44/K45 -> 0.48 | ... R46: =R44/R45 -> 0.5
B48: EBITDA | D48: ='3 Statement Model'!E25 -> 1602 | E48: ='3 Statement Model'!F25 -> 1681 | F48: ='3 Statement Model'!G25 -> 1810 | G48: ='3 Statement Model'!H25 -> 2026 | H48: ='3 Statement Model'!I25 -> 2139 | I48: ='3 Statement Model'!J25 -> 2086.7005 | J48: ='3 Statement Model'!K25 -> 2368.405 | K48: ='3 Statement Model'!L25 -> 2676.2977 | ... R48: ='3 Statement Model'!S25 -> 6646.1506
B49: Total Sales | D49: ='3 Statement Model'!E13 -> 8048 | E49: ='3 Statement Model'!F13 -> 9512 | F49: ='3 Statement Model'!G13 -> 9764 | G49: ='3 Statement Model'!H13 -> 9653 | H49: ='3 Statement Model'!I13 -> 10831 | I49: ='3 Statement Model'!J13 -> 12347.34 | J49: ='3 Statement Model'!K13 -> 14014.231 | K49: ='3 Statement Model'!L13 -> 15836.081 | ... R49: ='3 Statement Model'!S13 -> 35164.818
B50: EBITDA Margin | D50: =D48/D49 -> 0.19905567 | E50: =E48/E49 -> 0.17672414 | F50: =F48/F49 -> 0.18537485 | G50: =G48/G49 -> 0.20988294 | H50: =H48/H49 -> 0.19748869 | I50: =I48/I49 -> 0.169 | J50: =J48/J49 -> 0.169 | K50: =K48/K49 -> 0.169 | ... R50: =R48/R49 -> 0.189
B52: EBIT | D52: ='3 Statement Model'!E30 -> 1463 | E52: ='3 Statement Model'!F30 -> 1542 | F52: ='3 Statement Model'!G30 -> 1655 | G52: ='3 Statement Model'!H30 -> 1868 | H52: ='3 Statement Model'!I30 -> 1961 | I52: ='3 Statement Model'!J30 -> 1895.53 | J52: ='3 Statement Model'!K30 -> 2162.286 | K52: ='3 Statement Model'!L30 -> 2453.2868 | ... R52: ='3 Statement Model'!S30 -> 6294.6181
B53: Total Sales | D53: ='3 Statement Model'!E13 -> 8048 | E53: ='3 Statement Model'!F13 -> 9512 | F53: ='3 Statement Model'!G13 -> 9764 | G53: ='3 Statement Model'!H13 -> 9653 | H53: ='3 Statement Model'!I13 -> 10831 | I53: ='3 Statement Model'!J13 -> 12347.34 | J53: ='3 Statement Model'!K13 -> 14014.231 | K53: ='3 Statement Model'!L13 -> 15836.081 | ... R53: ='3 Statement Model'!S13 -> 35164.818
B54: EBIT Margin | D54: =D52/D53 -> 0.18178429 | E54: =E52/E53 -> 0.16211102 | F54: =F52/F53 -> 0.1695002 | G54: =G52/G53 -> 0.19351497 | H54: =H52/H53 -> 0.18105438 | I54: =I52/I53 -> 0.15351727 | J54: =J52/J53 -> 0.15429216 | K54: =K52/K53 -> 0.15491755 | ... R54: =R52/R53 -> 0.17900329
B56: Net Profit | D56: ='3 Statement Model'!E39 -> 1199 | E56: ='3 Statement Model'!F39 -> 1255 | F56: ='3 Statement Model'!G39 -> 1322 | G56: ='3 Statement Model'!H39 -> 1502 | H56: ='3 Statement Model'!I39 -> 1658 | I56: ='3 Statement Model'!J39 -> 1517.2067 | J56: ='3 Statement Model'!K39 -> 1727.1787 | K56: ='3 Statement Model'!L39 -> 1966.4236 | ... R56: ='3 Statement Model'!S39 -> 5030.5038
B57: Total Sales | D57: ='3 Statement Model'!E13 -> 8048 | E57: ='3 Statement Model'!F13 -> 9512 | F57: ='3 Statement Model'!G13 -> 9764 | G57: ='3 Statement Model'!H13 -> 9653 | H57: ='3 Statement Model'!I13 -> 10831 | I57: ='3 Statement Model'!J13 -> 12347.34 | J57: ='3 Statement Model'!K13 -> 14014.231 | K57: ='3 Statement Model'!L13 -> 15836.081 | ... R57: ='3 Statement Model'!S13 -> 35164.818
B58: Net Profit Margin | D58: =D56/D57 -> 0.14898111 | E58: =E56/E57 -> 0.1319386 | F58: =F56/F57 -> 0.13539533 | G58: =G56/G57 -> 0.1555993 | H58: =H56/H57 -> 0.15307912 | I58: =I56/I57 -> 0.12287721 | J58: =J56/J57 -> 0.12324463 | K58: =K56/K57 -> 0.12417362 | ... R58: =R56/R57 -> 0.14305502
B60: Net Profit | D60: ='3 Statement Model'!E39 -> 1199 | E60: ='3 Statement Model'!F39 -> 1255 | F60: ='3 Statement Model'!G39 -> 1322 | G60: ='3 Statement Model'!H39 -> 1502 | H60: ='3 Statement Model'!I39 -> 1658 | I60: ='3 Statement Model'!J39 -> 1517.2067 | J60: ='3 Statement Model'!K39 -> 1727.1787 | K60: ='3 Statement Model'!L39 -> 1966.4236 | ... R60: ='3 Statement Model'!S39 -> 5030.5038
B61: Total Asset | D61: ='3 Statement Model'!E74 -> 5510 | E61: ='3 Statement Model'!F74 -> 5786 | F61: ='3 Statement Model'!G74 -> 6946 | G61: ='3 Statement Model'!H74 -> 7421 | H61: ='3 Statement Model'!I74 -> 8338 | I61: ='3 Statement Model'!J74 -> 8943.3076 | J61: ='3 Statement Model'!K74 -> 9652.4731 | K61: ='3 Statement Model'!L74 -> 10209.62 | ... R61: ='3 Statement Model'!S74 -> 16782.584
B62: Return on Asset | D62: =D60/D61 -> 0.21760436 | E62: =E60/E61 -> 0.21690287 | F62: =F60/F61 -> 0.19032537 | G62: =G60/G61 -> 0.2023986 | H62: =H60/H61 -> 0.19884864 | I62: =I60/I61 -> 0.16964716 | J62: =J60/J61 -> 0.1789364 | K62: =K60/K61 -> 0.19260498 | ... R62: =R60/R61 -> 0.29974548
B64: Net Profit | D64: ='3 Statement Model'!E39 -> 1199 | E64: ='3 Statement Model'!F39 -> 1255 | F64: ='3 Statement Model'!G39 -> 1322 | G64: ='3 Statement Model'!H39 -> 1502 | H64: ='3 Statement Model'!I39 -> 1658 | I64: ='3 Statement Model'!J39 -> 1517.2067 | J64: ='3 Statement Model'!K39 -> 1727.1787 | K64: ='3 Statement Model'!L39 -> 1966.4236 | ... R64: ='3 Statement Model'!S39 -> 5030.5038
B65: Total Equity | D65: ='3 Statement Model'!E84 -> 3258 | E65: ='3 Statement Model'!F84 -> 3405 | F65: ='3 Statement Model'!G84 -> 3956 | G65: ='3 Statement Model'!H84 -> 4169 | H65: ='3 Statement Model'!I84 -> 4266 | I65: ='3 Statement Model'!J84 -> 4569.4413 | J65: ='3 Statement Model'!K84 -> 4914.8771 | K65: ='3 Statement Model'!L84 -> 5308.1618 | ... R65: ='3 Statement Model'!S84 -> 9272.4831
B66: Return on Equity | D66: =D64/D65 -> 0.36801719 | E66: =E64/E65 -> 0.36857562 | F66: =F64/F65 -> 0.33417594 | G66: =G64/G65 -> 0.36027824 | H66: =H64/H65 -> 0.38865448 | I66: =I64/I65 -> 0.33203331 | J66: =J64/J65 -> 0.3514185 | K66: =K64/K65 -> 0.37045283 | ... R66: =R64/R65 -> 0.5425196
A68: # | B68: Efficiency Ratio
B70: Revenue | D70: ='3 Statement Model'!E13 -> 8048 | E70: ='3 Statement Model'!F13 -> 9512 | F70: ='3 Statement Model'!G13 -> 9764 | G70: ='3 Statement Model'!H13 -> 9653 | H70: ='3 Statement Model'!I13 -> 10831 | I70: ='3 Statement Model'!J13 -> 12347.34 | J70: ='3 Statement Model'!K13 -> 14014.231 | K70: ='3 Statement Model'!L13 -> 15836.081 | ... R70: ='3 Statement Model'!S13 -> 35164.818
B71: Total Asset | D71: ='3 Statement Model'!E74 -> 5510 | E71: ='3 Statement Model'!F74 -> 5786 | F71: ='3 Statement Model'!G74 -> 6946 | G71: ='3 Statement Model'!H74 -> 7421 | H71: ='3 Statement Model'!I74 -> 8338 | I71: ='3 Statement Model'!J74 -> 8943.3076 | J71: ='3 Statement Model'!K74 -> 9652.4731 | K71: ='3 Statement Model'!L74 -> 10209.62 | ... R71: ='3 Statement Model'!S74 -> 16782.584
B72: Asset Turnover Ratio | D72: =D70/D71 -> 1.4606171 | E72: =E70/E71 -> 1.6439682 | F72: =F70/F71 -> 1.4057011 | G72: =G70/G71 -> 1.3007681 | H72: =H70/H71 -> 1.2989926 | I72: =I70/I71 -> 1.3806234 | J72: =J70/J71 -> 1.4518798 | K72: =K70/K71 -> 1.5510941 | ... R72: =R70/R71 -> 2.095316
B74: Change in Revenue | D74: ='3 Statement Model'!E13-'3 Statement Model'!D13 -> 733 | E74: ='3 Statement Model'!F13-'3 Statement Model'!E13 -> 1464 | F74: ='3 Statement Model'!G13-'3 Statement Model'!F13 -> 252 | G74: ='3 Statement Model'!H13-'3 Statement Model'!G13 -> -111 | H74: ='3 Statement Model'!I13-'3 Statement Model'!H13 -> 1178 | I74: ='3 Statement Model'!J13-'3 Statement Model'!I13 -> 1516.34 | J74: ='3 Statement Model'!K13-'3 Statement Model'!J13 -> 1666.8909 | K74: ='3 Statement Model'!L13-'3 Statement Model'!K13 -> 1821.85 | ... R74: ='3 Statement Model'!S13-'3 Statement Model'!R13 -> 3767.659
B75: Change in Asset | D75: ='3 Statement Model'!E74-'3 Statement Model'!D74 -> 508 | E75: ='3 Statement Model'!F74-'3 Statement Model'!E74 -> 276 | F75: ='3 Statement Model'!G74-'3 Statement Model'!F74 -> 1160 | G75: ='3 Statement Model'!H74-'3 Statement Model'!G74 -> 475 | H75: ='3 Statement Model'!I74-'3 Statement Model'!H74 -> 917 | I75: ='3 Statement Model'!J74-'3 Statement Model'!I74 -> 605.30755 | J75: ='3 Statement Model'!K74-'3 Statement Model'!J74 -> 709.16553 | K75: ='3 Statement Model'!L74-'3 Statement Model'!K74 -> 557.14651 | ... R75: ='3 Statement Model'!S74-'3 Statement Model'!R74 -> 1309.5864
B76: Reinvestment Ratio | D76: =D74/D75 -> 1.4429134 | E76: =E74/E75 -> 5.3043478 | F76: =F74/F75 -> 0.21724138 | G76: =G74/G75 -> -0.23368421 | H76: =H74/H75 -> 1.2846238 | I76: =I74/I75 -> 2.5050737 | J76: =J74/J75 -> 2.3504962 | K76: =K74/K75 -> 3.2699657 | ... R76: =R74/R75 -> 2.8769839
B78: COGS | D78: ='3 Statement Model'!E14 -> 4270 | E78: ='3 Statement Model'!F14 -> 5436 | F78: ='3 Statement Model'!G14 -> 5351 | G78: ='3 Statement Model'!H14 -> 4748 | H78: ='3 Statement Model'!I14 -> 5388 | I78: ='3 Statement Model'!J14 -> 6420.6168 | J78: ='3 Statement Model'!K14 -> 7287.4001 | K78: ='3 Statement Model'!L14 -> 8234.7621 | ... R78: ='3 Statement Model'!S14 -> 17582.409
B79: Inventory | D79: ='3 Statement Model'!E69 -> 1126 | E79: ='3 Statement Model'!F69 -> 1412 | F79: ='3 Statement Model'!G69 -> 1225 | G79: ='3 Statement Model'!H69 -> 1336 | H79: ='3 Statement Model'!I69 -> 1235 | I79: ='3 Statement Model'!J69 -> 1589.9315 | J79: ='3 Statement Model'!K69 -> 1804.5722 | K79: ='3 Statement Model'!L69 -> 1995.7801 | ... R79: ='3 Statement Model'!S69 -> 3853.6787
B80: Inventory Turnover Ratio | D80: =D78/D79 -> 3.7921847 | E80: =E78/E79 -> 3.8498584 | F80: =F78/F79 -> 4.3681633 | G80: =G78/G79 -> 3.5538922 | H80: =H78/H79 -> 4.362753 | I80: =I78/I79 -> 4.0382979 | J80: =J78/J79 -> 4.0382979 | K80: =K78/K79 -> 4.126087 | ... R80: =R78/R79 -> 4.5625
A82: # | B82: Coverage Ratio
B84: Total Debt | D84: =SUM('3 Statement Model'!E88,'3 Statement Model'!E99) -> 348 | E84: =SUM('3 Statement Model'!F88,'3 Statement Model'!F99) -> 345 | F84: =SUM('3 Statement Model'!G88,'3 Statement Model'!G99) -> 475 | G84: =SUM('3 Statement Model'!H88,'3 Statement Model'!H99) -> 383 | H84: =SUM('3 Statement Model'!I88,'3 Statement Model'!I99) -> 379 | I84: =SUM('3 Statement Model'!J88,'3 Statement Model'!J99) -> 493.8936 | J84: =SUM('3 Statement Model'!K88,'3 Statement Model'!K99) -> 560.56924 | K84: =SUM('3 Statement Model'!L88,'3 Statement Model'!L99) -> 475.08243 | ... R84: =SUM('3 Statement Model'!S88,'3 Statement Model'!S99) -> 879.12044
B85: EBITDA | D85: ='3 Statement Model'!E25 -> 1602 | E85: ='3 Statement Model'!F25 -> 1681 | F85: ='3 Statement Model'!G25 -> 1810 | G85: ='3 Statement Model'!H25 -> 2026 | H85: ='3 Statement Model'!I25 -> 2139 | I85: ='3 Statement Model'!J25 -> 2086.7005 | J85: ='3 Statement Model'!K25 -> 2368.405 | K85: ='3 Statement Model'!L25 -> 2676.2977 | ... R85: ='3 Statement Model'!S25 -> 6646.1506
B86: Debt to EBITDA Coverage Ratio | D86: =D84/D85 -> 0.21722846 | E86: =E84/E85 -> 0.20523498 | F86: =F84/F85 -> 0.26243094 | G86: =G84/G85 -> 0.18904245 | H86: =H84/H85 -> 0.1771856 | I86: =I84/I85 -> 0.23668639 | J86: =J84/J85 -> 0.23668639 | K86: =K84/K85 -> 0.17751479 | ... R86: =R84/R85 -> 0.13227513
B88: EBIT | D88: ='3 Statement Model'!E30 -> 1463 | E88: ='3 Statement Model'!F30 -> 1542 | F88: ='3 Statement Model'!G30 -> 1655 | G88: ='3 Statement Model'!H30 -> 1868 | H88: ='3 Statement Model'!I30 -> 1961 | I88: ='3 Statement Model'!J30 -> 1895.53 | J88: ='3 Statement Model'!K30 -> 2162.286 | K88: ='3 Statement Model'!L30 -> 2453.2868 | ... R88: ='3 Statement Model'!S30 -> 6294.6181
B89: Interest | D89: ='3 Statement Model'!E34 -> 34 | E89: ='3 Statement Model'!F34 -> 39 | F89: ='3 Statement Model'!G34 -> 56 | G89: ='3 Statement Model'!H34 -> 73 | H89: ='3 Statement Model'!I34 -> 53 | I89: ='3 Statement Model'!J34 -> 54.55585 | J89: ='3 Statement Model'!K34 -> 65.903927 | K89: ='3 Statement Model'!L34 -> 64.728229 | ... R89: ='3 Statement Model'!S34 -> 104.00309
B90: Interest Coverage Ratio | D90: =D88/D89 -> 43.029412 | E90: =E88/E89 -> 39.538462 | F90: =F88/F89 -> 29.553571 | G90: =G88/G89 -> 25.589041 | H90: =H88/H89 -> 37 | I90: =I88/I89 -> 34.744761 | J90: =J88/J89 -> 32.809669 | K90: =K88/K89 -> 37.901344 | ... R90: =R88/R89 -> 60.523377

Sheet Common Size Statement
B2: Marico Ltd
B3: 3 Statement Model
K4: Current Case
D8: Actual | J8: Explicit Forecast Period | O8: Maturity Period
B9: In INR crores unless started otherwise | D9: 2020 | E9: 2021 | F9: 2022 | G9: 2023 | H9: 2024 | I9: 2025 | J9: 2026 | K9: 2027 | L9: 2028 | M9: 2029 | N9: 2030 | O9: =N9+1 -> 2031 | P9: =O9+1 -> 2032 | Q9: =P9+1 -> 2033 | R9: =Q9+1 -> 2034 | S9: =R9+1 -> 2035
A11: # | B11: Income Statement
B13: Revenue | D13: ='3 Statement Model'!D13/'3 Statement Model'!D$13 -> 1 | E13: ='3 Statement Model'!E13/'3 Statement Model'!E$13 -> 1 | F13: ='3 Statement Model'!F13/'3 Statement Model'!F$13 -> 1 | G13: ='3 Statement Model'!G13/'3 Statement Model'!G$13 -> 1 | H13: ='3 Statement Model'!H13/'3 Statement Model'!H$13 -> 1 | I13: ='3 Statement Model'!I13/'3 Statement Model'!I$13 -> 1 | J13: ='3 Statement Model'!J13/'3 Statement Model'!J$13 -> 1 | K13: ='3 Statement Model'!K13/'3 Statement Model'!K$13 -> 1 | ... S13: ='3 Statement Model'!S13/'3 Statement Model'!S$13 -> 1
B14: Less: Cost of Goods Sold | D14: ='3 Statement Model'!D14/'3 Statement Model'!D$13 -> 0.51196172 | E14: ='3 Statement Model'!E14/'3 Statement Model'!E$13 -> 0.5305666 | F14: ='3 Statement Model'!F14/'3 Statement Model'!F$13 -> 0.57148865 | G14: ='3 Statement Model'!G14/'3 Statement Model'!G$13 -> 0.54803359 | H14: ='3 Statement Model'!H14/'3 Statement Model'!H$13 -> 0.49186781 | I14: ='3 Statement Model'!I14/'3 Statement Model'!I$13 -> 0.49746099 | J14: ='3 Statement Model'!J14/'3 Statement Model'!J$13 -> 0.52 | K14: ='3 Statement Model'!K14/'3 Statement Model'!K$13 -> 0.52 | ... S14: ='3 Statement Model'!S14/'3 Statement Model'!S$13 -> 0.5
B15: Gross Profit | D15: ='3 Statement Model'!D15/'3 Statement Model'!D$13 -> 0.48803828 | E15: ='3 Statement Model'!E15/'3 Statement Model'!E$13 -> 0.4694334 | F15: ='3 Statement Model'!F15/'3 Statement Model'!F$13 -> 0.42851135 | G15: ='3 Statement Model'!G15/'3 Statement Model'!G$13 -> 0.45196641 | H15: ='3 Statement Model'!H15/'3 Statement Model'!H$13 -> 0.50813219 | I15: ='3 Statement Model'!I15/'3 Statement Model'!I$13 -> 0.50253901 | J15: ='3 Statement Model'!J15/'3 Statement Model'!J$13 -> 0.48 | K15: ='3 Statement Model'!K15/'3 Statement Model'!K$13 -> 0.48 | ... S15: ='3 Statement Model'!S15/'3 Statement Model'!S$13 -> 0.5
B17: Gross Margin | D17: 0.48803828 | E17: 0.4694334 | F17: 0.42851135 | G17: 0.45196641 | H17: 0.50813219 | I17: 0.50253901 | J17: 0.48 | K17: 0.48 | L17: 0.48 | M17: 0.5 | N17: 0.5 | O17: 0.5 | P17: 0.5 | Q17: 0.5 | R17: 0.5 | S17: 0.5
B19: Less: SG&A Expenses (Excluding Depreciation & Interest)
B20: Employee Benefit Cost | D20: ='3 Statement Model'!D20/'3 Statement Model'!D$13 -> 0.065345181 | E20: ='3 Statement Model'!E20/'3 Statement Model'!E$13 -> 0.07082505 | F20: ='3 Statement Model'!F20/'3 Statement Model'!F$13 -> 0.061606392 | G20: ='3 Statement Model'!G20/'3 Statement Model'!G$13 -> 0.066878329 | H20: ='3 Statement Model'!H20/'3 Statement Model'!H$13 -> 0.07697089 | I20: ='3 Statement Model'!I20/'3 Statement Model'!I$13 -> 0.076724218 | J20: ='3 Statement Model'!J20/'3 Statement Model'!J$13 -> 0.076 | K20: ='3 Statement Model'!K20/'3 Statement Model'!K$13 -> 0.076 | ... S20: ='3 Statement Model'!S20/'3 Statement Model'!S$13 -> 0.076
B21: Advertisement and sales promotion | D21: ='3 Statement Model'!D21/'3 Statement Model'!D$13 -> 0.099384826 | E21: ='3 Statement Model'!E21/'3 Statement Model'!E$13 -> 0.086729622 | F21: ='3 Statement Model'!F21/'3 Statement Model'!F$13 -> 0.083683768 | G21: ='3 Statement Model'!G21/'3 Statement Model'!G$13 -> 0.08623515 | H21: ='3 Statement Model'!H21/'3 Statement Model'!H$13 -> 0.09862219 | I21: ='3 Statement Model'!I21/'3 Statement Model'!I$13 -> 0.10414551 | J21: ='3 Statement Model'!J21/'3 Statement Model'!J$13 -> 0.115 | K21: ='3 Statement Model'!K21/'3 Statement Model'!K$13 -> 0.115 | ... S21: ='3 Statement Model'!S21/'3 Statement Model'!S$13 -> 0.115
B22: Freight and distribution expenses | D22: ='3 Statement Model'!D22/'3 Statement Model'!D$13 -> 0.040191388 | E22: ='3 Statement Model'!E22/'3 Statement Model'!E$13 -> 0.037897614 | F22: ='3 Statement Model'!F22/'3 Statement Model'!F$13 -> 0.037216148 | G22: ='3 Statement Model'!G22/'3 Statement Model'!G$13 -> 0.039635395 | H22: ='3 Statement Model'!H22/'3 Statement Model'!H$13 -> 0.043095411 | I22: ='3 Statement Model'!I22/'3 Statement Model'!I$13 -> 0.041455083 | J22: ='3 Statement Model'!J22/'3 Statement Model'!J$13 -> 0.04 | K22: ='3 Statement Model'!K22/'3 Statement Model'!K$13 -> 0.04 | ... S22: ='3 Statement Model'!S22/'3 Statement Model'!S$13 -> 0.04
B23: Other Misc SG&A Expenses | D23: ='3 Statement Model'!D23/'3 Statement Model'!D$13 -> 0.086261107 | E23: ='3 Statement Model'!E23/'3 Statement Model'!E$13 -> 0.074925447 | F23: ='3 Statement Model'!F23/'3 Statement Model'!F$13 -> 0.069280908 | G23: ='3 Statement Model'!G23/'3 Statement Model'!G$13 -> 0.073842687 | H23: ='3 Statement Model'!H23/'3 Statement Model'!H$13 -> 0.079560758 | I23: ='3 Statement Model'!I23/'3 Statement Model'!I$13 -> 0.08272551 | J23: ='3 Statement Model'!J23/'3 Statement Model'!J$13 -> 0.08 | K23: ='3 Statement Model'!K23/'3 Statement Model'!K$13 -> 0.08 | ... S23: ='3 Statement Model'!S23/'3 Statement Model'!S$13 -> 0.08
B25: EBITDA | D25: ='3 Statement Model'!D25/'3 Statement Model'!D$13 -> 0.19685578 | E25: ='3 Statement Model'!E25/'3 Statement Model'!E$13 -> 0.19905567 | F25: ='3 Statement Model'!F25/'3 Statement Model'!F$13 -> 0.17672414 | G25: ='3 Statement Model'!G25/'3 Statement Model'!G$13 -> 0.18537485 | H25: ='3 Statement Model'!H25/'3 Statement Model'!H$13 -> 0.20988294 | I25: ='3 Statement Model'!I25/'3 Statement Model'!I$13 -> 0.19748869 | J25: ='3 Statement Model'!J25/'3 Statement Model'!J$13 -> 0.169 | K25: ='3 Statement Model'!K25/'3 Statement Model'!K$13 -> 0.169 | ... S25: ='3 Statement Model'!S25/'3 Statement Model'!S$13 -> 0.189
B27: EBITDA | D27: 0.19685578 | E27: 0.19905567 | F27: 0.17672414 | G27: 0.18537485 | H27: 0.20988294 | I27: 0.19748869 | J27: 0.169 | K27: 0.169 | L27: 0.169 | M27: 0.189 | N27: 0.189 | O27: 0.189 | P27: 0.189 | Q27: 0.189 | R27: 0.189 | S27: 0.189
B29: Less: Depreciation & Amortization | D29: ='3 Statement Model'!D29/'3 Statement Model'!D$13 -> 0.019138756 | E29: ='3 Statement Model'!E29/'3 Statement Model'!E$13 -> 0.017271372 | F29: ='3 Statement Model'!F29/'3 Statement Model'!F$13 -> 0.01461312 | G29: ='3 Statement Model'!G29/'3 Statement Model'!G$13 -> 0.015874642 | H29: ='3 Statement Model'!H29/'3 Statement Model'!H$13 -> 0.016367969 | I29: ='3 Statement Model'!I29/'3 Statement Model'!I$13 -> 0.016434309 | J29: ='3 Statement Model'!J29/'3 Statement Model'!J$13 -> 0.015482727 | K29: ='3 Statement Model'!K29/'3 Statement Model'!K$13 -> 0.014707836 | ... S29: ='3 Statement Model'!S29/'3 Statement Model'!S$13 -> 0.0099967078
B30: EBIT | D30: ='3 Statement Model'!D30/'3 Statement Model'!D$13 -> 0.17771702 | E30: ='3 Statement Model'!E30/'3 Statement Model'!E$13 -> 0.18178429 | F30: ='3 Statement Model'!F30/'3 Statement Model'!F$13 -> 0.16211102 | G30: ='3 Statement Model'!G30/'3 Statement Model'!G$13 -> 0.1695002 | H30: ='3 Statement Model'!H30/'3 Statement Model'!H$13 -> 0.19351497 | I30: ='3 Statement Model'!I30/'3 Statement Model'!I$13 -> 0.18105438 | J30: ='3 Statement Model'!J30/'3 Statement Model'!J$13 -> 0.15351727 | K30: ='3 Statement Model'!K30/'3 Statement Model'!K$13 -> 0.15429216 | ... S30: ='3 Statement Model'!S30/'3 Statement Model'!S$13 -> 0.17900329
B32: EBIT Margin | D32: 0.17771702 | E32: 0.18178429 | F32: 0.16211102 | G32: 0.1695002 | H32: 0.19351497 | I32: 0.18105438 | J32: 0.15351727 | K32: 0.15429216 | L32: 0.15491755 | M32: 0.1754156 | N32: 0.17755849 | O32: 0.17755849 | P32: 0.17755849 | Q32: 0.17755849 | R32: 0.17755849 | S32: 0.17755849
B34: Less: Interest | D34: ='3 Statement Model'!D34/'3 Statement Model'!D$13 -> 0.00683527 | E34: ='3 Statement Model'!E34/'3 Statement Model'!E$13 -> 0.0042246521 | F34: ='3 Statement Model'!F34/'3 Statement Model'!F$13 -> 0.0041000841 | G34: ='3 Statement Model'!G34/'3 Statement Model'!G$13 -> 0.0057353544 | H34: ='3 Statement Model'!H34/'3 Statement Model'!H$13 -> 0.0075624158 | I34: ='3 Statement Model'!I34/'3 Statement Model'!I$13 -> 0.0048933616 | J34: ='3 Statement Model'!J34/'3 Statement Model'!J$13 -> 0.0044184294 | K34: ='3 Statement Model'!K34/'3 Statement Model'!K$13 -> 0.0047026432 | ... S34: ='3 Statement Model'!S34/'3 Statement Model'!S$13 -> 0.0029575893
B35: Add: Other Income | D35: ='3 Statement Model'!D35/'3 Statement Model'!D$13 -> 0.01695147 | E35: ='3 Statement Model'!E35/'3 Statement Model'!E$13 -> 0.01167992 | F35: ='3 Statement Model'!F35/'3 Statement Model'!F$13 -> 0.010302775 | G35: ='3 Statement Model'!G35/'3 Statement Model'!G$13 -> 0.014748054 | H35: ='3 Statement Model'!H35/'3 Statement Model'!H$13 -> 0.014710453 | I35: ='3 Statement Model'!I35/'3 Statement Model'!I$13 -> 0.019204136 | J35: ='3 Statement Model'!J35/'3 Statement Model'!J$13 -> 0.015 | K35: ='3 Statement Model'!K35/'3 Statement Model'!K$13 -> 0.015 | ... S35: ='3 Statement Model'!S35/'3 Statement Model'!S$13 -> 0.015
B36: EBT | D36: ='3 Statement Model'!D36/'3 Statement Model'!D$13 -> 0.18783322 | E36: ='3 Statement Model'!E36/'3 Statement Model'!E$13 -> 0.18923956 | F36: ='3 Statement Model'!F36/'3 Statement Model'!F$13 -> 0.16831371 | G36: ='3 Statement Model'!G36/'3 Statement Model'!G$13 -> 0.1785129 | H36: ='3 Statement Model'!H36/'3 Statement Model'!H$13 -> 0.20066301 | I36: ='3 Statement Model'!I36/'3 Statement Model'!I$13 -> 0.19536516 | J36: ='3 Statement Model'!J36/'3 Statement Model'!J$13 -> 0.16409884 | K36: ='3 Statement Model'!K36/'3 Statement Model'!K$13 -> 0.16458952 | ... S36: ='3 Statement Model'!S36/'3 Statement Model'!S$13 -> 0.1910457
B38: Less: Taxes | D38: ='3 Statement Model'!D38/'3 Statement Model'!D$13 -> 0.045249487 | E38: ='3 Statement Model'!E38/'3 Statement Model'!E$13 -> 0.040258449 | F38: ='3 Statement Model'!F38/'3 Statement Model'!F$13 -> 0.036375105 | G38: ='3 Statement Model'!G38/'3 Statement Model'!G$13 -> 0.043117575 | H38: ='3 Statement Model'!H38/'3 Statement Model'!H$13 -> 0.045063711 | I38: ='3 Statement Model'!I38/'3 Statement Model'!I$13 -> 0.042286031 | J38: ='3 Statement Model'!J38/'3 Statement Model'!J$13 -> 0.041221629 | K38: ='3 Statement Model'!K38/'3 Statement Model'!K$13 -> 0.041344888 | ... S38: ='3 Statement Model'!S38/'3 Statement Model'!S$13 -> 0.047990681
B39: Net Income | D39: ='3 Statement Model'!D39/'3 Statement Model'!D$13 -> 0.14258373 | E39: ='3 Statement Model'!E39/'3 Statement Model'!E$13 -> 0.14898111 | F39: ='3 Statement Model'!F39/'3 Statement Model'!F$13 -> 0.1319386 | G39: ='3 Statement Model'!G39/'3 Statement Model'!G$13 -> 0.13539533 | H39: ='3 Statement Model'!H39/'3 Statement Model'!H$13 -> 0.1555993 | I39: ='3 Statement Model'!I39/'3 Statement Model'!I$13 -> 0.15307912 | J39: ='3 Statement Model'!J39/'3 Statement Model'!J$13 -> 0.12287721 | K39: ='3 Statement Model'!K39/'3 Statement Model'!K$13 -> 0.12324463 | ... S39: ='3 Statement Model'!S39/'3 Statement Model'!S$13 -> 0.14305502
B41: Sales Growth % | D41: NM | E41: 0.10020506 | F41: 0.18190855 | G41: 0.026492851 | H41: -0.011368292 | I41: 0.1220346 | J41: 0.14 | K41: 0.135 | L41: 0.13 | M41: 0.125 | N41: 0.12 | O41: 0.12 | P41: 0.12 | Q41: 0.12 | R41: 0.12 | S41: 0.12
B42: Gross Profit Margin % | D42: 0.48803828 | E42: 0.4694334 | F42: 0.42851135 | G42: 0.45196641 | H42: 0.50813219 | I42: 0.50253901 | J42: 0.48 | K42: 0.48 | L42: 0.48 | M42: 0.5 | N42: 0.5 | O42: 0.5 | P42: 0.5 | Q42: 0.5 | R42: 0.5 | S42: 0.5
B43: EBITDA Margin % | D43: 0.19685578 | E43: 0.19905567 | F43: 0.17672414 | G43: 0.18537485 | H43: 0.20988294 | I43: 0.19748869 | J43: 0.169 | K43: 0.169 | L43: 0.169 | M43: 0.189 | N43: 0.189 | O43: 0.189 | P43: 0.189 | Q43: 0.189 | R43: 0.189 | S43: 0.189
B44: EBIT Margin % | D44: 0.17771702 | E44: 0.18178429 | F44: 0.16211102 | G44: 0.1695002 | H44: 0.19351497 | I44: 0.18105438 | J44: 0.15351727 | K44: 0.15429216 | L44: 0.15491755 | M44: 0.1754156 | N44: 0.17755849 | O44: 0.17755849 | P44: 0.17755849 | Q44: 0.17755849 | R44: 0.17755849 | S44: 0.17755849
B45: Actual Tax Rate % | D45: 0.24090247 | E45: 0.21273802 | F45: 0.21611493 | G45: 0.24153758 | H45: 0.22457408 | I45: 0.21644612 | J45: 0.25 | K45: 0.25 | L45: 0.25 | M45: 0.25 | N45: 0.25 | O45: 0.25 | P45: 0.25 | Q45: 0.25 | R45: 0.25 | S45: 0.25
B46: Net Income Margin % | D46: 0.14258373 | E46: 0.14898111 | F46: 0.1319386 | G46: 0.13539533 | H46: 0.1555993 | I46: 0.15307912 | J46: 0.12294158 | K46: 0.12330106 | L46: 0.12425 | M46: 0.1400492 | N46: 0.14165056 | O46: 0.14165056 | P46: 0.14165056 | Q46: 0.14165056 | R46: 0.14165056 | S46: 0.14165056
A48: # | B48: Balance Sheet
B50: Assets
B52: Non Current Assets
B53: Property, Plant & Equipment | D53: ='3 Statement Model'!D54/'3 Statement Model'!D$74 -> 0.1307477 | E53: ='3 Statement Model'!E54/'3 Statement Model'!E$74 -> 0.10381125 | F53: ='3 Statement Model'!F54/'3 Statement Model'!F$74 -> 0.10369858 | G53: ='3 Statement Model'!G54/'3 Statement Model'!G$74 -> 0.091131587 | H53: ='3 Statement Model'!H54/'3 Statement Model'!H$74 -> 0.09432691 | I53: ='3 Statement Model'!I54/'3 Statement Model'!I$74 -> 0.085152315 | J53: ='3 Statement Model'!J54/'3 Statement Model'!J$74 -> 0.087259321 | K53: ='3 Statement Model'!K54/'3 Statement Model'!K$74 -> 0.089354886 | ... S53: ='3 Statement Model'!S54/'3 Statement Model'!S$74 -> 0.11355995
B54: Capital work-in-progress | D54: ='3 Statement Model'!D55/'3 Statement Model'!D$74 -> 0.011595362 | E54: ='3 Statement Model'!E55/'3 Statement Model'!E$74 -> 0.0043557169 | F54: ='3 Statement Model'!F55/'3 Statement Model'!F$74 -> 0.0067404079 | G54: ='3 Statement Model'!G55/'3 Statement Model'!G$74 -> 0.0096458393 | H54: ='3 Statement Model'!H55/'3 Statement Model'!H$74 -> 0.0059291201 | I54: ='3 Statement Model'!I55/'3 Statement Model'!I$74 -> 0.0047973135 | J54: ='3 Statement Model'!J55/'3 Statement Model'!J$74 -> 0.0044726182 | K54: ='3 Statement Model'!K55/'3 Statement Model'!K$74 -> 0.0041440157 | ... S54: ='3 Statement Model'!S55/'3 Statement Model'!S$74 -> 0.0023834232
B55: Right of use assets | D55: ='3 Statement Model'!D56/'3 Statement Model'!D$74 -> 0.029188325 | E55: ='3 Statement Model'!E56/'3 Statement Model'!E$74 -> 0.032667877 | F55: ='3 Statement Model'!F56/'3 Statement Model'!F$74 -> 0.030763913 | G55: ='3 Statement Model'!G56/'3 Statement Model'!G$74 -> 0.025194356 | H55: ='3 Statement Model'!H56/'3 Statement Model'!H$74 -> 0.02816332 | I55: ='3 Statement Model'!I56/'3 Statement Model'!I$74 -> 0.027584553 | J55: ='3 Statement Model'!J56/'3 Statement Model'!J$74 -> 0.019791335 | K55: ='3 Statement Model'!K56/'3 Statement Model'!K$74 -> 0.012846449 | ... S55: ='3 Statement Model'!S56/'3 Statement Model'!S$74 -> 0
B56: Investment Property | D56: ='3 Statement Model'!D57/'3 Statement Model'!D$74 -> 0.0033986405 | E56: ='3 Statement Model'!E57/'3 Statement Model'!E$74 -> 0.0030852995 | F56: ='3 Statement Model'!F57/'3 Statement Model'!F$74 -> 0.0038022814 | G56: ='3 Statement Model'!G57/'3 Statement Model'!G$74 -> 0.002303484 | H56: ='3 Statement Model'!H57/'3 Statement Model'!H$74 -> 0.0020212909 | I56: ='3 Statement Model'!I57/'3 Statement Model'!I$74 -> 0.0017989926 | J56: ='3 Statement Model'!J57/'3 Statement Model'!J$74 -> 0.0016772318 | K56: ='3 Statement Model'!K57/'3 Statement Model'!K$74 -> 0.0015540059 | ... S56: ='3 Statement Model'!S57/'3 Statement Model'!S$74 -> 0.00089378369
B57: Goodwill | D57: ='3 Statement Model'!D58/'3 Statement Model'!D$74 -> 0.10755698 | E57: ='3 Statement Model'!E58/'3 Statement Model'!E$74 -> 0.11125227 | F57: ='3 Statement Model'!F58/'3 Statement Model'!F$74 -> 0.11303146 | G57: ='3 Statement Model'!G58/'3 Statement Model'!G$74 -> 0.1241002 | H57: ='3 Statement Model'!H58/'3 Statement Model'!H$74 -> 0.1162916 | I57: ='3 Statement Model'!I58/'3 Statement Model'!I$74 -> 0.10278244 | J57: ='3 Statement Model'!J58/'3 Statement Model'!J$74 -> 0.095825845 | K57: ='3 Statement Model'!K58/'3 Statement Model'!K$74 -> 0.088785536 | ... S57: ='3 Statement Model'!S58/'3 Statement Model'!S$74 -> 0.051064842
B58: Intangible Assets | D58: ='3 Statement Model'!D59/'3 Statement Model'!D$74 -> 0.013994402 | E58: ='3 Statement Model'!E59/'3 Statement Model'!E$74 -> 0.041742287 | F58: ='3 Statement Model'!F59/'3 Statement Model'!F$74 -> 0.052886277 | G58: ='3 Statement Model'!G59/'3 Statement Model'!G$74 -> 0.080621941 | H58: ='3 Statement Model'!H59/'3 Statement Model'!H$74 -> 0.12626331 | I58: ='3 Statement Model'!I59/'3 Statement Model'!I$74 -> 0.11345646 | J58: ='3 Statement Model'!J59/'3 Statement Model'!J$74 -> 0.10454745 | K58: ='3 Statement Model'!K59/'3 Statement Model'!K$74 -> 0.095726763 | ... S58: ='3 Statement Model'!S59/'3 Statement Model'!S$74 -> 0.049813544
B59: Non Current Financial Assets | D59: ='3 Statement Model'!D60/'3 Statement Model'!D$74 -> 0.021391443 | E59: ='3 Statement Model'!E60/'3 Statement Model'!E$74 -> 0.049183303 | F59: ='3 Statement Model'!F60/'3 Statement Model'!F$74 -> 0.035948842 | G59: ='3 Statement Model'!G60/'3 Statement Model'!G$74 -> 0.079758134 | H59: ='3 Statement Model'!H60/'3 Statement Model'!H$74 -> 0.06023447 | I59: ='3 Statement Model'!I60/'3 Statement Model'!I$74 -> 0.02914368 | J59: ='3 Statement Model'!J60/'3 Statement Model'!J$74 -> 0.027171155 | K59: ='3 Statement Model'!K60/'3 Statement Model'!K$74 -> 0.025174895 | ... S59: ='3 Statement Model'!S60/'3 Statement Model'!S$74 -> 0.014479296
B60: Other Non Current assets | D60: ='3 Statement Model'!D61/'3 Statement Model'!D$74 -> 0.0051979208 | E60: ='3 Statement Model'!E61/'3 Statement Model'!E$74 -> 0.0047186933 | F60: ='3 Statement Model'!F61/'3 Statement Model'!F$74 -> 0.0051849291 | G60: ='3 Statement Model'!G61/'3 Statement Model'!G$74 -> 0.0066225166 | H60: ='3 Statement Model'!H61/'3 Statement Model'!H$74 -> 0.0053901091 | I60: ='3 Statement Model'!I61/'3 Statement Model'!I$74 -> 0.005876709 | J60: ='3 Statement Model'!J61/'3 Statement Model'!J$74 -> 0.0054789573 | K60: ='3 Statement Model'!K61/'3 Statement Model'!K$74 -> 0.0050764192 | ... S60: ='3 Statement Model'!S61/'3 Statement Model'!S$74 -> 0.0029196934
B61: Non current tax assets (net) | D61: ='3 Statement Model'!D62/'3 Statement Model'!D$74 -> 0.0089964014 | E61: ='3 Statement Model'!E62/'3 Statement Model'!E$74 -> 0.0099818512 | F61: ='3 Statement Model'!F62/'3 Statement Model'!F$74 -> 0.0098513654 | G61: ='3 Statement Model'!G62/'3 Statement Model'!G$74 -> 0.0096458393 | H61: ='3 Statement Model'!H62/'3 Statement Model'!H$74 -> 0.012801509 | I61: ='3 Statement Model'!I62/'3 Statement Model'!I$74 -> 0.012952746 | J61: ='3 Statement Model'!J62/'3 Statement Model'!J$74 -> 0.012076069 | K61: ='3 Statement Model'!K62/'3 Statement Model'!K$74 -> 0.011188842 | ... S61: ='3 Statement Model'!S62/'3 Statement Model'!S$74 -> 0.0064352426
B62: Deferred Assets | D62: ='3 Statement Model'!D63/'3 Statement Model'!D$74 -> 0.031787285 | E62: ='3 Statement Model'!E63/'3 Statement Model'!E$74 -> 0.033756806 | F62: ='3 Statement Model'!F63/'3 Statement Model'!F$74 -> 0.032319392 | G62: ='3 Statement Model'!G63/'3 Statement Model'!G$74 -> 0.021019292 | H62: ='3 Statement Model'!H63/'3 Statement Model'!H$74 -> 0.0091631856 | I62: ='3 Statement Model'!I63/'3 Statement Model'!I$74 -> 0.0068361717 | J62: ='3 Statement Model'!J63/'3 Statement Model'!J$74 -> 0.0063734809 | K62: ='3 Statement Model'!K63/'3 Statement Model'!K$74 -> 0.0059052224 | ... S62: ='3 Statement Model'!S63/'3 Statement Model'!S$74 -> 0.003396378
B63: Total Non Current Assets | D63: ='3 Statement Model'!D64/'3 Statement Model'!D$74 -> 0.36385446 | E63: ='3 Statement Model'!E64/'3 Statement Model'!E$74 -> 0.39455535 | F63: ='3 Statement Model'!F64/'3 Statement Model'!F$74 -> 0.39422745 | G63: ='3 Statement Model'!G64/'3 Statement Model'!G$74 -> 0.45004319 | H63: ='3 Statement Model'!H64/'3 Statement Model'!H$74 -> 0.46058483 | I63: ='3 Statement Model'!I64/'3 Statement Model'!I$74 -> 0.39038139 | J63: ='3 Statement Model'!J64/'3 Statement Model'!J$74 -> 0.36467346 | K63: ='3 Statement Model'!K64/'3 Statement Model'!K$74 -> 0.33975703 | ... S63: ='3 Statement Model'!S64/'3 Statement Model'!S$74 -> 0.24494615
B65: Current Assets
B66: Cash | D66: ='3 Statement Model'!D67/'3 Statement Model'!D$74 -> 0.018592563 | E66: ='3 Statement Model'!E67/'3 Statement Model'!E$74 -> 0.019782214 | F66: ='3 Statement Model'!F67/'3 Statement Model'!F$74 -> 0.047701348 | G66: ='3 Statement Model'!G67/'3 Statement Model'!G$74 -> 0.029801325 | H66: ='3 Statement Model'!H67/'3 Statement Model'!H$74 -> 0.030723622 | I66: ='3 Statement Model'!I67/'3 Statement Model'!I$74 -> 0.038498441 | J66: ='3 Statement Model'!J67/'3 Statement Model'!J$74 -> 0.043058651 | K66: ='3 Statement Model'!K67/'3 Statement Model'!K$74 -> 0.043784741 | ... S66: ='3 Statement Model'!S67/'3 Statement Model'!S$74 -> 0.064844459
B67: Bank | D67: ='3 Statement Model'!D68/'3 Statement Model'!D$74 -> 0.037185126 | E67: ='3 Statement Model'!E68/'3 Statement Model'!E$74 -> 0.15154265 | F67: ='3 Statement Model'!F68/'3 Statement Model'!F$74 -> 0.052367784 | G67: ='3 Statement Model'!G68/'3 Statement Model'!G$74 -> 0.079038295 | H67: ='3 Statement Model'!H68/'3 Statement Model'!H$74 -> 0.096348201 | I67: ='3 Statement Model'!I68/'3 Statement Model'!I$74 -> 0.054689374 | J67: ='3 Statement Model'!J68/'3 Statement Model'!J$74 -> 0.050987847 | K67: ='3 Statement Model'!K68/'3 Statement Model'!K$74 -> 0.047241779 | ... S67: ='3 Statement Model'!S68/'3 Statement Model'!S$74 -> 0.027171024
B68: Inventory | D68: ='3 Statement Model'!D69/'3 Statement Model'!D$74 -> 0.27588964 | E68: ='3 Statement Model'!E69/'3 Statement Model'!E$74 -> 0.20435572 | F68: ='3 Statement Model'!F69/'3 Statement Model'!F$74 -> 0.24403733 | G68: ='3 Statement Model'!G69/'3 Statement Model'!G$74 -> 0.1763605 | H68: ='3 Statement Model'!H69/'3 Statement Model'!H$74 -> 0.18002965 | I68: ='3 Statement Model'!I69/'3 Statement Model'!I$74 -> 0.14811705 | J68: ='3 Statement Model'!J69/'3 Statement Model'!J$74 -> 0.17777891 | K68: ='3 Statement Model'!K69/'3 Statement Model'!K$74 -> 0.18695439 | ... S68: ='3 Statement Model'!S69/'3 Statement Model'!S$74 -> 0.22962368
B69: Debtors | D69: ='3 Statement Model'!D70/'3 Statement Model'!D$74 -> 0.1077569 | E69: ='3 Statement Model'!E70/'3 Statement Model'!E$74 -> 0.070417423 | F69: ='3 Statement Model'!F70/'3 Statement Model'!F$74 -> 0.11268579 | G69: ='3 Statement Model'!G70/'3 Statement Model'!G$74 -> 0.14612727 | H69: ='3 Statement Model'!H70/'3 Statement Model'!H$74 -> 0.14405067 | I69: ='3 Statement Model'!I70/'3 Statement Model'!I$74 -> 0.15243464 | J69: ='3 Statement Model'!J70/'3 Statement Model'!J$74 -> 0.17021385 | K69: ='3 Statement Model'!K70/'3 Statement Model'!K$74 -> 0.17899888 | ... S69: ='3 Statement Model'!S70/'3 Statement Model'!S$74 -> 0.22388308
B70: Other Current Assets | D70: ='3 Statement Model'!D71/'3 Statement Model'!D$74 -> 0.19672131 | E70: ='3 Statement Model'!E71/'3 Statement Model'!E$74 -> 0.15934664 | F70: ='3 Statement Model'!F71/'3 Statement Model'!F$74 -> 0.1489803 | G70: ='3 Statement Model'!G71/'3 Statement Model'!G$74 -> 0.11862943 | H70: ='3 Statement Model'!H71/'3 Statement Model'!H$74 -> 0.088263037 | I70: ='3 Statement Model'!I71/'3 Statement Model'!I$74 -> 0.21587911 | J70: ='3 Statement Model'!J71/'3 Statement Model'!J$74 -> 0.19328728 | K70: ='3 Statement Model'!K71/'3 Statement Model'!K$74 -> 0.20326318 | ... S70: ='3 Statement Model'!S71/'3 Statement Model'!S$74 -> 0.2095316
B71: Total Current Assets | D71: ='3 Statement Model'!D72/'3 Statement Model'!D$74 -> 0.63614554 | E71: ='3 Statement Model'!E72/'3 Statement Model'!E$74 -> 0.60544465 | F71: ='3 Statement Model'!F72/'3 Statement Model'!F$74 -> 0.60577255 | G71: ='3 Statement Model'!G72/'3 Statement Model'!G$74 -> 0.54995681 | H71: ='3 Statement Model'!H72/'3 Statement Model'!H$74 -> 0.53941517 | I71: ='3 Statement Model'!I72/'3 Statement Model'!I$74 -> 0.60961861 | J71: ='3 Statement Model'!J72/'3 Statement Model'!J$74 -> 0.63532654 | K71: ='3 Statement Model'!K72/'3 Statement Model'!K$74 -> 0.66024297 | ... S71: ='3 Statement Model'!S72/'3 Statement Model'!S$74 -> 0.75505385
B73: Total Assets | D73: ='3 Statement Model'!D74/'3 Statement Model'!D$74 -> 1 | E73: ='3 Statement Model'!E74/'3 Statement Model'!E$74 -> 1 | F73: ='3 Statement Model'!F74/'3 Statement Model'!F$74 -> 1 | G73: ='3 Statement Model'!G74/'3 Statement Model'!G$74 -> 1 | H73: ='3 Statement Model'!H74/'3 Statement Model'!H$74 -> 1 | I73: ='3 Statement Model'!I74/'3 Statement Model'!I$74 -> 1 | J73: ='3 Statement Model'!J74/'3 Statement Model'!J$74 -> 1 | K73: ='3 Statement Model'!K74/'3 Statement Model'!K$74 -> 1 | ... S73: ='3 Statement Model'!S74/'3 Statement Model'!S$74 -> 1
D74: TRUE | E74: TRUE | F74: TRUE | G74: TRUE | H74: TRUE | I74: TRUE | J74: TRUE | K74: TRUE | L74: TRUE | M74: TRUE | N74: TRUE | O74: TRUE | P74: TRUE | Q74: TRUE | R74: TRUE | S74: TRUE
B76: EQUITY AND LIABILITIES
B78: Equity
B79: Equity share capital | D79: ='3 Statement Model'!D80/'3 Statement Model'!D$108 -> 0.025789684 | E79: ='3 Statement Model'!E80/'3 Statement Model'!E$108 -> 0.023411978 | F79: ='3 Statement Model'!F80/'3 Statement Model'!F$108 -> 0.022295195 | G79: ='3 Statement Model'!G80/'3 Statement Model'!G$108 -> 0.01857184 | H79: ='3 Statement Model'!H80/'3 Statement Model'!H$108 -> 0.017383102 | I79: ='3 Statement Model'!I80/'3 Statement Model'!I$108 -> 0.015471336 | J79: ='3 Statement Model'!J80/'3 Statement Model'!J$108 -> 0.014424194 | K79: ='3 Statement Model'!K80/'3 Statement Model'!K$108 -> 0.013364451 | ... S79: ='3 Statement Model'!S80/'3 Statement Model'!S$108 -> 0.0076865397
B80: Other equity | D80: ='3 Statement Model'!D81/'3 Statement Model'!D$108 -> 0.57856857 | E80: ='3 Statement Model'!E81/'3 Statement Model'!E$108 -> 0.5646098 | F80: ='3 Statement Model'!F81/'3 Statement Model'!F$108 -> 0.5563429 | G80: ='3 Statement Model'!G81/'3 Statement Model'!G$108 -> 0.52836165 | H80: ='3 Statement Model'!H81/'3 Statement Model'!H$108 -> 0.49898935 | I80: ='3 Statement Model'!I81/'3 Statement Model'!I$108 -> 0.46126169 | J80: ='3 Statement Model'!J81/'3 Statement Model'!J$108 -> 0.46397167 | K80: ='3 Statement Model'!K81/'3 Statement Model'!K$108 -> 0.46567103 | ... S80: ='3 Statement Model'!S81/'3 Statement Model'!S$108 -> 0.52748033
B81: Total Shareholder's Equity | D81: ='3 Statement Model'!D82/'3 Statement Model'!D$108 -> 0.60435826 | E81: ='3 Statement Model'!E82/'3 Statement Model'!E$108 -> 0.58802178 | F81: ='3 Statement Model'!F82/'3 Statement Model'!F$108 -> 0.57863809 | G81: ='3 Statement Model'!G82/'3 Statement Model'!G$108 -> 0.54693349 | H81: ='3 Statement Model'!H82/'3 Statement Model'!H$108 -> 0.51637246 | I81: ='3 Statement Model'!I82/'3 Statement Model'!I$108 -> 0.47673303 | J81: ='3 Statement Model'!J82/'3 Statement Model'!J$108 -> 0.47839586 | K81: ='3 Statement Model'!K82/'3 Statement Model'!K$108 -> 0.47903548 | ... S81: ='3 Statement Model'!S82/'3 Statement Model'!S$108 -> 0.53516687
B82: Minority Interest | D82: ='3 Statement Model'!D83/'3 Statement Model'!D$108 -> 0.0025989604 | E82: ='3 Statement Model'!E83/'3 Statement Model'!E$108 -> 0.0032667877 | F82: ='3 Statement Model'!F83/'3 Statement Model'!F$108 -> 0.0098513654 | G82: ='3 Statement Model'!G83/'3 Statement Model'!G$108 -> 0.022602937 | H82: ='3 Statement Model'!H83/'3 Statement Model'!H$108 -> 0.04541167 | I82: ='3 Statement Model'!I83/'3 Statement Model'!I$108 -> 0.034900456 | J82: ='3 Statement Model'!J83/'3 Statement Model'!J$108 -> 0.032538297 | K82: ='3 Statement Model'!K83/'3 Statement Model'!K$108 -> 0.030147714 | ... S82: ='3 Statement Model'!S83/'3 Statement Model'!S$108 -> 0.017339404
B83: Total equity | D83: ='3 Statement Model'!D84/'3 Statement Model'!D$108 -> 0.60695722 | E83: ='3 Statement Model'!E84/'3 Statement Model'!E$108 -> 0.59128857 | F83: ='3 Statement Model'!F84/'3 Statement Model'!F$108 -> 0.58848946 | G83: ='3 Statement Model'!G84/'3 Statement Model'!G$108 -> 0.56953642 | H83: ='3 Statement Model'!H84/'3 Statement Model'!H$108 -> 0.56178413 | I83: ='3 Statement Model'!I84/'3 Statement Model'!I$108 -> 0.51163349 | J83: ='3 Statement Model'!J84/'3 Statement Model'!J$108 -> 0.51093416 | K83: ='3 Statement Model'!K84/'3 Statement Model'!K$108 -> 0.5091832 | ... S83: ='3 Statement Model'!S84/'3 Statement Model'!S$108 -> 0.55250628
B85: Non-current liabilities
B87: Long Term Borrowings | D87: ='3 Statement Model'!D88/'3 Statement Model'!D$108 -> 0.0019992003 | E87: ='3 Statement Model'!E88/'3 Statement Model'!E$108 -> 0.0014519056 | F87: ='3 Statement Model'!F88/'3 Statement Model'!F$108 -> 0 | G87: ='3 Statement Model'!G88/'3 Statement Model'!G$108 -> 0.0002879355 | H87: ='3 Statement Model'!H88/'3 Statement Model'!H$108 -> 0 | I87: ='3 Statement Model'!I88/'3 Statement Model'!I$108 -> 0 | J87: ='3 Statement Model'!J88/'3 Statement Model'!J$108 -> 0 | K87: ='3 Statement Model'!K88/'3 Statement Model'!K$108 -> 0 | ... S87: ='3 Statement Model'!S88/'3 Statement Model'!S$108 -> 0
B88: Lease Liabilities | D88: ='3 Statement Model'!D89/'3 Statement Model'!D$108 -> 0 | E88: ='3 Statement Model'!E89/'3 Statement Model'!E$108 -> 0 | F88: ='3 Statement Model'!F89/'3 Statement Model'!F$108 -> 0.015727618 | G88: ='3 Statement Model'!G89/'3 Statement Model'!G$108 -> 0.013101065 | H88: ='3 Statement Model'!H89/'3 Statement Model'!H$108 -> 0.014014284 | I88: ='3 Statement Model'!I89/'3 Statement Model'!I$108 -> 0.014871672 | J88: ='3 Statement Model'!J89/'3 Statement Model'!J$108 -> 0.013865116 | K88: ='3 Statement Model'!K89/'3 Statement Model'!K$108 -> 0.012846449 | ... S88: ='3 Statement Model'!S89/'3 Statement Model'!S$108 -> 0.0073886118
B89: Other Provisions | D89: ='3 Statement Model'!D90/'3 Statement Model'!D$108 -> 0.028788485 | E89: ='3 Statement Model'!E90/'3 Statement Model'!E$108 -> 0.022141561 | F89: ='3 Statement Model'!F90/'3 Statement Model'!F$108 -> 0.00017283097 | G89: ='3 Statement Model'!G90/'3 Statement Model'!G$108 -> 0.038295422 | H89: ='3 Statement Model'!H90/'3 Statement Model'!H$108 -> 0.054574855 | I89: ='3 Statement Model'!I90/'3 Statement Model'!I$108 -> 0.14523867 | J89: ='3 Statement Model'!J90/'3 Statement Model'!J$108 -> 0.13540852 | K89: ='3 Statement Model'!K90/'3 Statement Model'!K$108 -> 0.12546008 | ... S89: ='3 Statement Model'!S90/'3 Statement Model'!S$108 -> 0.072158137
B90: Others Financial Liabilities - Long-term | D90: ='3 Statement Model'!D91/'3 Statement Model'!D$108 -> 0 | E90: ='3 Statement Model'!E91/'3 Statement Model'!E$108 -> 0.0001814882 | F90: ='3 Statement Model'!F91/'3 Statement Model'!F$108 -> 0 | G90: ='3 Statement Model'!G91/'3 Statement Model'!G$108 -> 0.000575871 | H90: ='3 Statement Model'!H91/'3 Statement Model'!H$108 -> 0.00013475273 | I90: ='3 Statement Model'!I91/'3 Statement Model'!I$108 -> 0.00011993284 | J90: ='3 Statement Model'!J91/'3 Statement Model'!J$108 -> 0.00011181545 | K90: ='3 Statement Model'!K91/'3 Statement Model'!K$108 -> 0.00010360039 | ... S90: ='3 Statement Model'!S91/'3 Statement Model'!S$108 -> 5.9585579e-05
B91: Employee benefit obligations (net) | D91: ='3 Statement Model'!D92/'3 Statement Model'!D$108 -> 0.0041983207 | E91: ='3 Statement Model'!E92/'3 Statement Model'!E$108 -> 0.0043557169 | F91: ='3 Statement Model'!F92/'3 Statement Model'!F$108 -> 0.0046664362 | G91: ='3 Statement Model'!G92/'3 Statement Model'!G$108 -> 0.002879355 | H91: ='3 Statement Model'!H92/'3 Statement Model'!H$108 -> 0.0025603018 | I91: ='3 Statement Model'!I92/'3 Statement Model'!I$108 -> 0.0032381866 | J91: ='3 Statement Model'!J92/'3 Statement Model'!J$108 -> 0.0030190173 | K91: ='3 Statement Model'!K92/'3 Statement Model'!K$108 -> 0.0027972106 | ... S91: ='3 Statement Model'!S92/'3 Statement Model'!S$108 -> 0.0016088106
B92: Deferred Tax Liabilities (Net) | D92: ='3 Statement Model'!D93/'3 Statement Model'!D$108 -> 0.0011995202 | E92: ='3 Statement Model'!E93/'3 Statement Model'!E$108 -> 0.015245009 | F92: ='3 Statement Model'!F93/'3 Statement Model'!F$108 -> 0.018838576 | G92: ='3 Statement Model'!G93/'3 Statement Model'!G$108 -> 0.02562626 | H92: ='3 Statement Model'!H93/'3 Statement Model'!H$108 -> 0.037596011 | I92: ='3 Statement Model'!I93/'3 Statement Model'!I$108 -> 0.029743344 | J92: ='3 Statement Model'!J93/'3 Statement Model'!J$108 -> 0.027730233 | K92: ='3 Statement Model'!K93/'3 Statement Model'!K$108 -> 0.025692897 | ... S92: ='3 Statement Model'!S93/'3 Statement Model'!S$108 -> 0.014777224
B93: Total non-current liabilities | D93: ='3 Statement Model'!D94/'3 Statement Model'!D$108 -> 0.036185526 | E93: ='3 Statement Model'!E94/'3 Statement Model'!E$108 -> 0.043375681 | F93: ='3 Statement Model'!F94/'3 Statement Model'!F$108 -> 0.039405461 | G93: ='3 Statement Model'!G94/'3 Statement Model'!G$108 -> 0.080765908 | H93: ='3 Statement Model'!H94/'3 Statement Model'!H$108 -> 0.1088802 | I93: ='3 Statement Model'!I94/'3 Statement Model'!I$108 -> 0.1932118 | J93: ='3 Statement Model'!J94/'3 Statement Model'!J$108 -> 0.1801347 | K93: ='3 Statement Model'!K94/'3 Statement Model'!K$108 -> 0.16690023 | ... S93: ='3 Statement Model'!S94/'3 Statement Model'!S$108 -> 0.095992368
B95: Current Liabilities
B97: Trade Payables | D97: ='3 Statement Model'!D98/'3 Statement Model'!D$108 -> 0.19552179 | E97: ='3 Statement Model'!E98/'3 Statement Model'!E$108 -> 0.20580762 | F97: ='3 Statement Model'!F98/'3 Statement Model'!F$108 -> 0.23228483 | G97: ='3 Statement Model'!G98/'3 Statement Model'!G$108 -> 0.20904117 | H97: ='3 Statement Model'!H98/'3 Statement Model'!H$108 -> 0.21304406 | I97: ='3 Statement Model'!I98/'3 Statement Model'!I$108 -> 0.16346846 | J97: ='3 Statement Model'!J98/'3 Statement Model'!J$108 -> 0.17331089 | K97: ='3 Statement Model'!K98/'3 Statement Model'!K$108 -> 0.1913527 | ... S97: ='3 Statement Model'!S98/'3 Statement Model'!S$108 -> 0.25627642
B98: Short Term Borrowings | D98: ='3 Statement Model'!D99/'3 Statement Model'!D$108 -> 0.06497401 | E98: ='3 Statement Model'!E99/'3 Statement Model'!E$108 -> 0.061705989 | F98: ='3 Statement Model'!F99/'3 Statement Model'!F$108 -> 0.059626685 | G98: ='3 Statement Model'!G99/'3 Statement Model'!G$108 -> 0.068096746 | H98: ='3 Statement Model'!H99/'3 Statement Model'!H$108 -> 0.051610295 | I98: ='3 Statement Model'!I99/'3 Statement Model'!I$108 -> 0.045454545 | J98: ='3 Statement Model'!J99/'3 Statement Model'!J$108 -> 0.055224937 | K98: ='3 Statement Model'!K99/'3 Statement Model'!K$108 -> 0.058075193 | ... S98: ='3 Statement Model'!S99/'3 Statement Model'!S$108 -> 0.052382901
B99: Lease Liabilities | D99: ='3 Statement Model'!D100/'3 Statement Model'!D$108 -> 0 | E99: ='3 Statement Model'!E100/'3 Statement Model'!E$108 -> 0 | F99: ='3 Statement Model'!F100/'3 Statement Model'!F$108 -> 0.0074317318 | G99: ='3 Statement Model'!G100/'3 Statement Model'!G$108 -> 0.0060466456 | H99: ='3 Statement Model'!H100/'3 Statement Model'!H$108 -> 0.0055248619 | I99: ='3 Statement Model'!I100/'3 Statement Model'!I$108 -> 0.0061165747 | J99: ='3 Statement Model'!J100/'3 Statement Model'!J$108 -> 0.0057025882 | K99: ='3 Statement Model'!K100/'3 Statement Model'!K$108 -> 0.00528362 | ... S99: ='3 Statement Model'!S100/'3 Statement Model'!S$108 -> 0.0030388646
B100: Others Financial Liabilities - Short-term | D100: ='3 Statement Model'!D101/'3 Statement Model'!D$108 -> 0.015793683 | E100: ='3 Statement Model'!E101/'3 Statement Model'!E$108 -> 0.014882033 | F100: ='3 Statement Model'!F101/'3 Statement Model'!F$108 -> 0.0077773937 | G100: ='3 Statement Model'!G101/'3 Statement Model'!G$108 -> 0.00575871 | H100: ='3 Statement Model'!H101/'3 Statement Model'!H$108 -> 0.007950411 | I100: ='3 Statement Model'!I101/'3 Statement Model'!I$108 -> 0.027704485 | J100: ='3 Statement Model'!J101/'3 Statement Model'!J$108 -> 0.02582937 | K100: ='3 Statement Model'!K101/'3 Statement Model'!K$108 -> 0.023931691 | ... S100: ='3 Statement Model'!S101/'3 Statement Model'!S$108 -> 0.013764269
B101: Other Current Liabilities | D101: ='3 Statement Model'!D102/'3 Statement Model'!D$108 -> 0.043382647 | E101: ='3 Statement Model'!E102/'3 Statement Model'!E$108 -> 0.052087114 | F101: ='3 Statement Model'!F102/'3 Statement Model'!F$108 -> 0.038714138 | G101: ='3 Statement Model'!G102/'3 Statement Model'!G$108 -> 0.031241002 | H101: ='3 Statement Model'!H102/'3 Statement Model'!H$108 -> 0.028432826 | I101: ='3 Statement Model'!I102/'3 Statement Model'!I$108 -> 0.027824418 | J101: ='3 Statement Model'!J102/'3 Statement Model'!J$108 -> 0.025941185 | K101: ='3 Statement Model'!K102/'3 Statement Model'!K$108 -> 0.024035291 | ... S101: ='3 Statement Model'!S102/'3 Statement Model'!S$108 -> 0.013823854
B102: Provisions | D102: ='3 Statement Model'!D103/'3 Statement Model'!D$108 -> 0.011595362 | E102: ='3 Statement Model'!E103/'3 Statement Model'!E$108 -> 0.0036297641 | F102: ='3 Statement Model'!F103/'3 Statement Model'!F$108 -> 0.0036294504 | G102: ='3 Statement Model'!G103/'3 Statement Model'!G$108 -> 0.0063345811 | H102: ='3 Statement Model'!H103/'3 Statement Model'!H$108 -> 0.0009432691 | I102: ='3 Statement Model'!I103/'3 Statement Model'!I$108 -> 0.0025185896 | J102: ='3 Statement Model'!J103/'3 Statement Model'!J$108 -> 0.0023481245 | K102: ='3 Statement Model'!K103/'3 Statement Model'!K$108 -> 0.0021756082 | ... S102: ='3 Statement Model'!S103/'3 Statement Model'!S$108 -> 0.0012512972
B103: Employee benefit obligations (net) | D103: ='3 Statement Model'!D104/'3 Statement Model'!D$108 -> 0.010795682 | E103: ='3 Statement Model'!E104/'3 Statement Model'!E$108 -> 0.01415608 | F103: ='3 Statement Model'!F104/'3 Statement Model'!F$108 -> 0.011061182 | G103: ='3 Statement Model'!G104/'3 Statement Model'!G$108 -> 0.010653614 | H103: ='3 Statement Model'!H104/'3 Statement Model'!H$108 -> 0.010645466 | I103: ='3 Statement Model'!I104/'3 Statement Model'!I$108 -> 0.011033821 | J103: ='3 Statement Model'!J104/'3 Statement Model'!J$108 -> 0.010287022 | K103: ='3 Statement Model'!K104/'3 Statement Model'!K$108 -> 0.0095312361 | ... S103: ='3 Statement Model'!S104/'3 Statement Model'!S$108 -> 0.0054818733
B104: Current Tax Liabilities - Short-term | D104: ='3 Statement Model'!D105/'3 Statement Model'!D$108 -> 0.014794082 | E104: ='3 Statement Model'!E105/'3 Statement Model'!E$108 -> 0.013067151 | F104: ='3 Statement Model'!F105/'3 Statement Model'!F$108 -> 0.011579675 | G104: ='3 Statement Model'!G105/'3 Statement Model'!G$108 -> 0.012525194 | H104: ='3 Statement Model'!H105/'3 Statement Model'!H$108 -> 0.011184476 | I104: ='3 Statement Model'!I105/'3 Statement Model'!I$108 -> 0.011033821 | J104: ='3 Statement Model'!J105/'3 Statement Model'!J$108 -> 0.010287022 | K104: ='3 Statement Model'!K105/'3 Statement Model'!K$108 -> 0.0095312361 | ... S104: ='3 Statement Model'!S105/'3 Statement Model'!S$108 -> 0.0054818733
B105: Total Current Liabilites | D105: ='3 Statement Model'!D106/'3 Statement Model'!D$108 -> 0.35685726 | E105: ='3 Statement Model'!E106/'3 Statement Model'!E$108 -> 0.36533575 | F105: ='3 Statement Model'!F106/'3 Statement Model'!F$108 -> 0.37210508 | G105: ='3 Statement Model'!G106/'3 Statement Model'!G$108 -> 0.34969767 | H105: ='3 Statement Model'!H106/'3 Statement Model'!H$108 -> 0.32933567 | I105: ='3 Statement Model'!I106/'3 Statement Model'!I$108 -> 0.29515471 | J105: ='3 Statement Model'!J106/'3 Statement Model'!J$108 -> 0.30893114 | K105: ='3 Statement Model'!K106/'3 Statement Model'!K$108 -> 0.32391657 | ... S105: ='3 Statement Model'!S106/'3 Statement Model'!S$108 -> 0.35150136
B107: Total Equity and Liabilites | D107: ='3 Statement Model'!D108/'3 Statement Model'!D$108 -> 1 | E107: ='3 Statement Model'!E108/'3 Statement Model'!E$108 -> 1 | F107: ='3 Statement Model'!F108/'3 Statement Model'!F$108 -> 1 | G107: ='3 Statement Model'!G108/'3 Statement Model'!G$108 -> 1 | H107: ='3 Statement Model'!H108/'3 Statement Model'!H$108 -> 1 | I107: ='3 Statement Model'!I108/'3 Statement Model'!I$108 -> 1 | J107: ='3 Statement Model'!J108/'3 Statement Model'!J$108 -> 1 | K107: ='3 Statement Model'!K108/'3 Statement Model'!K$108 -> 1 | ... S107: ='3 Statement Model'!S108/'3 Statement Model'!S$108 -> 1
D108: TRUE | E108: TRUE | F108: TRUE | G108: TRUE | H108: TRUE | I108: TRUE | J108: TRUE | K108: TRUE | L108: TRUE | M108: TRUE | N108: TRUE | O108: TRUE | P108: TRUE | Q108: TRUE | R108: TRUE | S108: TRUE
B109: Net Working Capital | D109: 1397 | E109: 1323 | F109: 1352 | G109: 1391 | H109: 1559 | I109: 2622 | J109: 2919.2134 | K109: 3246.6986 | L109: 3511.4771 | M109: 3842.7006 | N109: 4175.7059 | O109: 4175.7059 | P109: 4175.7059 | Q109: 4175.7059 | R109: 4175.7059 | S109: 4175.7059
B110: Debtors Days | D110: 0 | E110: 21.021061 | F110: 19.953743 | G110: 31.158081 | H110: 39.400186 | I110: 39.428492 | J110: 45 | K110: 45 | L110: 42 | M110: 42 | N110: 40 | O110: 40 | P110: 40 | Q110: 40 | R110: 40 | S110: 40
B111: Inventory Days | D111: 0 | E111: 56.827162 | F111: 48.694807 | G111: 49.288458 | H111: 48.418367 | I111: 43.320792 | J111: 47 | K111: 47 | L111: 46 | M111: 46 | N111: 46 | O111: 46 | P111: 46 | Q111: 46 | R111: 46 | S111: 46
B112: Trade Payable Days | D112: 0 | E112: 90.266979 | F112: 83.192605 | G112: 95.359746 | H112: 116.58014 | I112: 99.717892 | J112: 105 | K112: 105 | L112: 105 | M112: 102 | N112: 102 | O112: 102 | P112: 102 | Q112: 102 | R112: 102 | S112: 102

Sheet DCF Val
B2: ='Input Sheet'!C5 -> Marico Ltd | R2: Mid Year Convention
B3: Common Size Statement | R3: Yes
J4: Current Case | R4: No
E8: Actual | K8: Explicit Forecast Period | P8: Maturity Period
B9: In INR crores unless started otherwise | E9: ='3 Statement Model'!D9 -> 2020 | F9: ='3 Statement Model'!E9 -> 2021 | G9: ='3 Statement Model'!F9 -> 2022 | H9: ='3 Statement Model'!G9 -> 2023 | I9: ='3 Statement Model'!H9 -> 2024 | J9: ='3 Statement Model'!I9 -> 2025 | K9: ='3 Statement Model'!J9 -> 2026 | L9: ='3 Statement Model'!K9 -> 2027 | ... T9: ='3 Statement Model'!S9 -> 2035
A11: # | B11: Free Cash Flow to Firm
B13: EBITDA | E13: ='3 Statement Model'!D25 -> 1440 | F13: ='3 Statement Model'!E25 -> 1602 | G13: ='3 Statement Model'!F25 -> 1681 | H13: ='3 Statement Model'!G25 -> 1810 | I13: ='3 Statement Model'!H25 -> 2026 | J13: ='3 Statement Model'!I25 -> 2139 | K13: ='3 Statement Model'!J25 -> 2086.7005 | L13: ='3 Statement Model'!K25 -> 2368.405 | ... T13: ='3 Statement Model'!S25 -> 6646.1506
B14: Less: Depreciation & Amortization | E14: ='3 Statement Model'!D29*-1 -> -140 | F14: ='3 Statement Model'!E29*-1 -> -139 | G14: ='3 Statement Model'!F29*-1 -> -139 | H14: ='3 Statement Model'!G29*-1 -> -155 | I14: ='3 Statement Model'!H29*-1 -> -158 | J14: ='3 Statement Model'!I29*-1 -> -178 | K14: ='3 Statement Model'!J29*-1 -> -191.1705 | L14: ='3 Statement Model'!K29*-1 -> -206.11901 | ... T14: ='3 Statement Model'!S29*-1 -> -351.53241
B15: EBIT | E15: =SUM(E13:E14) -> 1300 | F15: =SUM(F13:F14) -> 1463 | G15: =SUM(G13:G14) -> 1542 | H15: =SUM(H13:H14) -> 1655 | I15: =SUM(I13:I14) -> 1868 | J15: =SUM(J13:J14) -> 1961 | K15: =SUM(K13:K14) -> 1895.53 | L15: =SUM(L13:L14) -> 2162.286 | ... T15: =SUM(T13:T14) -> 6294.6181
B16: Less: Tax | E16: ='3 Statement Model'!D38*-1 -> -331 | F16: ='3 Statement Model'!E38*-1 -> -324 | G16: ='3 Statement Model'!F38*-1 -> -346 | H16: ='3 Statement Model'!G38*-1 -> -421 | I16: ='3 Statement Model'!H38*-1 -> -435 | J16: ='3 Statement Model'!I38*-1 -> -458 | K16: ='3 Statement Model'!J38*-1 -> -508.97747 | L16: ='3 Statement Model'!K38*-1 -> -579.4168 | ... T16: ='3 Statement Model'!S38*-1 -> -1687.5835
B17: EBIT (1-T) | E17: =SUM(E15:E16) -> 969 | F17: =SUM(F15:F16) -> 1139 | G17: =SUM(G15:G16) -> 1196 | H17: =SUM(H15:H16) -> 1234 | I17: =SUM(I15:I16) -> 1433 | J17: =SUM(J15:J16) -> 1503 | K17: =SUM(K15:K16) -> 1386.5525 | L17: =SUM(L15:L16) -> 1582.8692 | ... T17: =SUM(T15:T16) -> 4607.0346
B18: Add: Depreciation & Amortization | E18: =E14*-1 -> 140 | F18: =F14*-1 -> 139 | G18: =G14*-1 -> 139 | H18: =H14*-1 -> 155 | I18: =I14*-1 -> 158 | J18: =J14*-1 -> 178 | K18: =K14*-1 -> 191.1705 | L18: =L14*-1 -> 206.11901 | ... T18: =T14*-1 -> 351.53241
B19: Cash NOPAT | E19: =SUM(E17:E18) -> 1109 | F19: =SUM(F17:F18) -> 1278 | G19: =SUM(G17:G18) -> 1335 | H19: =SUM(H17:H18) -> 1389 | I19: =SUM(I17:I18) -> 1591 | J19: =SUM(J17:J18) -> 1681 | K19: =SUM(K17:K18) -> 1577.723 | L19: =SUM(L17:L18) -> 1788.9882 | ... T19: =SUM(T17:T18) -> 4958.567
B20: Less: Reinvestment
B21: Change in Working Capital | E21: ='3 Statement Model'!D121 -> 33 | F21: ='3 Statement Model'!E121 -> 730 | G21: ='3 Statement Model'!F121 -> -342 | H21: ='3 Statement Model'!G121 -> -59 | I21: ='3 Statement Model'!H121 -> -226 | J21: ='3 Statement Model'!I121 -> -293 | K21: ='3 Statement Model'!J121 -> -347.86124 | L21: ='3 Statement Model'!K121 -> -356.45842 | ... T21: ='3 Statement Model'!S121 -> -697.00463
B22: Capex During the Year | E22: ='3 Statement Model'!D125 -> -186 | F22: ='3 Statement Model'!E125 -> -137 | G22: ='3 Statement Model'!F125 -> -129 | H22: ='3 Statement Model'!G125 -> -157 | I22: ='3 Statement Model'!H125 -> -135 | J22: ='3 Statement Model'!I125 -> -122 | K22: ='3 Statement Model'!J125 -> -197.55744 | L22: ='3 Statement Model'!K125 -> -224.22769 | ... T22: ='3 Statement Model'!S125 -> -439.56022
B23: Free Cash Flow to Firm | E23: =E19+SUM(E21:E22) -> 956 | F23: =F19+SUM(F21:F22) -> 1871 | G23: =G19+SUM(G21:G22) -> 864 | H23: =H19+SUM(H21:H22) -> 1173 | I23: =I19+SUM(I21:I22) -> 1230 | J23: =J19+SUM(J21:J22) -> 1266 | K23: =K19+SUM(K21:K22) -> 1032.3043 | L23: =L19+SUM(L21:L22) -> 1208.3021 | ... T23: =T19+SUM(T21:T22) -> 3822.0022
B25: Discount Period (Year) | C25: Mid Year ? | D25: Yes | K25: =IF(D25="Yes",(K9-J9)/2,K9-J9) -> 0.5 | L25: =K25+1 -> 1.5 | M25: =L25+1 -> 2.5 | N25: =M25+1 -> 3.5 | O25: =N25+1 -> 4.5 | P25: =O25+1 -> 5.5 | Q25: =P25+1 -> 6.5 | R25: =Q25+1 -> 7.5 | S25: =R25+1 -> 8.5 | T25: =S25+1 -> 9.5
B26: Discount Rate (WACC) | C26: =WACC!E24 -> 0.1
B27: Present Value Factor | K27: =1/(1+$C$26)^K25 -> 0.95346259 | L27: =1/(1+$C$26)^L25 -> 0.86678417 | M27: =1/(1+$C$26)^M25 -> 0.78798561 | N27: =1/(1+$C$26)^N25 -> 0.71635056 | O27: =1/(1+$C$26)^O25 -> 0.65122778 | P27: =1/(1+$C$26)^P25 -> 0.59202525 | Q27: =1/(1+$C$26)^Q25 -> 0.53820477 | R27: =1/(1+$C$26)^R25 -> 0.48927707 | ... T27: =1/(1+$C$26)^T25 -> 0.40436121
B29: Present Value of Free Cash Flow to Firm | K29: =K23*K27 -> 984.26353 | L29: =L23*L27 -> 1047.3371 | M29: =M23*M27 -> 1284.6014 | N29: =N23*N27 -> 1356.9101 | O29: =O23*O27 -> 1393.519 | P29: =P23*P27 -> 1493.4336 | Q29: =Q23*Q27 -> 1475.9734 | R29: =R23*R27 -> 1509.4004 | ... T29: =T23*T27 -> 1545.4694
A32: # | B32: DCF Calculation - Perpetuity Growth
B34: Perpetuity Growth | C34: =WACC!E7 -> 0.043490142
B35: Terminal Year FCFF x (1+PGR) | C35: =T23*(1+C34) -> 3988.2216
B36: Terminal Value | C36: =C35/(C26-C34) -> 70575.678
B37: Present Value of Terminal Value | C37: =C36*T27 -> 28538.067
B38: Present Value of FCFFs | C38: =SUM(K29:T29) -> 13607.172
B39: Enterprise Value | C39: =SUM(C37:C38) -> 42145.239
B40: Implied Exit Multiple | C40: =C39/T13 -> 6.3413007
B41: Implied EV/EBITDA | C41: =C39/'3 Statement Model'!I25 -> 19.703244
B42: Less: Debt | C42: =SUM('3 Statement Model'!I99,'3 Statement Model'!I88)*-1 -> -379
B43: Add: Cash | C43: ='3 Statement Model'!I67 -> 321
B44: Less: Minority Interest | C44: ='3 Statement Model'!I83*-1 -> -291
B45: Add: Non Operating Asset | C45: ='3 Statement Model'!I60 -> 243
B46: Equity Value | C46: =SUM(C39,C42:C45) -> 42039.239
B47: Less: Equity Options | C47: ='Option Value'!E28*-1 -> -26.005868
B48: Equity Value for shareholder | C48: =SUM(C46:C47) -> 42013.233
A50: # | B50: DCF Calculation - Exit Multiple
B52: Exit Multiple | C52: 36
B53: Terminal Year EBITDA | C53: =T13 -> 6646.1506
B54: Terminal Value | C54: =C53*C52 -> 239261.42
B55: Present Value of Terminal Value | C55: =C54*T27 -> 96748.038
B56: Present Value of FCFFs | C56: =SUM(K29:T29) -> 13607.172
B57: Enterprise Value | C57: =SUM(C55:C56) -> 110355.21
B58: Implied Exit Multiple | C58: =C57/T13 -> 16.60438
B59: Implied EV/EBITDA | C59: =C57/'3 Statement Model'!I25 -> 51.591964
B60: Less: Debt | C60: =C42 -> -379
B61: Add: Cash | C61: =C43 -> 321
B62: Less: Minority Interest | C62: =C44 -> -291
B63: Add: Non Operating Asset | C63: =C45 -> 243
B64: Equity Value | C64: =SUM(C57,C60:C63) -> 110249.21
B65: Less: Equity Options | C65: =C47 -> -26.005868
B66: Equity Value for shareholder | C66: =SUM(C64:C65) -> 110223.2
A69: # | B69: Sensitivity Analysis
E71: Perpetuity Growth Rate
D72: =C48 -> 42013.233 | E72: 0.03 | F72: =WACC!E7 -> 0.043490142 | G72: 0.05 | H72: 0.06 | I72: 0.07 | J72: 0.08
C73: WACC | D73: 0.09 | E73: 43098.095 | F73: 51979.588 | G73: 58408.422 | H73: 73718.748 | I73: 104339.4 | J73: 196201.36
D74: 0.1 | E74: 36215.645 | F74: 42013.233 | G74: 45930.024 | H74: 54430.106 | I74: 68596.909 | J74: 96930.516
D75: 0.11 | E75: 31093.186 | F75: 35084.226 | G75: 37652.136 | H75: 42899.297 | I75: 50770.038 | J75: 63887.939
D76: 0.12 | E76: 27141.474 | F76: 29999.028 | G76: 31771.967 | H76: 35244.836 | I76: 40106.853 | J76: 47399.879
D77: 0.13 | E77: 24007.164 | F77: 26116.157 | G77: 27388.312 | H77: 29803.417 | I77: 33023.558 | J77: 37531.755
D78: 0.14 | E78: 21465.559 | F78: 23060.159 | G78: 24000.655 | H78: 25743.534 | I78: 27984.378 | J78: 30972.171
E83: Exit Multiple
D84: =C66 -> 110223.2 | E84: 0.09 | F84: 0.1 | G84: 0.11 | H84: 0.12 | I84: 0.13 | J84: 0.14
C85: WACC | D85: 34 | E85: 113817.59 | F85: 104848.31 | G85: 96680.185 | H85: 89234.799 | I85: 82442.055 | J85: 76239.209
D86: 35 | E86: 116748.6 | F86: 107535.76 | G86: 99146.235 | H86: 91499.438 | I86: 84523.308 | J86: 78153.35
D87: 36 | E87: 119679.62 | F87: 110223.2 | G87: 101612.28 | H87: 93764.076 | I87: 86604.561 | J87: 80067.492
D88: 37 | E88: 122610.64 | F88: 112910.65 | G88: 104078.33 | H88: 96028.715 | I88: 88685.815 | J88: 81981.634
D89: 38 | E89: 125541.66 | F89: 115598.1 | G89: 106544.38 | H89: 98293.354 | I89: 90767.068 | J89: 83895.775
D90: 39 | E90: 128472.67 | F90: 118285.54 | G90: 109010.43 | H90: 100557.99 | I90: 92848.322 | J90: 85809.917

Sheet Option Value
B2: Valuing Options or Warrants
B3: Enter the current stock price = | E3: 730
B4: Enter the strike price on the option = | E4: 456 | M4: Tranche | N4: Grant date | O4: No of Option Granted | P4: Exercise price | Q4: Avg Maturity | R4: Avg Expected volatility | S4: AvgDividend yield (%
B5: Enter the expiration of the option = | E5: 3.9
B6: Enter the standard deviation in stock prices = | E6: 0.245 | F6: (volatility) | M6: Scheme XII | N6: 44651 | O6: 26630 | P6: 357.65 | Q6: 3.9 | R6: 0.2453 | S6: 0.019
B7: Enter the annualized dividend yield on stock = | E7: 0.019 | M7: Scheme XII | N7: 44895 | O7: 78570 | P7: 346 | Q7: 3.9 | R7: 0.2453 | S7: 0.019
B8: Enter the Risk Free rate = | E8: =WACC!E7 -> 0.043490142 | M8: Scheme XIII | N8: 44895 | O8: 43150 | P8: 372.1 | Q8: 3.9 | R8: 0.2453 | S8: 0.019
B9: Enter the number of options outstanding = | E9: 0.08464833 | M9: Scheme XIV | N9: 45016 | O9: 115100 | P9: 330.38 | Q9: 3.9 | R9: 0.2453 | S9: 0.019
B10: Enter the number of shares outstanding = | E10: 130 | M10: Scheme XV | N10: 45260 | O10: 808 | P10: 1 | Q10: 3.9 | R10: 0.2453 | S10: 0.019
M11: Scheme XVI | N11: 45260 | O11: 291355 | P11: 420 | Q11: 3.9 | R11: 0.2453 | S11: 0.019
B12: Do not input any numbers below this line | M12: Scheme XVIII | N12: 45382 | O12: 297940 | P12: 451.56 | Q12: 3.9 | R12: 0.2453 | S12: 0.019
B13: VALUING OPTIONS WHEN THERE IS DILUTION | M13: Scheme XIX | N13: 45626 | O13: 19862 | P13: 1 | Q13: 3.9 | R13: 0.2453 | S13: 0.019
B14: Stock Price= | D14: =E3 -> 730 | E14: # Warrants issued= | G14: =E9 -> 0.08464833 | M14: Scheme XX | N14: 45626 | O14: 553837 | P14: 525 | Q14: 3.9 | R14: 0.2453 | S14: 0.019
B15: Strike Price= | D15: =E4 -> 456 | E15: # Shares outstanding= | G15: =E10 -> 130 | M15: Scheme XXII | N15: 45382 | O15: 270634 | P15: 520 | Q15: 3.9 | R15: 0.2453 | S15: 0.019
B16: Adjusted S = | D16: =(D14*G15+D27*G14)/(G15+G14) -> 729.72489 | E16: T.Bond rate= | G16: =E8 -> 0.043490142 | M16: Scheme XXIV | N16: 45382 | O16: 575837 | P16: 520.96 | Q16: 3.9 | R16: 0.2453 | S16: 0.019
B17: Adjusted K = | D17: =D15 -> 456 | E17: Variance= | G17: =E6^2 -> 0.060025 | M17: Scheme XXV | N17: 45747 | O17: 21898 | P17: 1 | Q17: 3.9 | R17: 0.2453 | S17: 0.019
B18: Expiration (in years) = | D18: =E5 -> 3.9 | E18: Annualized dividend yield= | G18: =E7 -> 0.019 | M18: Scheme XXVI | N18: 45991 | O18: 51541 | P18: 1 | Q18: 3.9 | R18: 0.2453 | S18: 0.019
E19: Div. Adj. interest rate= | G19: =G16-G18 -> 0.024490142 | M19: Scheme XXVII | N19: 45991 | O19: 588740 | P19: 500 | Q19: 3.9 | R19: 0.2453 | S19: 0.019
M20: Scheme XXVIII | N20: 45747 | O20: 12604 | P20: 1 | Q20: 3.9 | R20: 0.2453 | S20: 0.019
B21: d1 = | C21: =(LN(D16/D17)+(G19+(G17/2))*D18)/(((G17)^(0.5))*(D18^0.5)) -> 1.4110872 | D21: =(D19*G20+D32*G19)/(G20+G19) -> 0 | M21: Scheme XXIX | N21: 45747 | O21: 176516 | P21: 498.25 | Q21: 3.9 | R21: 0.2453 | S21: 0.019
B22: N (d1) = | C22: =NORMSDIST(C21) -> 0.92089054 | M22: Scheme XXX | N22: 45747 | O22: 220893 | P22: 1 | Q22: 3.9 | R22: 0.2453 | S22: 0.019
M23: Scheme XXXI | N23: 45747 | O23: 958478 | P23: 483.5 | Q23: 3.9 | R23: 0.2453 | S23: 0.019
B24: d2 = | C24: =C21-((G17^0.5)*(D18^(0.5))) -> 0.92725093 | M24: Scheme XXXII | N24: 46112 | O24: 21867 | P24: 1 | Q24: 3.9 | R24: 0.2453 | S24: 0.019
B25: N (d2) = | C25: =NORMSDIST(C24) -> 0.82310187 | M25: Scheme XXXIII | N25: 46112 | O25: 196560 | P25: 483.5 | Q25: 3.9 | R25: 0.2453 | S25: 0.019
M26: Scheme XXXIV | N26: 46356 | O26: 83324 | P26: 1 | Q26: 3.9 | R26: 0.2453 | S26: 0.019
B27: Value per option = | D27: =((EXP((0-G18)*D18))*D16*C22-D17*(EXP((0-G16)*D18))*C25) -> 307.22246 | M27: Scheme XXXV | N27: 46356 | O27: 851767 | P27: 527.68 | Q27: 3.9 | R27: 0.2453 | S27: 0.019
B28: Value of all options outstanding = | E28: =D27*E9 -> 26.005868 | M28: Scheme XXXVII | N28: 45747 | O28: 12600 | P28: 1 | Q28: 3.9 | R28: 0.2453 | S28: 0.019
M29: Scheme XXXVIII | N29: 45747 | O29: 264361 | P29: 530 | Q29: 3.9 | R29: 0.2453 | S29: 0.019
M30: Scheme XXXIX | N30: 45992 | O30: 118782 | P30: 1 | Q30: 3.9 | R30: 0.2453 | S30: 0.019
M31: Scheme XXXIX | N31: 45992 | O31: 889760 | P31: 506.17 | Q31: 3.9 | R31: 0.2453 | S31: 0.019
M32: Scheme XL | N32: 46357 | O32: 237327 | P32: 300 | Q32: 3.9 | R32: 0.2453 | S32: 0.019
M33: Scheme XLI | N33: 46356 | O33: 1967686 | P33: 500 | Q33: 3.9 | R33: 0.2453 | S33: 0.019
M34: Scheme XLII | N34: 46112 | O34: 67163 | P34: 1 | Q34: 3.9 | R34: 0.2453 | S34: 0.019
O36: Weighted Average | P36: =SUMPRODUCT(P6:P34,$O$6:$O$34)/SUM($O$6:$O$34) -> 456.49539 | Q36: =SUMPRODUCT(Q6:Q34,$O$6:$O$34)/SUM($O$6:$O$34) -> 3.9 | R36: =SUMPRODUCT(R6:R34,$O$6:$O$34)/SUM($O$6:$O$34) -> 0.2453 | S36: =SUMPRODUCT(S6:S34,$O$6:$O$34)/SUM($O$6:$O$34) -> 0.019

Sheet Client Data >

Sheet P&l 25-24
B3: Particulars | D3: 43525 | E3: 43891 | F3: 44256 | G3: 44621 | H3: 44986 | I3: 45382 | J3: 45717
B5: Revenue | K5: -1
B6: Revenue from operations | D6: 7334 | E6: 7315 | F6: 8048 | G6: 9512 | H6: 9764 | I6: 9653 | J6: 10831
B8: Revenue Growth YoY % | D8: =D6/6322-1 -> 0.16007593 | E8: =E6/D6-1 -> -0.0025906736 | F8: =F6/E6-1 -> 0.10020506 | G8: =G6/F6-1 -> 0.18190855 | H8: =H6/G6-1 -> 0.026492851 | I8: =I6/H6-1 -> -0.011368292 | J8: =J6/I6-1 -> 0.1220346
B10: Expenses
B12: Cost of Goods Sold
B13: Cost of materials consumed | D13: -3995 | E13: -3428 | F13: -3884 | G13: -5061 | H13: -4649 | I13: -3941 | J13: -4572
B14: Purchases of stock-in-trade | D14: -145 | E14: -177 | F14: -339 | G14: -491 | H14: -541 | I14: -752 | J14: -960
B15: Changes in inventories | D15: 123 | E15: -140 | F15: -47 | G15: 116 | H15: -161 | I15: -55 | J15: 144
B16: Total Cost of Goods Sold | D16: =SUM(D13:D15) -> -4017 | E16: =SUM(E13:E15) -> -3745 | F16: =SUM(F13:F15) -> -4270 | G16: =SUM(G13:G15) -> -5436 | H16: =SUM(H13:H15) -> -5351 | I16: =SUM(I13:I15) -> -4748 | J16: =SUM(J13:J15) -> -5388
B18: Gross Profit | D18: =D6+D16 -> 3317 | E18: =E6+E16 -> 3570 | F18: =F6+F16 -> 3778 | G18: =G6+G16 -> 4076 | H18: =H6+H16 -> 4413 | I18: =I6+I16 -> 4905 | J18: =J6+J16 -> 5443
B20: Cost of materials consumed % of COGS | D20: =-D13/D16 -> -0.99452328 | E20: =-E13/E16 -> -0.91535381 | F20: =-F13/F16 -> -0.90960187 | G20: =-G13/G16 -> -0.93101545 | H20: =-H13/H16 -> -0.86880957 | I20: =-I13/I16 -> -0.8300337 | J20: =-J13/J16 -> -0.84855234
B21: Cost of materials consumed % Sales | D21: =-D13/D6 -> 0.54472321 | E21: =-E13/E6 -> 0.46862611 | F21: =-F13/F6 -> 0.48260437 | G21: =-G13/G6 -> 0.53206476 | H21: =-H13/H6 -> 0.47613683 | I21: =-I13/I6 -> 0.40826686 | J21: =-J13/J6 -> 0.42212169
B22: COGS % Sales | D22: =-D16/D6 -> 0.54772293 | E22: =-E16/E6 -> 0.51196172 | F22: =-F16/F6 -> 0.5305666 | G22: =-G16/G6 -> 0.57148865 | H22: =-H16/H6 -> 0.54803359 | I22: =-I16/I6 -> 0.49186781 | J22: =-J16/J6 -> 0.49746099
B23: Gross Margin | D23: =1-D22 -> 0.45227707 | E23: =1-E22 -> 0.48803828 | F23: =1-F22 -> 0.4694334 | G23: =1-G22 -> 0.42851135 | H23: =1-H22 -> 0.45196641 | I23: =1-I22 -> 0.50813219 | J23: =1-J22 -> 0.50253901
B25: Cost of materials consumed % Sales | D25: =-D13/D6 -> 0.54472321 | E25: =-E13/E6 -> 0.46862611 | F25: =-F13/F6 -> 0.48260437 | G25: =-G13/G6 -> 0.53206476 | H25: =-H13/H6 -> 0.47613683 | I25: =-I13/I6 -> 0.40826686 | J25: =-J13/J6 -> 0.42212169
B26: Purchases of stock-in-trade % Sales | D26: =-D14/D6 -> 0.01977093 | E26: =-E14/E6 -> 0.024196856 | F26: =-F14/F6 -> 0.042122266 | G26: =-G14/G6 -> 0.051619008 | H26: =-H14/H6 -> 0.05540762 | I26: =-I14/I6 -> 0.077903243 | J26: =-J14/J6 -> 0.088634475
B27: Changes in inventories % Sales | D27: =D15/D6 -> 0.016771203 | E27: =-E15/E6 -> 0.019138756 | F27: =-F15/F6 -> 0.0058399602 | G27: =G15/G6 -> 0.012195122 | H27: =-H15/H6 -> 0.016489144 | I27: =-I15/I6 -> 0.0056977106 | J27: =J15/J6 -> 0.013295171
B29: SG&A Expenses (Excluding Depreciation & Intereset)
B30: Employee benefit expense | D30: -466 | E30: -478 | F30: -570 | G30: -586 | H30: -653 | I30: -743 | J30: -831
B31: Other expenses | D31: -1526 | E31: -1652 | F31: -1606 | G31: -1809 | H31: -1950 | I31: -2136 | J31: -2473
B32: Total SG&A Expenses | D32: =SUM(D30:D31) -> -1992 | E32: =SUM(E30:E31) -> -2130 | F32: =SUM(F30:F31) -> -2176 | G32: =SUM(G30:G31) -> -2395 | H32: =SUM(H30:H31) -> -2603 | I32: =SUM(I30:I31) -> -2879 | J32: =SUM(J30:J31) -> -3304
B34: Earnings Before Interest, Taxes, Depreciation, and Amortization (EBITDA) | D34: =D18+D32 -> 1325 | E34: =E18+E32 -> 1440 | F34: =F18+F32 -> 1602 | G34: =G18+G32 -> 1681 | H34: =H18+H32 -> 1810 | I34: =I18+I32 -> 2026 | J34: =J18+J32 -> 2139
B36: Less: Depreciation and amortization expense | D36: -131 | E36: -140 | F36: -139 | G36: -139 | H36: -155 | I36: -158 | J36: -178
B37: Earnings Before Interest and Taxes (EBIT) | D37: =D34+D36 -> 1194 | E37: =E34+E36 -> 1300 | F37: =F34+F36 -> 1463 | G37: =G34+G36 -> 1542 | H37: =H34+H36 -> 1655 | I37: =I34+I36 -> 1868 | J37: =J34+J36 -> 1961
B39: Less: Finance costs | D39: -40 | E39: -50 | F39: -34 | G39: -39 | H39: -56 | I39: -73 | J39: -53
B40: Add: Other Income | D40: 103 | E40: 124 | F40: 94 | G40: 98 | H40: 144 | I40: 142 | J40: 208
B42: Profit Before Tax | D42: =D37+D39+D40 -> 1257 | E42: =E37+E39+E40 -> 1374 | F42: =F37+F39+F40 -> 1523 | G42: =G37+G39+G40 -> 1601 | H42: =H37+H39+H40 -> 1743 | I42: =I37+I39+I40 -> 1937 | J42: =J37+J39+J40 -> 2116
B44: Less: Tax Expenses | D44: -126 | E44: -331 | F44: -324 | G44: -346 | H44: -421 | I44: -435 | J44: -458
B45: Profit After Tax | D45: =SUM(D42:D44) -> 1131 | E45: =SUM(E42:E44) -> 1043 | F45: =SUM(F42:F44) -> 1199 | G45: =SUM(G42:G44) -> 1255 | H45: =SUM(H42:H44) -> 1322 | I45: =SUM(I42:I44) -> 1502 | J45: =SUM(J42:J44) -> 1658

Sheet Balance Sheet
B1: Balance sheet
B2: Particulars | C2: 43525 | D2: 43891 | E2: 44256 | F2: 44621 | G2: 45016 | H2: 45352 | I2: 45717
B4: ASSETS
B5: Non-current assets
B7: Fixed Asset | C7: =SUM(C8:C13) -> 1370 | D7: =SUM(D8:D13) -> 1483 | E7: =SUM(E8:E13) -> 1636 | F7: =SUM(F8:F13) -> 1799 | G7: =SUM(G8:G13) -> 2313 | H7: =SUM(H8:H13) -> 2768 | I7: =SUM(I8:I13) -> 2798
B8: Property plant and equipment | C8: 572 | D8: 654 | E8: 572 | F8: 600 | G8: 633 | H8: 700 | I8: 710
B9: Capital work-in-progress | C9: 45 | D9: 58 | E9: 24 | F9: 39 | G9: 67 | H9: 44 | I9: 40
B10: Right of use assets | C10: 153 | D10: 146 | E10: 180 | F10: 178 | G10: 175 | H10: 209 | I10: 230
B11: Investment property | C11: 17 | D11: 17 | E11: 17 | F11: 22 | G11: 16 | H11: 15 | I11: 15
B12: Goodwill | C12: 503 | D12: 538 | E12: 613 | F12: 654 | G12: 862 | H12: 863 | I12: 857
B13: Other intangible assets | C13: 80 | D13: 70 | E13: 230 | F13: 306 | G13: 560 | H13: 937 | I13: 946
B15: Financial assets | C15: =SUM(C16:C18) -> 63 | D15: =SUM(D16:D18) -> 107 | E15: =SUM(E16:E18) -> 271 | F15: =SUM(F16:F18) -> 208 | G15: =SUM(G16:G18) -> 554 | H15: =SUM(H16:H18) -> 447 | I15: =SUM(I16:I18) -> 243
B16: (i) Investments | C16: 34 | D16: 76 | E16: 226 | F16: 187 | G16: 518 | H16: 343 | I16: 215
B17: (ii) Loans | C17: 18 | D17: 20 | E17: 18 | F17: 4 | G17: 4 | H17: 4 | I17: 6
B18: (iii) Other financial assets | C18: 11 | D18: 11 | E18: 27 | F18: 17 | G18: 32 | H18: 100 | I18: 22
B20: Deferred tax assets (net) | C20: 202 | D20: 159 | E20: 186 | F20: 187 | G20: 146 | H20: 68 | I20: 57
B21: Non current tax assets (net) | C21: 39 | D21: 45 | E21: 55 | F21: 57 | G21: 67 | H21: 95 | I21: 108
B22: Other non-current assets | C22: 35 | D22: 26 | E22: 26 | F22: 30 | G22: 46 | H22: 40 | I22: 49
B23: Total non-current assets | C23: =SUM(C20:C22,C15,C7) -> 1709 | D23: =SUM(D20:D22,D15,D7) -> 1820 | E23: =SUM(E20:E22,E15,E7) -> 2174 | F23: =SUM(F20:F22,F15,F7) -> 2281 | G23: =SUM(G20:G22,G15,G7) -> 3126 | H23: =SUM(H20:H22,H15,H7) -> 3418 | I23: =SUM(I20:I22,I15,I7) -> 3255
B25: Current assets
B26: Inventories | C26: 1411 | D26: 1380 | E26: 1126 | F26: 1412 | G26: 1225 | H26: 1336 | I26: 1235
B27: Trade receivables | C27: 517 | D27: 539 | E27: 388 | F27: 652 | G27: 1015 | H27: 1069 | I27: 1271
B29: Other Cureest Asset | C29: =SUM(C30:C35) -> 720 | D29: =SUM(D30:D35) -> 984 | E29: =SUM(E30:E35) -> 878 | F29: =SUM(F30:F35) -> 862 | G29: =SUM(G30:G35) -> 824 | H29: =SUM(H30:H35) -> 655 | I29: =SUM(I30:I35) -> 1800
B30: Investments | C30: 391 | D30: 628 | E30: 628 | F30: 641 | G30: 578 | H30: 259 | I30: 1375
B31: Other current assets | C31: 308 | D31: 340 | E31: 224 | F31: 213 | G31: 229 | H31: 378 | I31: 413
B32: Assets classified as held for sale | C32: 12 | D32: 8 | E32: 14 | F32: 0 | G32: 7 | H32: 5
B33: Current tax asset (net) | C33: 0 | D33: 0 | E33: 1 | F33: 1 | G33: 2 | H33: 2 | I33: 2
B34: Loans | C34: 5 | D34: 5 | E34: 6 | F34: 5 | G34: 4 | H34: 6 | I34: 7
B35: Other financial assets | C35: 4 | D35: 3 | E35: 5 | F35: 2 | G35: 4 | H35: 5 | I35: 3
B37: Cash and cash equivalents | C37: 48 | D37: 93 | E37: 109 | F37: 276 | G37: 207 | H37: 228 | I37: 321
B38: Bank balances | C38: 504 | D38: 186 | E38: 835 | F38: 303 | G38: 549 | H38: 715 | I38: 456
B40: Total current assets | C40: =SUM(C26:C29,C37,C38) -> 3200 | D40: =SUM(D26:D29,D37,D38) -> 3182 | E40: =SUM(E26:E29,E37,E38) -> 3336 | F40: =SUM(F26:F29,F37,F38) -> 3505 | G40: =SUM(G26:G29,G37,G38) -> 3820 | H40: =SUM(H26:H29,H37,H38) -> 4003 | I40: =SUM(I26:I29,I37,I38) -> 5083
B42: Total Assets | C42: =SUM(C40+C23) -> 4909 | D42: =SUM(D40+D23) -> 5002 | E42: =SUM(E40+E23) -> 5510 | F42: =SUM(F40+F23) -> 5786 | G42: =SUM(G40+G23) -> 6946 | H42: =SUM(H40+H23) -> 7421 | I42: =SUM(I40+I23) -> 8338
B44: EQUITY AND LIABILITIES
B45: Equity
B46: Equity share capital | C46: 129 | D46: 129 | E46: 129 | F46: 129 | G46: 129 | H46: 129 | I46: 129
B47: Other equity
